Workbook

Sheet README
A1: CORSA Jakarta Flagship – Financial Model v0.2
A2: Preliminary – most inputs are placeholders to be validated.
A4: Note from Jonas | B4: I created this Financial model to give me a general overview of all the components to take into account. I'm using it to. However, even if most data are sourced, I'm currently working on checking all the numbers and data, and verify the accuracy of the finidngs. Many data need to be discussed with the Pillar 1 team, and I'm waiting for their inputs to adjust the model.
A6: Purpose | B6: Test whether a 120–180 m² CORSA flagship in Jakarta works commercially, what it costs, whether CHF 200k is enough and which assumptions matter most.
A7: How to use | B7: 1) Pick scenario in Inputs!D4. 2) Edit blue cells only (Inputs, Rent_Data, Menu, Staffing, CAPEX unit costs, Revenue dwell times). 3) Read Dashboard, Scenarios, Sensitivity, MonteCarlo.
A8: Colour code | B8: Blue text = hard-coded input · Black = formula · Green = link to another sheet · Yellow fill = key assumption · Light-green fill = key output.
A9: Currency | B9: Model runs in IDR; CHF shown at the Inputs FX rate. Menu prices are NET of the 10% restaurant tax (PBJT), which is passed through to guests.
A10: Sheet map | B10: Dashboard → Inputs → Rent_Data → Location → Menu → Revenue → Staffing → OPEX → CAPEX → Funding → Scenarios → PnL_Monthly → Annual → Sensitivity → MonteCarlo → Sources → Research_Tracker → Methods
A11: Scenario logic | B11: Conservative = fewer guests, lower spend, higher costs/rent, longer ramp-up. Optimistic = the reverse. Scenarios sheet calculates all three in parallel (steady state); PnL_Monthly runs the active one month by month.
A12: Biggest early finding | B12: Foreign-owned PT PMA rules (IDR 2.5bn paid-up ≈ CHF 115k, IDR 10bn investment plan ≈ CHF 460k per KBLI) may matter more for the CHF 200k question than the CAPEX itself – verify with a lawyer.
A13: Status | B13: v0.2 – structure complete, numbers indicative, every input traced to a source or marked as an assumption. See Research_Tracker for what to validate before 22 Oct.
A14: Sources (v0.2) | B14: Added 8 Oct 2026: 32 new sources (S46–S77) and a source trail on every sheet – per-row columns in Inputs (I, K, L), Staffing (K–M), CAPEX (K–M), Menu (O–Q), and a 'Sources & calculation basis' table at the bottom of every other sheet (MonteCarlo: top right).
A15: v0.6 (16 Oct 2026) | B15: CAPEX (Rent) completed: per-item financing route (buy / finance lease / rental / sponsor), BFI-based lease maths, provider directory, Buy-vs-Lease summary; new switch Inputs!H4 (1 = Buy, 2 = Lease) feeds Funding, PnL, Scenarios, Annual, Dashboard. Sources S83–S104.

Sheet Dashboard
A1: CORSA Jakarta Flagship – Dashboard
A2: Live outputs for the ACTIVE scenario (change it in Inputs!D4). All figures are preliminary estimates.
A3: Not from Jonas: | B3: This sheet will make more sense once many more data will be confirmed and scenario tested
B4: But the KPIs are relevant in my opinion
A5: Active scenario | B5: =Inputs!$E$4 -> Base
A6: CAPEX mode | B6: =Inputs!$I$4 -> Lease – CAPEX (Rent)
A7: Key question (brief) | B7: IDR | C7: CHF
A8: Total investment requirement | B8: =CHOOSE(Inputs!$H$4,'CAPEX (Buy)'!$H$37,'CAPEX (Rent)'!$H$40) -> 4.2662461e+09 | C8: =B8/Inputs!$H$10 -> 197511.39
A9: Founder equity | B9: =Funding!$B$8 -> 4320000000 | C9: =B9/Inputs!$H$10 -> 200000
A10: Funding gap (+) / surplus (−) | B10: =Funding!$B$9 -> -53753870 | C10: =B10/Inputs!$H$10 -> -2488.6051
A11: Bank loan needed | B11: =Funding!$B$10 -> 0 | C11: =B11/Inputs!$H$10 -> 0
A12: Mature monthly revenue (year-1 prices) | B12: =Scenarios!$F$13 -> 735630000 | C12: =B12/Inputs!$H$10 -> 34056.944
A13: Steady-state monthly EBITDA | B13: =Scenarios!$F$34 -> 1.3478627e+08 | C13: =B13/Inputs!$H$10 -> 6240.1051
A14: Break-even revenue per trading day | B14: =Scenarios!$F$43 -> 16761712 | C14: =B14/Inputs!$H$10 -> 776.00518
A15: Year-1 revenue (with ramp-up) | B15: =Annual!$C$5 -> 7295392080 | C15: =B15/Inputs!$H$10 -> 337749.63
A16: Year-1 EBITDA | B16: =Annual!$C$11 -> 7.3026459e+08 | C16: =B16/Inputs!$H$10 -> 33808.546
A17: Year-3 EBITDA | B17: =Annual!$E$11 -> 0 | C17: =B17/Inputs!$H$10 -> 0
A18: Lowest cash balance over 60 months | B18: =MIN(PnL_Monthly!$C$49:$BJ$49) -> 7.9481373e+08 | C18: =B18/Inputs!$H$10 -> 36796.932
A19: NPV of 5-year project cash flows | B19: =Annual!$C$31 -> -3.185886e+09 | C19: =B19/Inputs!$H$10 -> -147494.72
A20: Break-even guests per day | B20: =Scenarios!$F$45 -> 136.71312
A21: Mature guests per day (model) | B21: =Scenarios!$F$6 -> 200
A22: EBITDA margin at maturity | B22: =Scenarios!$F$35 -> 0.18322563
A23: Prime cost % (COGS + staff) | B23: =Scenarios!$F$39 -> 0.51941666
A24: Occupancy cost % (rent + SC) | B24: =Scenarios!$F$40 -> 0.051349481
A25: Payback month (full model, incl. ramp-up) | B25: =IF(MIN(PnL_Monthly!$C$53:$BJ$53)=0,"> 60 months",MIN(PnL_Monthly!$C$53:$BJ$53)) -> > 60 months
A26: Project IRR (5 yrs incl. terminal value) | B26: =Annual!$C$30 -> -0.46909486
A27: PT PMA paid-up capital check | B27: =Funding!$B$23 -> OK – equity covers paid-up capital
A28: Seats | B28: =Revenue!$C$5 -> 60
A29: Equipment lease/rental/sponsor payments per month (months 1–36) | B29: =IF(Inputs!$H$4=2,'CAPEX (Rent)'!$H$47,0) -> 18483150 | C29: =B29/Inputs!$H$10 -> 855.70137
B30: Scenario comparison (steady state) | C30: Conservative | D30: Base | E30: Optimistic
A31: Revenue / month (IDR) | B31: =Scenarios!$C$13 -> 481770000 | C31: =Scenarios!$D$13 -> 735630000 | D31: =Scenarios!$E$13 -> 1083805000
A32: EBITDA / month (IDR) | B32: =Scenarios!$C$34 -> -1.0789767e+08 | C32: =Scenarios!$D$34 -> 1.3478627e+08 | D32: =Scenarios!$E$34 -> 4.116417e+08
A33: EBITDA margin | B33: =Scenarios!$C$35 -> -0.22396096 | C33: =Scenarios!$D$35 -> 0.18322563 | D33: =Scenarios!$E$35 -> 0.37981159
A34: Break-even revenue / day (IDR) | B34: =Scenarios!$C$43 -> 22950907 | C34: =Scenarios!$D$43 -> 16761712 | D34: =Scenarios!$E$43 -> 14180295
A35: Break-even guests / day | B35: =Scenarios!$C$45 -> 221.52005 | C35: =Scenarios!$D$45 -> 136.71312 | D35: =Scenarios!$E$45 -> 100.09112
A36: Total investment (CHF) | B36: =Scenarios!$C$54 -> 314583.94 | C36: =Scenarios!$D$54 -> 197511.39 | D36: =Scenarios!$E$54 -> 159628.48
A37: Gap vs CHF 200k equity (CHF) | B37: =Scenarios!$C$55 -> 114583.94 | C37: =Scenarios!$D$55 -> -2488.6051 | D37: =Scenarios!$E$55 -> -40371.523
A38: Simple payback (years) | B38: =Scenarios!$C$56 -> never | C38: =Scenarios!$D$56 -> 3.3816169 | D38: =Scenarios!$E$56 -> 0.93217547
A40: MODEL CHECKS
A41: Scenario engine = CAPEX sheet | B41: =Scenarios!$F$58 -> OK
A42: Scenario engine = Revenue sheet | B42: =Scenarios!$F$59 -> OK
A43: Cash never negative | B43: =IF(MIN(PnL_Monthly!$C$49:$BJ$49)>=0,"OK","Cash goes negative – increase WC reserve / funding") -> OK
A44: Additional equity required | B44: =IF(Funding!$B$11>0,"Need "&TEXT(Funding!$C$11,"#,##0")&" CHF more","OK") -> OK
A45: Staff salaries ≥ UMP | B45: =IF(COUNTIF(Staffing!$E$6:$E$14,"Below UMP!")>0,"Some roles below UMP","OK") -> OK
A46: Capacity | B46: =Revenue!$E$26 -> OK – demand fits seat capacity
A47: Menu vs revenue spend | B47: =Menu!$I$30 -> OK
A48: Seasonality average ≈ 1.00 | B48: =IF(ABS(AVERAGE(Inputs!$H$92:$H$103)-1)<0.02,"OK","Average "&TEXT(AVERAGE(Inputs!$H$92:$H$103),"0.00")) -> OK
A51: SOURCES & CALCULATION BASIS – Dashboard
A52: Figure / cells | B52: Value used (live) | C52: Source ID(s) → Sources sheet | F52: How the figure was derived from the source | N52: Evidence status
A53: All figures on this sheet | B53: — | C53: Scenarios, PnL_Monthly, Annual, Funding, CAPEX | F53: Pure links – trace each number to its sheet, then to Inputs col I/K and the Sources sheet. | N53: Model formula
A54: Total investment & funding gap | B54: =Dashboard!B8 -> 4.2662461e+09 | C54: S10, S64–S70; Brief; S16 | F54: CAPEX total vs CHF 200k × FX. | N54: Partly sourced
A55: Mature revenue & guests/day | B55: =Dashboard!B12 -> 735630000 | C55: S46, S43, S31, S33 | F55: Weakest-evidenced block: 200 guests/day is above every measured pasta comparable (S46). | N55: Assumption – validate
A56: Break-even, EBITDA, payback, IRR, NPV | B56: =Dashboard!B13 -> 1.3478627e+08 | C56: S49–S57, S62, S63 | F56: Driven by sourced cost rates + assumed volume. | N56: Partly sourced
A57: PT PMA check | B57: =Dashboard!B27 -> OK – equity covers paid-up capital | C57: S01, S02 | F57: Equity vs IDR 2.5bn paid-up per KBLI. | N57: Sourced
A58: Check thresholds (rows 40–47) | B58: — | C58: — | F58: Model QA tolerances (85% capacity, 15% menu gap, seasonality ±2%) – team choices. | N58: Decision / policy

Sheet Inputs
A1: Inputs & Scenario Assumptions
A2: Every assumption lives here. Edit blue cells (columns E–G). Column H = active scenario. Column I = source IDs (Sources sheet), column K = how each value was calculated, column L = evidence status (green = sourced/derived, yellow = partly sourced, orange = assumption to validate).
C4: ACTIVE SCENARIO (1 = Conservative, 2 = Base, 3 = Optimistic) → | D4: 2 | E4: =CHOOSE($D$4,"Conservative","Base","Optimistic") -> Base | F4: CAPEX MODE (1 = Buy, 2 = Lease/sponsor) → | H4: 2 | I4: =CHOOSE($H$4,"Buy – CAPEX (Buy)","Lease – CAPEX (Rent)") -> Lease – CAPEX (Rent)
A5: Note from Jonas: | B5: These Inputs and scenarios have not been carefully reviewed yet. This sheet will be more relevant once other assumptions will be confirmed or infirmed
B6: Regarding the seasonality, the impact of Ramadan and seasons on the scheduling of consumptions as well as the quantity must be assessed (culture and society?)
A8: Key | B8: Category | C8: Parameter | D8: Unit | E8: Conservative | F8: Base | G8: Optimistic | H8: ACTIVE | I8: Source ID(s) & key facts (see Sources sheet) | J8: Confidence | K8: How the value was calculated from the source | L8: Evidence status
A9: GENERAL & MACRO
A10: fx | B10: Macro | C10: FX rate (IDR per 1 CHF) | D10: IDR/CHF | E10: 20500 | F10: 21600 | G10: 22500 | H10: =CHOOSE($D$4,E10,F10,G10) -> 21600 | I10: S16 (CHF/IDR spot ~21,580; 30-day avg 21,640; 90-day range 21,423–22,518) | J10: H | K10: Base 21,600 = 30-day average 21,640 rounded. Conservative 20,500 ≈ 5% below the 90-day low (weaker CHF→IDR conversion of equity). Optimistic 22,500 ≈ 90-day high 22,518. | L10: Derived from sources
A11: open_date | B11: Timing | C11: Opening month (first month of trading) | D11: date | E11: 46569 | F11: 46569 | G11: 46569 | H11: =CHOOSE($D$4,E11,F11,G11) -> 46569 | I11: S65 (PT PMA setup), S10 (fit-out); brief | J11: L | K11: Oct 2026 + ~3 months company setup/licensing (S65) + 3–4 months lease search & fit-out + buffer ≈ Jul 2027. Timeline estimate, not a sourced figure. | L11: Assumption – validate
A12: days | B12: Timing | C12: Trading days per month | D12: days | E12: 30 | F12: 30 | G12: 30 | H12: =CHOOSE($D$4,E12,F12,G12) -> 30 | I12: Team assumption (7-day operation); Ramadan/Lebaran handled by seasonality (S58) | J12: M | K12: 30 trading days per month = 7-day opening. Closure days around Idul Fitri are captured through the Mar seasonality index, not here. | L12: Assumption – validate
A13: price_inc | B13: Macro | C13: Menu price increase p.a. | D13: % | E13: 0.03 | F13: 0.04 | G13: 0.05 | H13: =CHOOSE($D$4,E13,F13,G13) -> 0.04 | I13: S18 (CPI 3.28% yoy Sep 2026; volatile food 5.03%; core 2.84%) | J13: M | K13: Base 4% sits between headline CPI 3.28% and volatile-food inflation 5.03% (menu costs track food). Conservative 3% ≈ CPI (cannot pass on food inflation). Optimistic 5% ≈ volatile-food inflation. | L13: Derived from sources
A14: infl | B14: Macro | C14: Opex inflation p.a. | D14: % | E14: 0.045 | F14: 0.035 | G14: 0.03 | H14: =CHOOSE($D$4,E14,F14,G14) -> 0.035 | I14: S18 (CPI 3.28%), S17 (BI target 2.5% ±1) | J14: M | K14: Base 3.5% = CPI 3.28% rounded up / top of BI band. Conservative 4.5% = 1 pp above band. Optimistic 3.0% = band mid-point + 0.5 pp. | L14: Derived from sources
A15: wage_g | B15: Macro | C15: Wage growth p.a. | D15: % | E15: 0.07 | F15: 0.062 | G15: 0.05 | H15: =CHOOSE($D$4,E15,F15,G15) -> 0.062 | I15: S04 (Jakarta UMP 2026 +6.17% vs 2025) | J15: M | K15: Base 6.2% = latest UMP increase 6.17%. Conservative 7%, optimistic 5% = ±1 pp around it. | L15: Derived from sources
A16: cit | B16: Tax | C16: Corporate income tax rate | D16: % | E16: 0.22 | F16: 0.22 | G16: 0.22 | H16: =CHOOSE($D$4,E16,F16,G16) -> 0.22 | I16: S15 (PT PMA not eligible for 0.5% MSME final tax); UU HPP – CIT 22% | J16: M | K16: Statutory corporate rate 22% applied to all scenarios. | L16: Sourced
A17: pbjt | B17: Tax | C17: Restaurant tax PBJT (charged on top of menu prices) | D17: % | E17: 0.1 | F17: 0.1 | G17: 0.1 | H17: =CHOOSE($D$4,E17,F17,G17) -> 0.1 | I17: S13 (Jakarta PBJT food & beverage 10%), S03 | J17: H | K17: 10% charged on top of net menu prices and passed to the government → excluded from revenue. | L17: Sourced
A18: vat | B18: Tax | C18: Non-recoverable VAT on CAPEX & services | D18: % | E18: 0.11 | F18: 0.11 | G18: 0.11 | H18: =CHOOSE($D$4,E18,F18,G18) -> 0.11 | I18: S03 (restaurants collect PBJT, not VAT → input VAT not creditable); VAT rate 11% | J18: M | K18: 11% statutory VAT on CAPEX/services treated as a cost because it cannot be reclaimed. | L18: Sourced
A19: LOCATION & SPACE
A20: district | B20: Location | C20: Selected district (1 SCBD, 2 Senopati main road, 3 Senopati side streets, 4 Kuningan, 5 Kemang, 6 PIK) | D20: # | E20: 2 | F20: 2 | G20: 2 | H20: =CHOOSE($D$4,E20,F20,G20) -> 2 | I20: Location sheet (scores from S20–S29, S46) | J20: - | K20: Decision input: 2 = Senopati main road (highest weighted score with acceptable rent). | L20: Decision / policy
A21: sqm | B21: Space | C21: Usable floor area (ground floor focus) | D21: m² | E21: 150 | F21: 150 | G21: 150 | H21: =CHOOSE($D$4,E21,F21,G21) -> 150 | I21: Brief (120–180 m², ground floor) | J21: - | K21: 150 m² = mid-point of the brief's 120–180 m² range. | L21: Decision / policy
A22: gfa_factor | B22: Space | C22: Paid surface ÷ trading surface (non-trading space you still pay for) | D22: x | E22: 1.2 | F22: 1 | G22: 1 | H22: =CHOOSE($D$4,E22,F22,G22) -> 1 | I22: Rent_Data (v0.5: listings filtered to 100–200 m² of total rented surface) | J22: L | K22: Rent_Data now holds units of 100–200 m² total surface (all floors), matching the brief's 120–180 m², so rent = rate × 150 m² with no upper-floor gross-up (base/optimistic 1.0). Conservative 1.2 = paying ~30 m² of stairs/storage/non-trading space (e.g. a 180 m² unit for 150 m² used). Team estimate. | L22: Partly sourced
A23: foh_share | B23: Space | C23: Dining area share of usable area | D23: % | E23: 0.6 | F23: 0.6 | G23: 0.6 | H23: =CHOOSE($D$4,E23,F23,G23) -> 0.6 | I23: S35 (Toast: ~60/40 dining/kitchen split) | J23: M | K23: 60% of 150 m² = 90 m² dining area. | L23: Sourced
A24: sqm_seat | B24: Space | C24: m² of dining area per seat | D24: m² | E24: 1.5 | F24: 1.5 | G24: 1.5 | H24: =CHOOSE($D$4,E24,F24,G24) -> 1.5 | I24: S35 (12–15 sq ft/seat ≈ 1.1–1.4 m²) | J24: M | K24: 1.5 m²/seat = top of the S35 range (1.4 m²) + comfort margin for a flagship → 90 m² / 1.5 = 60 seats. | L24: Derived from sources
A25: rent_sqm | B25: Rent | C25: Base rent (IDR per m² GFA per month) | D25: IDR | E25: =INDEX(Location!$E$8:$E$13,$H$20) -> 351857.87 | F25: =INDEX(Location!$D$8:$D$13,$H$20) -> 251828.12 | G25: =INDEX(Location!$C$8:$C$13,$H$20) -> 205161.38 | H25: =CHOOSE($D$4,E25,F25,G25) -> 251828.12 | I25: Location → Rent_Data (S20–S26 listings) | J25: L | K25: Linked: Optimistic = P25, Base = median, Conservative = P75 of asking rents per m² of rented surface (100–200 m² units) for the selected district. Senopati main road uses the side-street × premium fallback while it has <3 listings. | L25: Derived from sources
A26: sc_sqm | B26: Rent | C26: Service charge / CAM (IDR per m² per month) | D26: IDR | E26: =INDEX(Location!$G$8:$G$13,$H$20) -> 0 | F26: =INDEX(Location!$G$8:$G$13,$H$20) -> 0 | G26: =INDEX(Location!$G$8:$G$13,$H$20) -> 0 | H26: =CHOOSE($D$4,E26,F26,G26) -> 0 | I26: Location col G; S27 (mall SC IDR 154k/m²/mo) | J26: L | K26: Linked: street ruko = 0 (owner pays building costs); mall/podium units use the Location sheet estimate (anchored on S27). | L26: Derived from sources
A27: rent_grossup | B27: Rent | C27: Rent gross-up for 10% PPh 4(2) if landlord quotes net | D27: % | E27: 0.111 | F27: 0 | G27: 0 | H27: =CHOOSE($D$4,E27,F27,G27) -> 0 | I27: S14 (PPh 4(2) final tax 10% on gross rent, withheld by corporate tenant) | J27: M | K27: If the landlord quotes rent net of tax, cost = net ÷ 0.9 → +11.1%. Conservative assumes net quote; base/optimistic assume gross quote (0%). | L27: Derived from sources
A28: rent_esc | B28: Rent | C28: Rent escalation p.a. | D28: % | E28: 0.08 | F28: 0.06 | G28: 0.05 | H28: =CHOOSE($D$4,E28,F28,G28) -> 0.06 | I28: S18 (CPI 3.28%); S28/S29 (vacancy tightening, F&B demand) | J28: L | K28: Base 6% ≈ CPI + ~3 pp for a tightening prime market. No published Jakarta ruko renewal-uplift statistic found → ask 2 brokers (Research_Tracker). | L28: Assumption – validate
A29: prepay_m | B29: Rent | C29: Rent paid upfront (months per payment block) | D29: months | E29: 24 | F29: 12 | G29: 12 | H29: =CHOOSE($D$4,E29,F29,G29) -> 12 | I29: S20/S21 listings & research notes (ruko leases min. 12 months, 1–2 yrs paid upfront) | J29: M | K29: Base 12 months paid upfront per block; conservative 24 months. | L29: Partly sourced
A30: deposit_m | B30: Rent | C30: Security deposit (months of rent) | D30: months | E30: 3 | F30: 2 | G30: 1 | H30: =CHOOSE($D$4,E30,F30,G30) -> 2 | I30: No public source found – market practice to confirm with brokers | J30: L | K30: Security deposit 2 months (base). Validate in broker interviews. | L30: Assumption – validate
A31: fitout_m | B31: Rent | C31: Paid rent months during fit-out (before opening) | D31: months | E31: 3 | F31: 2 | G31: 1 | H31: =CHOOSE($D$4,E31,F31,G31) -> 2 | I31: No public source found – negotiation point | J31: L | K31: Base: 2 months rent paid during fit-out; optimistic 1 (rent-free period negotiated). | L31: Assumption – validate
A32: REVENUE AT MATURITY (per trading day, before ramp-up & seasonality)
A33: cov_morning | B33: Revenue | C33: Guests – morning 07–11 (coffee, breakfast) | D33: guests/day | E33: 35 | F33: 45 | G33: 55 | H33: =CHOOSE($D$4,E33,F33,G33) -> 45 | I33: S46 Volume_Proxy (busiest in-zone comparables ≈ 53–67 guests/day base, 106–134 high); S43 (Fore ≈ IDR 13m sales/store/day) | J33: L | K33: Daypart split of a 200-guest day: morning 45 / lunch 75 / afternoon 35 / dinner 45. Cross-check: busiest in-zone pasta venues ≈ 53–67 guests/day at 100 guests/review (134 at 200/review); Fore Coffee IDR 1.5tn ÷ 316 stores ÷ 365 ≈ IDR 13m/day per store. CORSA base needs 200 → above any measured pasta comparable; this is the most important assumption to validate with field counts. | L33: Assumption – validate
A34: tkt_morning | B34: Revenue | C34: Avg net spend – morning | D34: IDR/guest | E34: 55000 | F34: 65000 | G34: 75000 | H34: =CHOOSE($D$4,E34,F34,G34) -> 65000 | I34: S31 (latte 45–52k, pastry), Menu sheet prices | J34: M | K34: Latte 50k + 40% pastry attach × 38k ≈ 65k. | L34: Derived from sources
A35: cov_lunch | B35: Revenue | C35: Guests – lunch 11–15 | D35: guests/day | E35: 60 | F35: 75 | G35: 95 | H35: =CHOOSE($D$4,E35,F35,G35) -> 75 | I35: See cov_morning (S46, S43) | J35: L | K35: 75 guests = largest daypart (office lunch, SCBD/Senopati). Same evidence caveat as above. | L35: Assumption – validate
A36: tkt_lunch | B36: Revenue | C36: Avg net spend – lunch (pasta + drink) | D36: IDR/guest | E36: 110000 | F36: 120000 | G36: 135000 | H36: =CHOOSE($D$4,E36,F36,G36) -> 120000 | I36: S46 (in-zone pasta venue median avg ~133k); S33/S34; Menu sheet | J36: M | K36: Pasta ~98k + 50% drink attach × ~45k ≈ 120k. Note: S46 shows in-zone pasta at ~133k → price headroom. | L36: Derived from sources
A37: cov_aft | B37: Revenue | C37: Guests – afternoon 15–18 | D37: guests/day | E37: 25 | F37: 35 | G37: 45 | H37: =CHOOSE($D$4,E37,F37,G37) -> 35 | I37: See cov_morning (S46, S43) | J37: L | K37: 35 guests (coffee/snack). No direct evidence. | L37: Assumption – validate
A38: tkt_aft | B38: Revenue | C38: Avg net spend – afternoon | D38: IDR/guest | E38: 60000 | F38: 70000 | G38: 80000 | H38: =CHOOSE($D$4,E38,F38,G38) -> 70000 | I38: S31, Menu sheet | J38: L | K38: Coffee/functional drink ~50k + 50% snack attach × ~40k ≈ 70k. | L38: Derived from sources
A39: cov_dinner | B39: Revenue | C39: Guests – dinner 18–22 | D39: guests/day | E39: 35 | F39: 45 | G39: 60 | H39: =CHOOSE($D$4,E39,F39,G39) -> 45 | I39: See cov_morning; S46 Weekday_Pattern (weekend ≈ 1.45× weekday) | J39: L | K39: 45 guests average incl. weekend uplift. No direct evidence. | L39: Assumption – validate
A40: tkt_dinner | B40: Revenue | C40: Avg net spend – dinner | D40: IDR/guest | E40: 125000 | F40: 140000 | G40: 150000 | H40: =CHOOSE($D$4,E40,F40,G40) -> 140000 | I40: S46, S33/S34 (casual Italian 100–200k pp), Menu sheet | J40: L | K40: Pasta ~105k + 60% drink × 45k + 20% dessert × 55k ≈ 143k → 140k. | L40: Derived from sources
A41: del_orders | B41: Revenue | C41: Delivery orders per day (GoFood/GrabFood/ShopeeFood) | D41: orders/day | E41: 15 | F41: 25 | G41: 35 | H41: =CHOOSE($D$4,E41,F41,G41) -> 25 | I41: S30 (delivery market USD 5.4bn; Grab 47% / Gojek 35% / Shopee 18%) | J41: L | K41: 25 orders/day is a volume assumption; S30 only sizes the market. | L41: Assumption – validate
A42: del_tkt | B42: Revenue | C42: Avg delivery order value (gross, app price) | D42: IDR/order | E42: 100000 | F42: 115000 | G42: 130000 | H42: =CHOOSE($D$4,E42,F42,G42) -> 115000 | I42: S46 (delivery prices ~15.6% above dine-in net); S32 vs S31 | J42: M | K42: ~100k dine-in basket × 1.156 ≈ 115k gross app value. | L42: Derived from sources
A43: takeaway | B43: Revenue | C43: Take-away share of in-store guests | D43: % | E43: 0.3 | F43: 0.3 | G43: 0.3 | H43: =CHOOSE($D$4,E43,F43,G43) -> 0.3 | I43: Brief (sit-down + take-away) | J43: L | K43: 30% of in-store guests take away – assumption. | L43: Assumption – validate
A44: events_m | B44: Revenue | C44: Events & B2B (catering, office) per month | D44: IDR/month | E44: 0 | F44: 15000000 | G44: 25000000 | H44: =CHOOSE($D$4,E44,F44,G44) -> 15000000 | I44: No source – upside stream | J44: L | K44: IDR 15m/month ≈ 2 small office caterings; 0 in conservative. | L44: Assumption – validate
... A47: ramp_months | B47: Ramp-up | C47: Months to reach maturity (100%) | D47: months | E47: 12 | F47: 9 | G47: 6 | H47: =CHOOSE($D$4,E47,F47,G47) -> 9 | I47: S60 (stabilisation 13–26 weeks ≈ 3–6 months) | J47: L | K47: Base 9 months (longer than S60's 3–6 months because brand is unknown in Jakarta); optimistic 6 = top of S60; conservative 12. | L47: Partly sourced
A48: COGS & VARIABLE COSTS
A49: cogs_uplift | B49: COGS | C49: Food & beverage cost adjustment vs Menu sheet (pp) | D49: pp | E49: 0.03 | F49: 0 | G49: -0.02 | H49: =CHOOSE($D$4,E49,F49,G49) -> 0 | I49: S16 (FX), S18 (volatile food 5%) | J49: M | K49: ±pp adjustment to the Menu blended cost for imported ingredients / FX / waste. Scenario spread is an assumption. | L49: Assumption – validate
A50: events_cogs | B50: COGS | C50: Events/B2B cost of goods % | D50: % | E50: 0.4 | F50: 0.35 | G50: 0.3 | H50: =CHOOSE($D$4,E50,F50,G50) -> 0.35 | I50: S49 (food cost 28.5–30.3%) + packaging/transport | J50: L | K50: ≈ 30% food cost + ~5 pp for packaging, transport and staff meals → 35%. | L50: Derived from sources
A51: retail_cogs | B51: COGS | C51: Retail cost of goods % | D51: % | E51: 0.6 | F51: 0.55 | G51: 0.5 | H51: =CHOOSE($D$4,E51,F51,G51) -> 0.55 | I51: No source | J51: L | K51: 55% COGS = 45% gross margin on retail goods. Assumption. | L51: Assumption – validate
A52: pack_pct | B52: Variable | C52: Packaging % of take-away + delivery revenue | D52: % | E52: 0.06 | F52: 0.05 | G52: 0.04 | H52: =CHOOSE($D$4,E52,F52,G52) -> 0.05 | I52: S49 (packaging 1–2% of total sales FSR; 3–4% limited service) | J52: L | K52: Limited-service operators spend 3–4% of TOTAL sales on packaging with most sales off-premise → ~4–5% of off-premise revenue. Base 5% applied only to take-away + delivery revenue. | L52: Derived from sources
A53: waste_pct | B53: Variable | C53: Waste & spoilage % of F&B revenue | D53: % | E53: 0.02 | F53: 0.015 | G53: 0.01 | H53: =CHOOSE($D$4,E53,F53,G53) -> 0.015 | I53: S54 (FSR waste 4–10% of food purchased); S49/S50 (food cost ~28–30%) | J53: L | K53: 4–10% of purchases × ~30% food cost = 1.2–3.0% of revenue. Base 1.5% = lower part of range (assumes portion control). | L53: Derived from sources
A54: del_comm | B54: Variable | C54: Delivery platform commission % of delivery revenue | D54: % | E54: 0.28 | F54: 0.23 | G54: 0.2 | H54: =CHOOSE($D$4,E54,F54,G54) -> 0.23 | I54: S12 (GoFood ~20%, GrabFood 20–30%, ShopeeFood 15–25%; +11% VAT on fee); S30 shares | J54: M | K54: Share-weighted: 47% × 25% (Grab mid) + 35% × 20% (GoFood) + 18% × 20% (Shopee mid) ≈ 22.4% → 23%. Conservative 28% (new-merchant Grab 30%), optimistic 20%. | L54: Derived from sources
A55: pay_fee | B55: Variable | C55: Payment fees % of in-store revenue | D55: % | E55: 0.015 | F55: 0.012 | G55: 0.009 | H55: =CHOOSE($D$4,E55,F55,G55) -> 0.012 | I55: S47/S48 (QRIS 0.7% regular merchant); card MDR ~2% (to confirm with acquiring bank) | J55: L | K55: Assumed mix 50% QRIS × 0.7% + 40% cards × 2.0% + 10% cash × 0% ≈ 1.15% → 1.2%. Card MDR and mix need a bank quote. | L55: Partly sourced
A56: mkt_pct | B56: Variable | C56: Marketing % of revenue (post-opening) | D56: % | E56: 0.04 | F56: 0.03 | G56: 0.025 | H56: =CHOOSE($D$4,E56,F56,G56) -> 0.03 | I56: S52 (3–6% of revenue) | J56: L | K56: Base 3% = low end, because launch marketing is funded separately in CAPEX (pre-opening). | L56: Derived from sources
A57: maint_pct | B57: Variable | C57: Repairs & maintenance % of revenue | D57: % | E57: 0.02 | F57: 0.015 | G57: 0.01 | H57: =CHOOSE($D$4,E57,F57,G57) -> 0.015 | I57: S53 (1–3% of revenue) | J57: L | K57: Base 1.5% (new equipment under warranty in years 1–2). | L57: Derived from sources
A58: misc_pct | B58: Variable | C58: Miscellaneous operating costs % of revenue | D58: % | E58: 0.015 | F58: 0.01 | G58: 0.005 | H58: =CHOOSE($D$4,E58,F58,G58) -> 0.01 | I58: No source | J58: L | K58: 1% catch-all. Assumption. | L58: Assumption – validate
A59: royalty | B59: Variable | C59: Brand/royalty fee to CORSA CH % of revenue | D59: % | E59: 0 | F59: 0 | G59: 0 | H59: =CHOOSE($D$4,E59,F59,G59) -> 0 | I59: CORSA decision | J59: - | K59: 0% unless CORSA CH charges a brand fee. | L59: Decision / policy
A60: STAFF
A61: ump | B61: Staff | C61: Jakarta minimum wage UMP 2026 | D61: IDR/month | E61: 5729876 | F61: 5729876 | G61: 5729876 | H61: =CHOOSE($D$4,E61,F61,G61) -> 5729876 | I61: S04 (Jakarta UMP 2026 IDR 5,729,876) | J61: H | K61: Statutory minimum wage – used as salary floor check. | L61: Sourced
A62: sal_factor | B62: Staff | C62: Salary level factor vs Staffing sheet | D62: x | E62: 1.1 | F62: 1 | G62: 1 | H62: =CHOOSE($D$4,E62,F62,G62) -> 1 | I62: S73/S75 (manager pay spread) | J62: L | K62: 1.0 = Staffing sheet salaries; conservative +10% retention premium. Assumption. | L62: Assumption – validate
A63: bpjs | B63: Staff | C63: Employer BPJS contributions % of salary | D63: % | E63: 0.117 | F63: 0.115 | G63: 0.102 | H63: =CHOOSE($D$4,E63,F63,G63) -> 0.115 | I63: S05 (JHT 3.7% + JP 2% + JKK 0.24–1.74% + JKM 0.3% + JKN 4%) | J63: H | K63: 3.7 + 2.0 + 0.3 + 4.0 = 10.0% + JKK 0.24–1.74% → 10.2–11.7%. Base 11.5% (prudent; JP/JKN wage caps make the true rate slightly lower for high earners). | L63: Derived from sources
A64: thr | B64: Staff | C64: THR (13th month religious holiday bonus) accrual | D64: % | E64: 0.0833 | F64: 0.0833 | G64: 0.0833 | H64: =CHOOSE($D$4,E64,F64,G64) -> 0.0833 | I64: S76 (Permenaker 6/2016: THR = 1 month wage per year) | J64: H | K64: 1 ÷ 12 = 8.33% accrual on salaries. | L64: Sourced
A65: benefit | B65: Staff | C65: Meals, uniform, transport per head per month | D65: IDR/head | E65: 1200000 | F65: 1000000 | G65: 800000 | H65: =CHOOSE($D$4,E65,F65,G65) -> 1000000 | I65: No source – market practice | J65: L | K65: IDR 1.0m/head/month for staff meals, uniform, transport. Assumption. | L65: Assumption – validate
A66: FIXED OPERATING COSTS (per month, year-1 prices)
A67: fx_mgmt | B67: Fixed | C67: Local management / area oversight (part-time) | D67: IDR/month | E67: 30000000 | F67: 25000000 | G67: 20000000 | H67: =CHOOSE($D$4,E67,F67,G67) -> 25000000 | I67: S75 (F&B manager 12–25m/month) | J67: L | K67: IDR 25m/month ≈ top of S75 F&B-manager range – budget for local partner/area manager oversight on top of the store GM. | L67: Partly sourced
A68: fx_acct | B68: Fixed | C68: Accounting, tax, payroll & legal retainer | D68: IDR/month | E68: 12000000 | F68: 9000000 | G68: 7000000 | H68: =CHOOSE($D$4,E68,F68,G68) -> 9000000 | I68: S03/S15 (PT PMA needs full bookkeeping, LKPM reporting) | J68: L | K68: IDR 9m/month retainer – no price source; get 2 quotes. | L68: Assumption – validate
A69: fx_ins | B69: Fixed | C69: Insurance | D69: IDR/month | E69: 4000000 | F69: 3000000 | G69: 2500000 | H69: =CHOOSE($D$4,E69,F69,G69) -> 3000000 | I69: No source | J69: L | K69: IDR 3m/month property all-risk + public liability – get a broker quote. | L69: Assumption – validate
A70: fx_soft | B70: Fixed | C70: POS/software, internet, music licence | D70: IDR/month | E70: 4000000 | F70: 3000000 | G70: 2500000 | H70: =CHOOSE($D$4,E70,F70,G70) -> 3000000 | I70: S67 (Moka POS 299–799k/outlet/month) | J70: L | K70: POS ~0.8m + KDS/inventory add-ons + internet ~1m + music licence/apps ~1m ≈ 3m. Only the POS part is sourced. | L70: Partly sourced
A71: fx_clean | B71: Fixed | C71: Cleaning, pest control, waste & laundry | D71: IDR/month | E71: 6000000 | F71: 5000000 | G71: 4000000 | H71: =CHOOSE($D$4,E71,F71,G71) -> 5000000 | I71: No source | J71: L | K71: IDR 5m/month cleaning, pest control, waste collection, laundry. Assumption – quotes. | L71: Assumption – validate
A72: fx_other | B72: Fixed | C72: Other admin (bank, permits renewal, travel) | D72: IDR/month | E72: 5000000 | F72: 4000000 | G72: 3000000 | H72: =CHOOSE($D$4,E72,F72,G72) -> 4000000 | I72: No source | J72: L | K72: IDR 4m/month bank fees, permit renewals, travel. Assumption. | L72: Assumption – validate
A73: kwh | B73: Utilities | C73: Electricity consumption | D73: kWh/month | E73: 11000 | F73: 9000 | G73: 7500 | H73: =CHOOSE($D$4,E73,F73,G73) -> 9000 | I73: S55 (US restaurant median site EUI 325.6 kBtu/ft² ≈ 1,027 kWh/m²/yr, all fuels) | J73: L | K73: 1,027 kWh/m² × 150 m² ÷ 12 ≈ 12,840 kWh/month of all energy; ~30% assumed as LPG for cooking → ≈ 9,000 kWh electricity. Check with PLN connection (kVA) and AC load. | L73: Derived from sources
A74: tariff | B74: Utilities | C74: Electricity tariff B-2 | D74: IDR/kWh | E74: 1444.7 | F74: 1444.7 | G74: 1444.7 | H74: =CHOOSE($D$4,E74,F74,G74) -> 1444.7 | I74: S11 (PLN B-2 IDR 1,444.70/kWh from 1 Sep 2026) | J74: H | K74: Official tariff. | L74: Sourced
A75: watergas | B75: Utilities | C75: Water & gas | D75: IDR/month | E75: 8000000 | F75: 6000000 | G75: 5000000 | H75: =CHOOSE($D$4,E75,F75,G75) -> 6000000 | I75: S56 (PAM Jaya niaga IDR 4,900–21,500/m³); S57 (LPG 12 kg IDR 220k) | J75: L | K75: Water ~120 m³/month × 21,500 ≈ 2.6m + LPG ~15 × 12 kg × 220k ≈ 3.3m → ≈ 5.9m ≈ 6m. Consumption volumes are estimates. | L75: Derived from sources
A76: CAPEX & FUNDING
A77: overrun | B77: CAPEX | C77: CAPEX cost factor (overrun / savings) | D77: x | E77: 1.15 | F77: 1 | G77: 0.95 | H77: =CHOOSE($D$4,E77,F77,G77) -> 1 | I77: S64 (contingency 10% for renovation) | J77: M | K77: Conservative +15% overrun on hard costs (on top of contingency); optimistic −5% from negotiated quotes. Assumption. | L77: Assumption – validate
A78: contingency | B78: CAPEX | C78: Contingency reserve % of hard + soft costs | D78: % | E78: 0.15 | F78: 0.1 | G78: 0.075 | H78: =CHOOSE($D$4,E78,F78,G78) -> 0.1 | I78: S64 (5% ground-up, 10% renovation) | J78: M | K78: Base 10% = renovation/fit-out benchmark; conservative 15%; optimistic 7.5%. | L78: Derived from sources
A79: preopen_pay | B79: CAPEX | C79: Pre-opening payroll (months of full staff cost) | D79: months | E79: 1.5 | F79: 1 | G79: 0.75 | H79: =CHOOSE($D$4,E79,F79,G79) -> 1 | I79: S60 (stabilisation period); team assumption | J79: L | K79: 1 month of full payroll before opening for hiring and training. | L79: Assumption – validate
A80: wc_months | B80: CAPEX | C80: Working-capital reserve (months of staff + fixed opex + utilities) | D80: months | E80: 3 | F80: 3 | G80: 2 | H80: =CHOOSE($D$4,E80,F80,G80) -> 3 | I80: S36 (early-stage failure risk); team assumption | J80: M | K80: 3 months of staff + fixed opex + utilities kept as cash buffer for ramp-up. | L80: Assumption – validate
A81: dep_years | B81: CAPEX | C81: Depreciation life of fit-out & equipment | D81: years | E81: 5 | F81: 5 | G81: 5 | H81: =CHOOSE($D$4,E81,F81,G81) -> 5 | I81: S61 (PMK 72/2023: group 1 = 4 yrs, group 2 = 8 yrs, non-permanent building 10 yrs) | J81: M | K81: Blend: IT/smallwares 4 yrs, kitchen/coffee equipment & furniture 8 yrs, leasehold fit-out over lease term (~5 yrs) → 5 years straight-line for the model (accounting view, tax may differ). | L81: Derived from sources
A82: equity_chf | B82: Funding | C82: Founder equity available | D82: CHF | E82: 200000 | F82: 200000 | G82: 200000 | H82: =CHOOSE($D$4,E82,F82,G82) -> 200000 | I82: Brief (CHF 200,000) | J82: H | K82: Given by CORSA. | L82: Decision / policy
A83: loan_on | B83: Funding | C83: Fill funding gap with bank loan? (1 = yes, 0 = no) | D83: 1/0 | E83: 1 | F83: 1 | G83: 1 | H83: =CHOOSE($D$4,E83,F83,G83) -> 1 | I83: Model switch | J83: - | K83: 1 = fill funding gap with a bank loan. | L83: Decision / policy
A84: loan_rate | B84: Funding | C84: Loan interest rate p.a. | D84: % | E84: 0.12 | F84: 0.105 | G84: 0.09 | H84: =CHOOSE($D$4,E84,F84,G84) -> 0.105 | I84: S19 (BCA SBDK small business 8.01%, excl. risk premium); S17 (BI-Rate 5.75%) | J84: L | K84: 8.01% + ~2.5 pp risk premium for a new company ≈ 10.5%. Conservative 12%, optimistic 9%. | L84: Derived from sources
A85: loan_tenor | B85: Funding | C85: Loan tenor (months, annuity) | D85: months | E85: 36 | F85: 48 | G85: 60 | H85: =CHOOSE($D$4,E85,F85,G85) -> 48 | I85: S49 (debt service ≤12% of sales over 3–5 years) | J85: L | K85: Base 48 months – inside the 3–5 year benchmark. | L85: Partly sourced
A86: n_kbli | B86: Legal | C86: Number of KBLI codes registered (restaurant, café, retail…) | D86: # | E86: 2 | F86: 1 | G86: 1 | H86: =CHOOSE($D$4,E86,F86,G86) -> 1 | I86: S02 (capital requirement per KBLI) | J86: M | K86: 1 KBLI (56101 restaurant) in base; conservative adds a second (e.g. café/retail). | L86: Derived from sources
A87: pma_paidup | B87: Legal | C87: PT PMA minimum paid-up capital per KBLI | D87: IDR | E87: 2500000000 | F87: 2500000000 | G87: 2500000000 | H87: =CHOOSE($D$4,E87,F87,G87) -> 2500000000 | I87: S02 (BKPM Reg. 5/2025) | J87: M | K87: IDR 2.5bn per KBLI. | L87: Sourced
A88: pma_plan | B88: Legal | C88: PT PMA minimum investment plan per KBLI (excl. land & building) | D88: IDR | E88: 10000000000 | F88: 10000000000 | G88: 10000000000 | H88: =CHOOSE($D$4,E88,F88,G88) -> 10000000000 | I88: S01/S02 | J88: M | K88: IDR 10bn investment plan per KBLI (excl. land & buildings). | L88: Sourced
... A90: tv_mult | B90: Valuation | C90: Terminal value at Y5 (x Y5 EBITDA) | D90: x | E90: 0 | F90: 2 | G90: 3 | H90: =CHOOSE($D$4,E90,F90,G90) -> 2 | I90: No source | J90: L | K90: 2× year-5 EBITDA (value of remaining lease/brand); 0 in conservative. Assumption. | L90: Assumption – validate
A91: SEASONALITY (index by calendar month, 1.00 = normal)
A92: season_1 | B92: Season | C92: Seasonality – Jan | D92: index | E92: 1 | F92: 1 | G92: 1 | H92: =CHOOSE($D$4,E92,F92,G92) -> 1 | I92: S58 (Ramadan ≈ 8 Feb–9 Mar 2027, Idul Fitri ≈ 10 Mar 2027); S59 (Ramadan sales effect mixed: chains +15–30%, café chain dip in week 1) | J92: L | K92: Feb 0.92 / Mar 0.95: daytime/lunch dip during fasting + Lebaran exodus (mudik) around 10 Mar; partly offset by iftar. Note S59 reports Ramadan uplifts for chains → index may be too cautious. Dec 1.08 holiday season and other months 1.00 are assumptions. | L92: Partly sourced
A93: season_2 | B93: Season | C93: Seasonality – Feb | D93: index | E93: 0.92 | F93: 0.92 | G93: 0.92 | H93: =CHOOSE($D$4,E93,F93,G93) -> 0.92 | I93: S58 (Ramadan ≈ 8 Feb–9 Mar 2027, Idul Fitri ≈ 10 Mar 2027); S59 (Ramadan sales effect mixed: chains +15–30%, café chain dip in week 1) | J93: L | K93: Feb 0.92 / Mar 0.95: daytime/lunch dip during fasting + Lebaran exodus (mudik) around 10 Mar; partly offset by iftar. Note S59 reports Ramadan uplifts for chains → index may be too cautious. Dec 1.08 holiday season and other months 1.00 are assumptions. | L93: Partly sourced
A94: season_3 | B94: Season | C94: Seasonality – Mar | D94: index | E94: 0.95 | F94: 0.95 | G94: 0.95 | H94: =CHOOSE($D$4,E94,F94,G94) -> 0.95 | I94: S58 (Ramadan ≈ 8 Feb–9 Mar 2027, Idul Fitri ≈ 10 Mar 2027); S59 (Ramadan sales effect mixed: chains +15–30%, café chain dip in week 1) | J94: L | K94: Feb 0.92 / Mar 0.95: daytime/lunch dip during fasting + Lebaran exodus (mudik) around 10 Mar; partly offset by iftar. Note S59 reports Ramadan uplifts for chains → index may be too cautious. Dec 1.08 holiday season and other months 1.00 are assumptions. | L94: Partly sourced
A95: season_4 | B95: Season | C95: Seasonality – Apr | D95: index | E95: 1 | F95: 1 | G95: 1 | H95: =CHOOSE($D$4,E95,F95,G95) -> 1 | I95: S58 (Ramadan ≈ 8 Feb–9 Mar 2027, Idul Fitri ≈ 10 Mar 2027); S59 (Ramadan sales effect mixed: chains +15–30%, café chain dip in week 1) | J95: L | K95: Feb 0.92 / Mar 0.95: daytime/lunch dip during fasting + Lebaran exodus (mudik) around 10 Mar; partly offset by iftar. Note S59 reports Ramadan uplifts for chains → index may be too cautious. Dec 1.08 holiday season and other months 1.00 are assumptions. | L95: Partly sourced
A96: season_5 | B96: Season | C96: Seasonality – May | D96: index | E96: 1 | F96: 1 | G96: 1 | H96: =CHOOSE($D$4,E96,F96,G96) -> 1 | I96: S58 (Ramadan ≈ 8 Feb–9 Mar 2027, Idul Fitri ≈ 10 Mar 2027); S59 (Ramadan sales effect mixed: chains +15–30%, café chain dip in week 1) | J96: L | K96: Feb 0.92 / Mar 0.95: daytime/lunch dip during fasting + Lebaran exodus (mudik) around 10 Mar; partly offset by iftar. Note S59 reports Ramadan uplifts for chains → index may be too cautious. Dec 1.08 holiday season and other months 1.00 are assumptions. | L96: Partly sourced
A97: season_6 | B97: Season | C97: Seasonality – Jun | D97: index | E97: 1 | F97: 1 | G97: 1 | H97: =CHOOSE($D$4,E97,F97,G97) -> 1 | I97: S58 (Ramadan ≈ 8 Feb–9 Mar 2027, Idul Fitri ≈ 10 Mar 2027); S59 (Ramadan sales effect mixed: chains +15–30%, café chain dip in week 1) | J97: L | K97: Feb 0.92 / Mar 0.95: daytime/lunch dip during fasting + Lebaran exodus (mudik) around 10 Mar; partly offset by iftar. Note S59 reports Ramadan uplifts for chains → index may be too cautious. Dec 1.08 holiday season and other months 1.00 are assumptions. | L97: Partly sourced
A98: season_7 | B98: Season | C98: Seasonality – Jul | D98: index | E98: 1 | F98: 1 | G98: 1 | H98: =CHOOSE($D$4,E98,F98,G98) -> 1 | I98: S58 (Ramadan ≈ 8 Feb–9 Mar 2027, Idul Fitri ≈ 10 Mar 2027); S59 (Ramadan sales effect mixed: chains +15–30%, café chain dip in week 1) | J98: L | K98: Feb 0.92 / Mar 0.95: daytime/lunch dip during fasting + Lebaran exodus (mudik) around 10 Mar; partly offset by iftar. Note S59 reports Ramadan uplifts for chains → index may be too cautious. Dec 1.08 holiday season and other months 1.00 are assumptions. | L98: Partly sourced
A99: season_8 | B99: Season | C99: Seasonality – Aug | D99: index | E99: 1 | F99: 1 | G99: 1 | H99: =CHOOSE($D$4,E99,F99,G99) -> 1 | I99: S58 (Ramadan ≈ 8 Feb–9 Mar 2027, Idul Fitri ≈ 10 Mar 2027); S59 (Ramadan sales effect mixed: chains +15–30%, café chain dip in week 1) | J99: L | K99: Feb 0.92 / Mar 0.95: daytime/lunch dip during fasting + Lebaran exodus (mudik) around 10 Mar; partly offset by iftar. Note S59 reports Ramadan uplifts for chains → index may be too cautious. Dec 1.08 holiday season and other months 1.00 are assumptions. | L99: Partly sourced
A100: season_9 | B100: Season | C100: Seasonality – Sep | D100: index | E100: 1 | F100: 1 | G100: 1 | H100: =CHOOSE($D$4,E100,F100,G100) -> 1 | I100: S58 (Ramadan ≈ 8 Feb–9 Mar 2027, Idul Fitri ≈ 10 Mar 2027); S59 (Ramadan sales effect mixed: chains +15–30%, café chain dip in week 1) | J100: L | K100: Feb 0.92 / Mar 0.95: daytime/lunch dip during fasting + Lebaran exodus (mudik) around 10 Mar; partly offset by iftar. Note S59 reports Ramadan uplifts for chains → index may be too cautious. Dec 1.08 holiday season and other months 1.00 are assumptions. | L100: Partly sourced
A101: season_10 | B101: Season | C101: Seasonality – Oct | D101: index | E101: 1 | F101: 1 | G101: 1 | H101: =CHOOSE($D$4,E101,F101,G101) -> 1 | I101: S58 (Ramadan ≈ 8 Feb–9 Mar 2027, Idul Fitri ≈ 10 Mar 2027); S59 (Ramadan sales effect mixed: chains +15–30%, café chain dip in week 1) | J101: L | K101: Feb 0.92 / Mar 0.95: daytime/lunch dip during fasting + Lebaran exodus (mudik) around 10 Mar; partly offset by iftar. Note S59 reports Ramadan uplifts for chains → index may be too cautious. Dec 1.08 holiday season and other months 1.00 are assumptions. | L101: Partly sourced
A102: season_11 | B102: Season | C102: Seasonality – Nov | D102: index | E102: 1 | F102: 1 | G102: 1 | H102: =CHOOSE($D$4,E102,F102,G102) -> 1 | I102: S58 (Ramadan ≈ 8 Feb–9 Mar 2027, Idul Fitri ≈ 10 Mar 2027); S59 (Ramadan sales effect mixed: chains +15–30%, café chain dip in week 1) | J102: L | K102: Feb 0.92 / Mar 0.95: daytime/lunch dip during fasting + Lebaran exodus (mudik) around 10 Mar; partly offset by iftar. Note S59 reports Ramadan uplifts for chains → index may be too cautious. Dec 1.08 holiday season and other months 1.00 are assumptions. | L102: Partly sourced
A103: season_12 | B103: Season | C103: Seasonality – Dec | D103: index | E103: 1.08 | F103: 1.08 | G103: 1.08 | H103: =CHOOSE($D$4,E103,F103,G103) -> 1.08 | I103: S58 (Ramadan ≈ 8 Feb–9 Mar 2027, Idul Fitri ≈ 10 Mar 2027); S59 (Ramadan sales effect mixed: chains +15–30%, café chain dip in week 1) | J103: L | K103: Feb 0.92 / Mar 0.95: daytime/lunch dip during fasting + Lebaran exodus (mudik) around 10 Mar; partly offset by iftar. Note S59 reports Ramadan uplifts for chains → index may be too cautious. Dec 1.08 holiday season and other months 1.00 are assumptions. | L103: Partly sourced

Sheet Rent_Data
A1: Rent Evidence – Asking Rents from Listing Portals (accessed 6–8 Oct 2026) – units of 100–200 m²
A2: Only units with 100–200 m² of rented surface are kept (all floors, any format), per the brief's 120–180 m². IDR per m² of rented surface per month; asking prices – deals usually 5–15% lower.
A3: Jonas: | B3: I built this sheet to gather existing offers in both Tier 1 and Tier 2 locations and have an overview. | M3: Columns M–T: exact address as advertised, Google Maps link, link to the individual ad, listing ID, advertiser, ad date, verification note.
B4: I voluntarily choose a range from 100 to 200sqm to get more locations (more accurate quantitative data) and avoid rejectance of surface that my be inexact in the offers.
B5: These are selected available locations to give an idea of types of available surfaces and their prices . If @sam you have some contacts with agencies, I'd love to have a look and add their offers to this sheet
A7: # | B7: District | C7: Location / street | D7: Type | E7: Asking rent (IDR) | F7: Period | G7: Monthly rent (IDR) | H7: Surface m² (all floors) | I7: Floors | J7: IDR / m² / month | K7: Source | L7: Note | M7: Exact address / building (as advertised) | N7: Map | O7: Listing (click to open) | P7: Listing URL | Q7: Listing ID | R7: Advertiser / agent | S7: Ad date | T7: Verification 8 Oct 2026
A8: 3 | B8: SCBD | C8: Pacific Century Tower (rooftop F&B space) | D8: F&B space | E8: 95000000 | F8: month | G8: =IF(F8="year",E8/12,E8) -> 95000000 | H8: 191 | J8: =G8/H8 -> 497382.2 | K8: S23 | L8: Excl. VAT & service charge | M8: Pacific Century Place (PCP) Tower, SCBD Lot 10, Jakarta Selatan – rooftop | N8: =HYPERLINK("https://www.google.com/maps/search/?api=1&query=Pacific+Century+Place+SCBD+Jakarta","Google Maps") -> Google Maps | O8: =HYPERLINK("https://www.rumah123.com/en/property/jakarta-selatan-scbd/disewakan-space-utk-resto-bar-rooftop-di-pacific-century-tower-scbd-csr3740301/","Open ad") -> Open ad | P8: https://www.rumah123.com/en/property/jakarta-selatan-scbd/disewakan-space-utk-resto-bar-rooftop-di-pacific-century-tower-scbd-csr3740301/ | Q8: csr3740301 | R8: Zwitsa Bella Ratu (independent) | S8: Updated 28 Oct 2025 | T8: Confirmed. Same space also advertised by Sangga Buana (2 duplicate ads). Excl. VAT & service charge.
A9: 5 | B9: SCBD | C9: Equity Tower | D9: Office (reference) | E9: 60160000 | F9: month | G9: =IF(F9="year",E9/12,E9) -> 60160000 | H9: 188 | J9: =G9/H9 -> 320000 | K9: S22 | L9: Office tower – reference only | M9: Equity Tower, SCBD Lot 9, Jl. Jend. Sudirman Kav. 52-53, Jakarta Selatan | N9: =HYPERLINK("https://www.google.com/maps/search/?api=1&query=Equity+Tower+SCBD+Jakarta","Google Maps") -> Google Maps | O9: =HYPERLINK("https://www.rumah123.com/en/rent/jakarta-selatan/scbd/commercial-space/","Open results page") -> Open results page | P9: https://www.rumah123.com/en/rent/jakarta-selatan/scbd/commercial-space/ | Q9: not found | R9: Putera Frans – Century21 Rich Realty (on results page) | S9: not shown | T9: Individual ad not found (unverified candidates on Rumah123: ofr4180086, ofr4456549). Office tower – reference only.
A11: 6 | B11: Senopati main road | C11: Jl. Suryo – 3rd floor only | D11: Upper floor in building | E11: 520000000 | F11: year | G11: =IF(F11="year",E11/12,E11) -> 43333333 | H11: 150 | I11: 1 | J11: =G11/H11 -> 288888.89 | K11: S78 | L11: Upper floor, not street level | M11: Jl. Suryo (= Jl. Senopati), Kebayoran Baru, Jakarta Selatan | N11: =HYPERLINK("https://www.google.com/maps/search/?api=1&query=" & SUBSTITUTE(M11," ","+"),"Google Maps") -> Google Maps | O11: =HYPERLINK(P11,"Open results page") -> Open results page | P11: https://www.rumah123.com/en/rent/jakarta-selatan/senopati/shophouse/ | Q11: results page only | R11: Efendi Tobing – BAA Homes | S11: updated c. 4 Oct 2026 | T11: Seen on the Rumah123 results page only. Only 1 main-road listing → Location uses fallback until ≥3 (289k/m² vs fallback 267k: consistent).
A13: 7 | B13: Senopati side streets | C13: Wolter Monginsidi | D13: Ruko | E13: 29000000 | F13: month | G13: =IF(F13="year",E13/12,E13) -> 29000000 | H13: 185 | I13: 4 | J13: =G13/H13 -> 156756.76 | K13: S20 | M13: Jl. Wolter Monginsidi, Kebayoran Baru, Jakarta Selatan | N13: =HYPERLINK("https://www.google.com/maps/search/?api=1&query=Jl.+Wolter+Monginsidi+Kebayoran+Baru+Jakarta","Google Maps") -> Google Maps | O13: =HYPERLINK("https://www.flokq.com/sewa-ruko-jakarta/ruko/RKRbd0","Open ad") -> Open ad | P13: https://www.flokq.com/sewa-ruko-jakarta/ruko/RKRbd0 | Q13: RKRbd0 | R13: not shown on ad | S13: not shown | T13: Confirmed (nego).
A14: 8 | B14: Senopati side streets | C14: Wolter Monginsidi | D14: Ruko | E14: 29200000 | F14: month | G14: =IF(F14="year",E14/12,E14) -> 29200000 | H14: 195 | I14: 3 | J14: =G14/H14 -> 149743.59 | K14: S20 | M14: Jl. Wolter Monginsidi, Kebayoran Baru, Jakarta Selatan | N14: =HYPERLINK("https://www.google.com/maps/search/?api=1&query=Jl.+Wolter+Monginsidi+Kebayoran+Baru+Jakarta","Google Maps") -> Google Maps | O14: =HYPERLINK("https://www.flokq.com/sewa-ruko-jakarta/ruko/RKRfe7","Open ad") -> Open ad | P14: https://www.flokq.com/sewa-ruko-jakarta/ruko/RKRfe7 | Q14: RKRfe7 | R14: not shown on ad | S14: not shown | T14: Confirmed (nego).
A15: 9 | B15: Senopati side streets | C15: Wolter Monginsidi | D15: Ruko | E15: 16700000 | F15: month | G15: =IF(F15="year",E15/12,E15) -> 16700000 | H15: 160 | I15: 2 | J15: =G15/H15 -> 104375 | K15: S20 | M15: Near Jl. Wolter Monginsidi, Kebayoran Baru, Jakarta Selatan | N15: =HYPERLINK("https://www.google.com/maps/search/?api=1&query=Jl.+Wolter+Monginsidi+Kebayoran+Baru+Jakarta","Google Maps") -> Google Maps | O15: =HYPERLINK("https://www.flokq.com/sewa-ruko-jakarta/ruko/RKR37e","Open ad") -> Open ad | P15: https://www.flokq.com/sewa-ruko-jakarta/ruko/RKR37e | Q15: RKR37e | R15: not shown on ad | S15: not shown | T15: Confirmed (nego).
A16: 10 | B16: Senopati side streets | C16: Wijaya | D16: Ruko | E16: 37500000 | F16: month | G16: =IF(F16="year",E16/12,E16) -> 37500000 | H16: 112 | I16: 2 | J16: =G16/H16 -> 334821.43 | K16: S20 | M16: Jl. Wijaya, Kebayoran Baru, Jakarta Selatan | N16: =HYPERLINK("https://www.google.com/maps/search/?api=1&query=Jl.+Wijaya+I+Kebayoran+Baru+Jakarta","Google Maps") -> Google Maps | O16: =HYPERLINK("https://www.flokq.com/sewa-ruko-jakarta/ruko/RKR485","Open ad") -> Open ad | P16: https://www.flokq.com/sewa-ruko-jakarta/ruko/RKR485 | Q16: RKR485 | R16: not shown on ad | S16: not shown | T16: Confirmed. Twin ad RKR100 (same price/m², 4 floors).
A17: 11 | B17: Senopati side streets | C17: Haji Nawi | D17: Ruko | E17: 12500000 | F17: month | G17: =IF(F17="year",E17/12,E17) -> 12500000 | H17: 150 | I17: 2 | J17: =G17/H17 -> 83333.333 | K17: S20 | M17: Jl. Haji Nawi, Gandaria, Jakarta Selatan | N17: =HYPERLINK("https://www.google.com/maps/search/?api=1&query=Jl.+Haji+Nawi+Jakarta+Selatan","Google Maps") -> Google Maps | O17: =HYPERLINK("https://www.flokq.com/sewa-ruko-jakarta/ruko/RKR7b7","Open ad") -> Open ad | P17: https://www.flokq.com/sewa-ruko-jakarta/ruko/RKR7b7 | Q17: RKR7b7 | R17: not shown on ad | S17: not shown | T17: Price shown on results page only; ad page says 'nego'.
A18: 12 | B18: Senopati side streets | C18: Haji Nawi Raya | D18: Ruko | E18: 23000000 | F18: month | G18: =IF(F18="year",E18/12,E18) -> 23000000 | H18: 143 | I18: 2 | J18: =G18/H18 -> 160839.16 | K18: S20 | M18: Jl. Haji Nawi Raya, Gandaria, Jakarta Selatan | N18: =HYPERLINK("https://www.google.com/maps/search/?api=1&query=Jl.+Haji+Nawi+Raya+Jakarta+Selatan","Google Maps") -> Google Maps | O18: =HYPERLINK("https://www.flokq.com/sewa-ruko-jakarta/ruko/RKR678","Open ad") -> Open ad | P18: https://www.flokq.com/sewa-ruko-jakarta/ruko/RKR678 | Q18: RKR678 | R18: not shown on ad | S18: not shown | T18: Confirmed.
A19: 13 | B19: Senopati side streets | C19: Kebayoran Baru | D19: Ruko | E19: 18800000 | F19: month | G19: =IF(F19="year",E19/12,E19) -> 18800000 | H19: 160 | I19: 2 | J19: =G19/H19 -> 117500 | K19: S20 | M19: Kebayoran Baru, near Treasury Tower & Pacific Century Place, Jakarta Selatan | N19: =HYPERLINK("https://www.google.com/maps/search/?api=1&query=Pacific+Century+Place+SCBD+Jakarta","Google Maps") -> Google Maps | O19: =HYPERLINK("https://www.flokq.com/sewa-ruko-jakarta/ruko/RKR6fb","Open ad") -> Open ad | P19: https://www.flokq.com/sewa-ruko-jakarta/ruko/RKR6fb | Q19: RKR6fb | R19: not shown on ad | S19: c. Apr 2025 (photo filename) | T19: Confirmed (nego).
A20: 14 | B20: Senopati side streets | C20: Kebayoran Baru | D20: Ruko | E20: 16700000 | F20: month | G20: =IF(F20="year",E20/12,E20) -> 16700000 | H20: 160 | I20: 3 | J20: =G20/H20 -> 104375 | K20: S20 | M20: Kebayoran Baru, Jakarta Selatan (no street given) | N20: =HYPERLINK("https://www.google.com/maps/search/?api=1&query=Kebayoran+Baru+Jakarta+Selatan","Google Maps") -> Google Maps | O20: =HYPERLINK("https://www.flokq.com/sewa-ruko-jakarta/ruko/RKRcae","Open ad") -> Open ad | P20: https://www.flokq.com/sewa-ruko-jakarta/ruko/RKRcae | Q20: RKRcae | R20: not shown on ad | S20: c. Mar 2025 (photo filename) | T20: Confirmed (nego). Location vague.
A21: 15 | B21: Senopati side streets | C21: Kyai Maja | D21: Ruko | E21: 14500000 | F21: month | G21: =IF(F21="year",E21/12,E21) -> 14500000 | H21: 193 | I21: 3 | J21: =G21/H21 -> 75129.534 | K21: S20 | M21: Jl. Kyai Maja, Kebayoran Baru, Jakarta Selatan | N21: =HYPERLINK("https://www.google.com/maps/search/?api=1&query=Jl.+Kyai+Maja+Jakarta+Selatan","Google Maps") -> Google Maps | O21: =HYPERLINK("https://www.flokq.com/sewa-ruko-jakarta/ruko/RKR927","Open ad") -> Open ad | P21: https://www.flokq.com/sewa-ruko-jakarta/ruko/RKR927 | Q21: RKR927 | R21: not shown on ad | S21: not shown | T21: Confirmed (nego).
A22: 16 | B22: Senopati side streets | C22: Cipaku | D22: Ruko | E22: 9000000 | F22: month | G22: =IF(F22="year",E22/12,E22) -> 9000000 | H22: 105 | I22: 2 | J22: =G22/H22 -> 85714.286 | K22: S20 | M22: Jl. Cipaku, Kebayoran Baru (near Treasury Tower / Pacific Century Place), Jakarta Selatan | N22: =HYPERLINK("https://www.google.com/maps/search/?api=1&query=" & SUBSTITUTE(M22," ","+"),"Google Maps") -> Google Maps | O22: =HYPERLINK(P22,"Open ad") -> Open ad | P22: https://www.flokq.com/sewa-ruko-jakarta/ruko/RKRb4b | Q22: RKRb4b | R22: not shown | S22: not shown | T22: Added 8 Oct 2026. Price from Flokq results page (ad says nego). Cipaku is at the edge of the Senopati area.
A24: 17 | B24: Kuningan | C24: Jl. HR Rasuna Said | D24: Ruko | E24: 35000000 | F24: month | G24: =IF(F24="year",E24/12,E24) -> 35000000 | H24: 110 | I24: 2 | J24: =G24/H24 -> 318181.82 | K24: S24 | M24: Jl. HR Rasuna Said, Kuningan, Jakarta Selatan | N24: =HYPERLINK("https://www.google.com/maps/search/?api=1&query=Jl.+HR+Rasuna+Said+Kuningan+Jakarta","Google Maps") -> Google Maps | O24: =HYPERLINK("https://www.flokq.com/sewa-ruko-jakarta/ruko/RKR3de","Open ad") -> Open ad | P24: https://www.flokq.com/sewa-ruko-jakarta/ruko/RKR3de | Q24: RKR3de | R24: not shown on ad | S24: not shown | T24: Confirmed (nego).
A25: 18 | B25: Kuningan | C25: Epicentrum Walk (Epiwalk) – ex-restaurant | D25: Shophouse in mall complex | E25: 330000000 | F25: year | G25: =IF(F25="year",E25/12,E25) -> 27500000 | H25: 110 | I25: 2 | J25: =G25/H25 -> 250000 | K25: S79 | L25: Ex-resto, furnished, 24h mall access | M25: Epicentrum Walk, Jl. HR Rasuna Said, Kuningan, Jakarta Selatan | N25: =HYPERLINK("https://www.google.com/maps/search/?api=1&query=" & SUBSTITUTE(M25," ","+"),"Google Maps") -> Google Maps | O25: =HYPERLINK(P25,"Open ad") -> Open ad | P25: https://www.rumah123.com/properti/jakarta-pusat-menteng/disewakan-ex-resto-di-epiwalk-rasuna-said-kuningan-shr9910999/ | Q25: shr9910999 | R25: Gido – GadingPro Menteng | S25: c. Aug 2026 | T25: Added 8 Oct 2026 from results page; ad page would not open – confirm with agent.
A27: 19 | B27: Kemang | C27: Benda Kemang | D27: Ruko | E27: 20800000 | F27: month | G27: =IF(F27="year",E27/12,E27) -> 20800000 | H27: 170 | I27: 1 | J27: =G27/H27 -> 122352.94 | K27: S25 | M27: Jl. Benda / Kemang, Jakarta Selatan | N27: =HYPERLINK("https://www.google.com/maps/search/?api=1&query=Jl.+Benda+Kemang+Jakarta+Selatan","Google Maps") -> Google Maps | O27: =HYPERLINK("https://www.flokq.com/sewa-ruko-jakarta/ruko/RKR422","Open ad") -> Open ad | P27: https://www.flokq.com/sewa-ruko-jakarta/ruko/RKR422 | Q27: RKR422 | R27: not shown on ad | S27: not shown | T27: Confirmed (rounded '20,8 juta', nego).
A28: 20 | B28: Kemang | C28: Kemang | D28: Ruko | E28: 29000000 | F28: month | G28: =IF(F28="year",E28/12,E28) -> 29000000 | H28: 170 | I28: 1 | J28: =G28/H28 -> 170588.24 | K28: S25 | M28: Kemang, Jakarta Selatan (no street given) | N28: =HYPERLINK("https://www.google.com/maps/search/?api=1&query=Kemang+Jakarta+Selatan","Google Maps") -> Google Maps | O28: =HYPERLINK("https://www.flokq.com/sewa-ruko-jakarta/ruko/RKR3c0","Open ad") -> Open ad | P28: https://www.flokq.com/sewa-ruko-jakarta/ruko/RKR3c0 | Q28: RKR3c0 | R28: not shown on ad | S28: not shown | T28: Confirmed. Near-twin of row 44 (RKR653).
A29: 21 | B29: Kemang | C29: Kemang Raya | D29: Ruko | E29: 50000000 | F29: month | G29: =IF(F29="year",E29/12,E29) -> 50000000 | H29: 120 | I29: 4 | J29: =G29/H29 -> 416666.67 | K29: S25 | M29: Jl. Kemang Raya, near Kinderfield School, Jakarta Selatan | N29: =HYPERLINK("https://www.google.com/maps/search/?api=1&query=Jl.+Kemang+Raya+Jakarta+Selatan","Google Maps") -> Google Maps | O29: =HYPERLINK("https://www.flokq.com/sewa-ruko-jakarta/ruko/RKR71d","Open ad") -> Open ad | P29: https://www.flokq.com/sewa-ruko-jakarta/ruko/RKR71d | Q29: RKR71d | R29: not shown on ad | S29: not shown | T29: Confirmed (nego).
A30: 22 | B30: Kemang | C30: Kemang Raya | D30: Ruko | E30: 29000000 | F30: month | G30: =IF(F30="year",E30/12,E30) -> 29000000 | H30: 170 | I30: 1 | J30: =G30/H30 -> 170588.24 | K30: S25 | M30: Jl. Kemang Raya, Jakarta Selatan | N30: =HYPERLINK("https://www.google.com/maps/search/?api=1&query=Jl.+Kemang+Raya+Jakarta+Selatan","Google Maps") -> Google Maps | O30: =HYPERLINK("https://www.flokq.com/sewa-ruko-jakarta/ruko/RKR653","Open ad") -> Open ad | P30: https://www.flokq.com/sewa-ruko-jakarta/ruko/RKR653 | Q30: RKR653 | R30: not shown on ad | S30: not shown | T30: Confirmed. Floors not stated in ad.
A31: 23 | B31: Kemang | C31: Kemang | D31: Ruko | E31: 16600000 | F31: month | G31: =IF(F31="year",E31/12,E31) -> 16600000 | H31: 128 | I31: 2 | J31: =G31/H31 -> 129687.5 | K31: S25 | M31: Kemang, Jakarta Selatan (no street; ad body wrongly says 'Kemang, Bogor') | N31: =HYPERLINK("https://www.google.com/maps/search/?api=1&query=Kemang+Jakarta+Selatan","Google Maps") -> Google Maps | O31: =HYPERLINK("https://www.flokq.com/sewa-ruko-jakarta/ruko/RKR545","Open ad") -> Open ad | P31: https://www.flokq.com/sewa-ruko-jakarta/ruko/RKR545 | Q31: RKR545 | R31: not shown on ad | S31: not shown | T31: Confirmed (nego).
A32: 24 | B32: Kemang | C32: Jl. Benda Raya | D32: Ruko | E32: 25000000 | F32: month | G32: =IF(F32="year",E32/12,E32) -> 25000000 | H32: 110 | I32: 1 | J32: =G32/H32 -> 227272.73 | K32: S25 | M32: Jl. Benda Raya No. 1, Kemang, Jakarta Selatan | N32: =HYPERLINK("https://www.google.com/maps/search/?api=1&query=Jl.+Benda+Raya+No.+1+Kemang+Jakarta+Selatan","Google Maps") -> Google Maps | O32: =HYPERLINK("https://www.flokq.com/sewa-ruko-jakarta/ruko/RKR7fd","Open ad") -> Open ad | P32: https://www.flokq.com/sewa-ruko-jakarta/ruko/RKR7fd | Q32: RKR7fd | R32: not shown on ad | S32: not shown | T32: Confirmed. Identical twin ad RKR961. Ad says 2 floors (model: 1).
A33: 25 | B33: Kemang | C33: Kemang Utara | D33: Ruko | E33: 25000000 | F33: month | G33: =IF(F33="year",E33/12,E33) -> 25000000 | H33: 200 | I33: 2 | J33: =G33/H33 -> 125000 | K33: S25 | M33: Jl. Kemang Utara, Jakarta Selatan | N33: =HYPERLINK("https://www.google.com/maps/search/?api=1&query=Jl.+Kemang+Utara+Jakarta+Selatan","Google Maps") -> Google Maps | O33: =HYPERLINK("https://www.flokq.com/sewa-ruko-jakarta/ruko/RKR5f6","Open ad") -> Open ad | P33: https://www.flokq.com/sewa-ruko-jakarta/ruko/RKR5f6 | Q33: RKR5f6 | R33: not shown on ad | S33: not shown | T33: Confirmed (nego).
A34: 26 | B34: Kemang | C34: Kemang Timur Raya | D34: Ruko | E34: 15000000 | F34: month | G34: =IF(F34="year",E34/12,E34) -> 15000000 | H34: 180 | I34: 2 | J34: =G34/H34 -> 83333.333 | K34: S25 | M34: Jl. Kemang Timur Raya, near Pasar Kemang, Jakarta Selatan | N34: =HYPERLINK("https://www.google.com/maps/search/?api=1&query=Jl.+Kemang+Timur+Raya+Jakarta+Selatan","Google Maps") -> Google Maps | O34: =HYPERLINK("https://www.flokq.com/sewa-ruko-jakarta/ruko/RKR729","Open ad") -> Open ad | P34: https://www.flokq.com/sewa-ruko-jakarta/ruko/RKR729 | Q34: RKR729 | R34: not shown on ad | S34: not shown | T34: Confirmed (nego).
A35: 27 | B35: Kemang | C35: Kemang Raya | D35: Ruko | E35: 29200000 | F35: month | G35: =IF(F35="year",E35/12,E35) -> 29200000 | H35: 200 | I35: 3 | J35: =G35/H35 -> 146000 | K35: S25 | M35: Jl. Kemang Raya, Jakarta Selatan | N35: =HYPERLINK("https://www.google.com/maps/search/?api=1&query=Jl.+Kemang+Raya+Jakarta+Selatan","Google Maps") -> Google Maps | O35: =HYPERLINK("https://www.flokq.com/sewa-ruko-jakarta/ruko/RKR5b3","Open ad") -> Open ad | P35: https://www.flokq.com/sewa-ruko-jakarta/ruko/RKR5b3 | Q35: RKR5b3 | R35: not shown on ad | S35: not shown | T35: Confirmed (nego).
A36: 28 | B36: Kemang | C36: Kemang Raya | D36: Ruko | E36: 23330000 | F36: month | G36: =IF(F36="year",E36/12,E36) -> 23330000 | H36: 200 | I36: 2 | J36: =G36/H36 -> 116650 | K36: S80 | M36: Jl. Kemang Raya, Mampang Prapatan, Jakarta Selatan | N36: =HYPERLINK("https://www.google.com/maps/search/?api=1&query=" & SUBSTITUTE(M36," ","+"),"Google Maps") -> Google Maps | O36: =HYPERLINK(P36,"Open ad") -> Open ad | P36: https://www.pinhome.id/disewa/ruko-sekunder/unit/disewakan-ruko-lokasi-strategis-di-kemang-raya-1 | Q36: I-78337 | R36: Indah – Agen Kantor Properti | S36: not shown (photos c. 2022) | T36: Added 8 Oct 2026; confirmed on ad. May be stale – confirm availability.
A37: 29 | B37: Kemang | C37: Bangka – 1-floor F&B unit | D37: Ruko (single level) | E37: 350000000 | F37: year | G37: =IF(F37="year",E37/12,E37) -> 29166667 | H37: 200 | I37: 1 | J37: =G37/H37 -> 145833.33 | K37: S81 | L37: Min. 2 yrs; no alcohol / non-halal | M37: Bangka, Mampang Prapatan (Kemang), Jakarta Selatan | N37: =HYPERLINK("https://www.google.com/maps/search/?api=1&query=" & SUBSTITUTE(M37," ","+"),"Google Maps") -> Google Maps | O37: =HYPERLINK(P37,"Open ad") -> Open ad | P37: https://kiosrumah.com/iklan/ruko/disewakan-ruko-kemang-1-lantai-untuk-f-b-bangka-mampang-prapat/26185 | Q37: TRK173 | R37: Roby – Century21 | S37: not shown (photos c. Nov 2024) | T37: Added 8 Oct 2026; confirmed on ad, marketed for F&B. Confirm availability.
A38: 30 | B38: Kemang | C38: Kemang Raya 10 – business space | D38: Commercial space | E38: 30000000 | F38: month | G38: =IF(F38="year",E38/12,E38) -> 30000000 | H38: 130 | J38: =G38/H38 -> 230769.23 | K38: S82 | M38: Jl. Kemang Raya, Jakarta Selatan | N38: =HYPERLINK("https://www.google.com/maps/search/?api=1&query=" & SUBSTITUTE(M38," ","+"),"Google Maps") -> Google Maps | O38: =HYPERLINK(P38,"Open results page") -> Open results page | P38: https://www.rumah123.com/en/rent/jakarta-selatan/kemang/commercial-space/ | Q38: results page only | R38: not shown | S38: not shown | T38: Added 8 Oct 2026 from results page; floors unknown.
A40: 31 | B40: PIK | C40: Jl. Elang Laut, PIK | D40: Ruko | E40: 175000000 | F40: year | G40: =IF(F40="year",E40/12,E40) -> 14583333 | H40: 160 | I40: 3.5 | J40: =G40/H40 -> 91145.833 | K40: S26 | M40: Jl. Elang Laut, PIK 1, Jakarta Utara | N40: =HYPERLINK("https://www.google.com/maps/search/?api=1&query=Jl.+Elang+Laut+PIK+Jakarta+Utara","Google Maps") -> Google Maps | O40: =HYPERLINK("https://www.brighton.co.id/cari-properti/view/ruko-3-5-lantai-di-elang-laut-pantai-indah-kapuk","Open ad") -> Open ad | P40: https://www.brighton.co.id/cari-properti/view/ruko-3-5-lantai-di-elang-laut-pantai-indah-kapuk | Q40: 091826-BRIM00005 | R40: Andy Andreas – Brighton Impact Jelambar (probable) | S40: 05 Oct 2026 | T40: Confirmed. Description says LB 76.5 (inconsistent with 160).
A41: 32 | B41: PIK | C41: Stanford Boulevard, PIK 2 | D41: Ruko | E41: 300000000 | F41: year | G41: =IF(F41="year",E41/12,E41) -> 25000000 | H41: 197 | J41: =G41/H41 -> 126903.55 | K41: S26 | M41: Ruko Stanford Boulevard, unit A6, PIK 2, Jakarta Utara | N41: =HYPERLINK("https://www.google.com/maps/search/?api=1&query=Stanford+Boulevard+PIK+2","Google Maps") -> Google Maps | O41: =HYPERLINK("https://www.brighton.co.id/cari-properti/view/ruko-pik-2-stanford-boulevard-hadap-jalan-utama","Open ad") -> Open ad | P41: https://www.brighton.co.id/cari-properti/view/ruko-pik-2-stanford-boulevard-hadap-jalan-utama | Q41: 311026-PROBS00022 | R41: not shown on ad | S41: 02 Oct 2026 | T41: Confirmed. 285m/yr on 2-yr lease, 275m on 3-yr; deposit 35m.
A42: 33 | B42: PIK | C42: Pasadena Walk, PIK 2 | D42: Ruko | E42: 80000000 | F42: year | G42: =IF(F42="year",E42/12,E42) -> 6666666.7 | H42: 141 | J42: =G42/H42 -> 47281.324 | K42: S26 | M42: Pasadena Walk, PIK 2, Jakarta Utara | N42: =HYPERLINK("https://www.google.com/maps/search/?api=1&query=Pasadena+Walk+PIK+2","Google Maps") -> Google Maps | O42: =HYPERLINK("https://www.brighton.co.id/disewa/ruko/jakarta-utara/pantai-indah-kapuk","Open results page") -> Open results page | P42: https://www.brighton.co.id/disewa/ruko/jakarta-utara/pantai-indah-kapuk | Q42: not found | R42: not shown on ad | S42: not shown | T42: NOT FOUND – individual ad not traceable (removed or on page 2+). Treat as unverified.
C45: Reference: Jakarta mall average (Colliers Q4 2024, S27): rent IDR 564,400 + service charge IDR 154,035 per m²/month
A48: SOURCES & CALCULATION BASIS – Rent_Data
A49: Figure / cells | D49: Value used (live) | E49: Source ID(s) → Sources sheet | H49: How the figure was derived from the source | M49: Evidence status
A50: Asking rent, period, m², floors (cols E, F, H, I) | D50: — | E50: Per row in col K: S20–S26, S78–S82 | H50: Copied from each listing as advertised (accessed 6–8 Oct 2026). Surface m² = total rented surface of the unit, all floors (LB for a ruko). | M50: Sourced
A51: Monthly rent (col G) | D51: — | E51: — | H51: Formula: asking rent ÷ 12 when quoted per year. | M51: Model formula
A52: IDR / m² / month (col J) | D52: — | E52: — | H52: Formula: monthly rent ÷ building m². Feeds P25 / median / P75 on the Location sheet. | M52: Model formula
A53: Mall reference (row 45) | D53: — | E53: S27 | H53: Colliers Q4 2024: IDR 564,400 rent + 154,035 service charge per m² per month. | M53: Sourced
A54: Limitation | D54: — | E54: S28 (JLL), S29 (CBRE) | H54: Asking ≠ deal rents. Thin samples: Senopati main road 1 (fallback in use), Kuningan 2, PIK 3. Validate with 2 brokers. | M54: Partly sourced
A55: Location & ad trail (cols M–T) | D55: — | E55: S20–S26 individual ads (col P) | H55: Each row traced to its individual ad (URL, ID, advertiser, date) where the ad page opened; otherwise the results page is linked (col T says so). 33 listings, all 100–200 m². 6 added on 8 Oct 2026 (Senopati main road, Cipaku, Epiwalk, 3× Kemang). | M55: Partly sourced

Sheet Location
A1: Location Economics – District Comparison
A2: Rent statistics come from Rent_Data. Scores and demand index are judgement inputs (blue) – replace with field observation (footfall counts, competitor mapping).
A3: Note from Jonas: | B3: Georaphical information would be really interesting to assess the areas.
B4: The choice of criteria as well as their weight may be edited depending on goals and findings from group1
A5: Criteria weights → | I5: 0.2 | J5: 0.2 | K5: 0.2 | L5: 0.2 | M5: 0.1 | N5: 0.1 | O5: =SUM(I5:N5) -> 1
A7: District | B7: Tier | C7: Rent P25 (IDR/m²/mo) | D7: Rent median | E7: Rent P75 | F7: n | G7: Service charge IDR/m²/mo | H7: Demand index (Senopati=1) | I7: Footfall | J7: Office density | K7: Target-customer fit | L7: Visibility / street | M7: Competition (5=low) | N7: Access (MRT etc.) | O7: Weighted score (/5) | P7: Monthly rent+SC for model unit | Q7: Est. monthly revenue | R7: Occupancy cost % of revenue | S7: Est. EBITDA / month | T7: Break-even revenue / day | U7: Rent cap @12% → max monthly rent | V7: Main-road premium × (used while n < 3)
A8: SCBD | B8: 1 | C8: =PERCENTILE(Rent_Data!$J$8:$J$9,0.25) -> 364345.55 | D8: =MEDIAN(Rent_Data!$J$8:$J$9) -> 408691.1 | E8: =PERCENTILE(Rent_Data!$J$8:$J$9,0.75) -> 453036.65 | F8: =COUNT(Rent_Data!$J$8:$J$9) -> 2 | G8: 120000 | H8: 1.1 | O8: =SUMPRODUCT(I8:N8,$I$5:$N$5) -> 0 | P8: =(D8*(1+Inputs!$H$27)+G8)*Inputs!$H$21*Inputs!$H$22 -> 79303665 | Q8: =Scenarios!$F$13*H8 -> 8.09193e+08 | R8: =P8/Q8 -> 0.0980034 | S8: =Q8*Scenarios!$F$24-(Scenarios!$F$32+P8) -> 1.3585215e+08 | T8: =(Scenarios!$F$32+P8)/Scenarios!$F$24/Inputs!$H$12 -> 19152452 | U8: =0.12*Q8 -> 97103160
A9: Senopati main road | B9: 1 | C9: =IF($F$9>=3,PERCENTILE(Rent_Data!$J$11:$J$11,0.25),C10*$V$9) -> 205161.38 | D9: =IF($F$9>=3,MEDIAN(Rent_Data!$J$11:$J$11),D10*$V$9) -> 251828.12 | E9: =IF($F$9>=3,PERCENTILE(Rent_Data!$J$11:$J$11,0.75),E10*$V$9) -> 351857.87 | F9: =COUNT(Rent_Data!$J$11:$J$11) -> 1 | G9: 0 | H9: 1 | O9: =SUMPRODUCT(I9:N9,$I$5:$N$5) -> 0 | P9: =(D9*(1+Inputs!$H$27)+G9)*Inputs!$H$21*Inputs!$H$22 -> 37774219 | Q9: =Scenarios!$F$13*H9 -> 735630000 | R9: =P9/Q9 -> 0.051349481 | S9: =Q9*Scenarios!$F$24-(Scenarios!$F$32+P9) -> 1.3478627e+08 | T9: =(Scenarios!$F$32+P9)/Scenarios!$F$24/Inputs!$H$12 -> 16761712 | U9: =0.12*Q9 -> 88275600 | V9: 2.27
A10: Senopati side streets | B10: 1 | C10: =PERCENTILE(Rent_Data!$J$13:$J$22,0.25) -> 90379.464 | D10: =MEDIAN(Rent_Data!$J$13:$J$22) -> 110937.5 | E10: =PERCENTILE(Rent_Data!$J$13:$J$22,0.75) -> 155003.47 | F10: =COUNT(Rent_Data!$J$13:$J$22) -> 10 | G10: 0 | H10: 0.9 | O10: =SUMPRODUCT(I10:N10,$I$5:$N$5) -> 0 | P10: =(D10*(1+Inputs!$H$27)+G10)*Inputs!$H$21*Inputs!$H$22 -> 16640625 | Q10: =Scenarios!$F$13*H10 -> 662067000 | R10: =P10/Q10 -> 0.025134352 | S10: =Q10*Scenarios!$F$24-(Scenarios!$F$32+P10) -> 1.1332454e+08 | T10: =(Scenarios!$F$32+P10)/Scenarios!$F$24/Inputs!$H$12 -> 15545107 | U10: =0.12*Q10 -> 79448040
A11: Kuningan | B11: 1 | C11: =PERCENTILE(Rent_Data!$J$24:$J$25,0.25) -> 267045.45 | D11: =MEDIAN(Rent_Data!$J$24:$J$25) -> 284090.91 | E11: =PERCENTILE(Rent_Data!$J$24:$J$25,0.75) -> 301136.36 | F11: =COUNT(Rent_Data!$J$24:$J$25) -> 2 | G11: 50000 | H11: 0.9 | O11: =SUMPRODUCT(I11:N11,$I$5:$N$5) -> 0 | P11: =(D11*(1+Inputs!$H$27)+G11)*Inputs!$H$21*Inputs!$H$22 -> 50113636 | Q11: =Scenarios!$F$13*H11 -> 662067000 | R11: =P11/Q11 -> 0.075692696 | S11: =Q11*Scenarios!$F$24-(Scenarios!$F$32+P11) -> 79851526 | T11: =(Scenarios!$F$32+P11)/Scenarios!$F$24/Inputs!$H$12 -> 17472059 | U11: =0.12*Q11 -> 79448040
A12: Kemang | B12: 2 | C12: =PERCENTILE(Rent_Data!$J$27:$J$38,0.25) -> 124338.24 | D12: =MEDIAN(Rent_Data!$J$27:$J$38) -> 145916.67 | E12: =PERCENTILE(Rent_Data!$J$27:$J$38,0.75) -> 184759.36 | F12: =COUNT(Rent_Data!$J$27:$J$38) -> 12 | G12: 0 | H12: 0.85 | O12: =SUMPRODUCT(I12:N12,$I$5:$N$5) -> 0 | P12: =(D12*(1+Inputs!$H$27)+G12)*Inputs!$H$21*Inputs!$H$22 -> 21887500 | Q12: =Scenarios!$F$13*H12 -> 625285500 | R12: =P12/Q12 -> 0.03500401 | S12: =Q12*Scenarios!$F$24-(Scenarios!$F$32+P12) -> 86779999 | T12: =(Scenarios!$F$32+P12)/Scenarios!$F$24/Inputs!$H$12 -> 15847156 | U12: =0.12*Q12 -> 75034260
A13: PIK | B13: 2 | C13: =PERCENTILE(Rent_Data!$J$40:$J$42,0.25) -> 69213.579 | D13: =MEDIAN(Rent_Data!$J$40:$J$42) -> 91145.833 | E13: =PERCENTILE(Rent_Data!$J$40:$J$42,0.75) -> 109024.69 | F13: =COUNT(Rent_Data!$J$40:$J$42) -> 3 | G13: 0 | H13: 0.95 | O13: =SUMPRODUCT(I13:N13,$I$5:$N$5) -> 0 | P13: =(D13*(1+Inputs!$H$27)+G13)*Inputs!$H$21*Inputs!$H$22 -> 13671875 | Q13: =Scenarios!$F$13*H13 -> 698848500 | R13: =P13/Q13 -> 0.019563432 | S13: =Q13*Scenarios!$F$24-(Scenarios!$F$32+P13) -> 1.3759095e+08 | T13: =(Scenarios!$F$32+P13)/Scenarios!$F$24/Inputs!$H$12 -> 15374204 | U13: =0.12*Q13 -> 83861820
A16: How to read: rent stats are per m² of total building area (ruko = whole multi-storey building). Model rent = rate × usable m² × GFA factor (Inputs).
A17: Columns Q–T use the ACTIVE scenario steady-state economics (Scenarios sheet) scaled by the district demand index; only rent & service charge change by district.
A18: Occupancy cost benchmark: total rent + service charge ideally ≤ 10–12% of revenue for full-service restaurants (industry rule of thumb – verify with Jakarta operators).
A19: Upgrade path: replace demand index with a Huff gravity estimate (S40/S41) or with footfall counts at 3 comparable venues per district (Methods sheet).
A20: Filter: 100–200 m² of rented surface (all floors, any format: ruko, mall unit, single level). Senopati main road has <3 listings → rent = side streets × premium V8 until ≥3 are added (switches automatically). Kuningan n=2 – low confidence.
A23: SOURCES & CALCULATION BASIS – Location
A24: Figure / cells | D24: Value used (live) | F24: Source ID(s) → Sources sheet | I24: How the figure was derived from the source | Q24: Evidence status
A25: Rent P25 / median / P75, n (cols C–F) | D25: =Location!D9 -> 251828.12 | F25: S20–S26 via Rent_Data | I25: PERCENTILE / MEDIAN / COUNT over each district's IDR per m² of rented surface per month in Rent_Data (listings of 100–200 m²). Senopati main road: if fewer than 3 listings, side-street stats × premium V8 = 2.27 (ratio of main-road to side-street medians in the unfiltered v0.3 sample, 270.6k / 119.2k). | Q25: Derived from sources
A26: Service charge (col G) | D26: =Location!G8 -> 120000 | F26: S27; S22/S23 | I26: Street ruko = 0. SCBD 120k: podium/office F&B listings quote rent 'excl. service charge' (S23); set below the Colliers mall average of 154k (S27). Kuningan 50k = mix of ruko and mall units. Estimates. | Q26: Partly sourced
A27: Demand index (col H) | D27: =Location!H9 -> 1 | F27: S46 Volume_Proxy (in-zone velocity); S28/S29 | I27: Relative revenue potential vs Senopati = 1.0. Team judgement informed by competitor review velocity; replace with a Huff gravity estimate (S40/S41). | Q27: Assumption – validate
A28: Criteria scores (cols I–N, 1–5) | D28: — | F28: S28, S29, S46, S30 | I28: Team scoring of footfall, office density, customer fit, visibility, competition, access. Qualitative – document evidence per score after field visits. | Q28: Assumption – validate
A29: Criteria weights (I4:N4) | D29: =Location!O5 -> 1 | F29: — | I29: Team weighting (sum = 100%). | Q29: Decision / policy
A30: Est. revenue, EBITDA, break-even (cols Q–T) | D30: =Location!Q9 -> 735630000 | F30: Scenarios sheet | I30: Active-scenario steady state × demand index, with the district's own rent. | Q30: Model formula
A31: Occupancy cost % (col R) and rent cap 12% (col U) | D31: =Location!R9 -> 0.051349481 | F31: S49 (10%, ideal 6–7%); S51 (≤8–10%) | I31: Rent + SC ÷ revenue. Note the 12% cap in col U is above both benchmarks – a strict test would use 10%. | Q31: Derived from sources

Sheet Menu
A1: Menu, Pricing & Food Cost (Kasavana–Smith menu engineering)
A2: ILLUSTRATIVE placeholder menu – replace prices with your pricing decision and food costs with recipe costing from supplier quotes. Prices are NET of 10% PBJT.
A3: Note Jonas | B3: This sheets gives an idea of pricing of potential dishes and takes as source the comparisons provided by expanding Tiago's datasets (italian restaurants in Jakarta)
B4: It will be more relevant with team 1 inputs on potential menu, numbers such as COGS, popularity will be much better estimated
B5: The CORSA pricing is here to give an idea, but not definitive at all
A6: Category | B6: Item | C6: Price net (IDR) | D6: Food cost (IDR) | E6: Cost % | F6: Contribution (IDR) | G6: Units per 100 guests | H6: Revenue / 100 guests | I6: Cost / 100 guests | J6: Revenue mix | K6: Popularity in category | L6: Menu-engineering class | M6: CM × units (helper) | N6: Guest price incl. PBJT | O6: Price benchmark (source) | P6: Food-cost benchmark & check | Q6: Evidence status
A7: Pasta | B7: Cacio e pepe | C7: 89000 | D7: 24000 | E7: =D7/C7 -> 0.26966292 | F7: =C7-D7 -> 65000 | G7: 12 | H7: =C7*G7 -> 1068000 | I7: =D7*G7 -> 288000 | J7: =H7/SUM($H$7:$H$26) -> 0.10667199 | K7: =G7/SUMIF($A$7:$A$26,A7,$G$7:$G$26) -> 0.21818182 | L7: =IF(AND(F7>=SUMIF($A$7:$A$26,A7,$M$7:$M$26)/SUMIF($A$7:$A$26,A7,$G$7:$G$26),K7>=0.7/COUNTIF($A$7:$A$26,A7)),"Star",IF(K7>=0.7/COUNTIF($A$7:$A$26,A7),"Plowhorse",IF(F7>=SUMIF($A$7:$A$26,A7,$M$7:$M$26)/SUMIF($A$7:$A$26,A7,$G$7:$G$26),"Puzzle","Dog"))) -> Plowhorse | M7: =F7*G7 -> 780000 | N7: =C7*(1+Inputs!$H$17) -> 97900 | O7: S46: in-zone pasta venue medians avg ~133k (9 venues), mid-premium tier 80–165k; PBTP Blok M ~80k; S33 Pasta, Bitte! 86k, Toscana 155k | P7: Cost 27% vs S50 food 28–35%; S49 FSR max 30.3% → below range. Item cost itself = estimate, recipe costing pending. | Q7: Partly sourced
A8: Pasta | B8: Carbonara (beef bacon, halal) | C8: 98000 | D8: 30000 | E8: =D8/C8 -> 0.30612245 | F8: =C8-D8 -> 68000 | G8: 15 | H8: =C8*G8 -> 1470000 | I8: =D8*G8 -> 450000 | J8: =H8/SUM($H$7:$H$26) -> 0.14682381 | K8: =G8/SUMIF($A$7:$A$26,A8,$G$7:$G$26) -> 0.27272727 | L8: =IF(AND(F8>=SUMIF($A$7:$A$26,A8,$M$7:$M$26)/SUMIF($A$7:$A$26,A8,$G$7:$G$26),K8>=0.7/COUNTIF($A$7:$A$26,A8)),"Star",IF(K8>=0.7/COUNTIF($A$7:$A$26,A8),"Plowhorse",IF(F8>=SUMIF($A$7:$A$26,A8,$M$7:$M$26)/SUMIF($A$7:$A$26,A8,$G$7:$G$26),"Puzzle","Dog"))) -> Plowhorse | M8: =F8*G8 -> 1020000 | N8: =C8*(1+Inputs!$H$17) -> 107800 | O8: S46: in-zone pasta venue medians avg ~133k (9 venues), mid-premium tier 80–165k; PBTP Blok M ~80k; S33 Pasta, Bitte! 86k, Toscana 155k | P8: Cost 31% vs S50 food 28–35%; S49 FSR max 30.3% → within range. Item cost itself = estimate, recipe costing pending. | Q8: Partly sourced
A9: Pasta | B9: Ragù bolognese | C9: 105000 | D9: 34000 | E9: =D9/C9 -> 0.32380952 | F9: =C9-D9 -> 71000 | G9: 11 | H9: =C9*G9 -> 1155000 | I9: =D9*G9 -> 374000 | J9: =H9/SUM($H$7:$H$26) -> 0.11536157 | K9: =G9/SUMIF($A$7:$A$26,A9,$G$7:$G$26) -> 0.2 | L9: =IF(AND(F9>=SUMIF($A$7:$A$26,A9,$M$7:$M$26)/SUMIF($A$7:$A$26,A9,$G$7:$G$26),K9>=0.7/COUNTIF($A$7:$A$26,A9)),"Star",IF(K9>=0.7/COUNTIF($A$7:$A$26,A9),"Plowhorse",IF(F9>=SUMIF($A$7:$A$26,A9,$M$7:$M$26)/SUMIF($A$7:$A$26,A9,$G$7:$G$26),"Puzzle","Dog"))) -> Star | M9: =F9*G9 -> 781000 | N9: =C9*(1+Inputs!$H$17) -> 115500 | O9: S46: in-zone pasta venue medians avg ~133k (9 venues), mid-premium tier 80–165k; PBTP Blok M ~80k; S33 Pasta, Bitte! 86k, Toscana 155k | P9: Cost 32% vs S50 food 28–35%; S49 FSR max 30.3% → within range. Item cost itself = estimate, recipe costing pending. | Q9: Partly sourced
A10: Pasta | B10: Pesto genovese | C10: 95000 | D10: 28000 | E10: =D10/C10 -> 0.29473684 | F10: =C10-D10 -> 67000 | G10: 8 | H10: =C10*G10 -> 760000 | I10: =D10*G10 -> 224000 | J10: =H10/SUM($H$7:$H$26) -> 0.075908909 | K10: =G10/SUMIF($A$7:$A$26,A10,$G$7:$G$26) -> 0.14545455 | L10: =IF(AND(F10>=SUMIF($A$7:$A$26,A10,$M$7:$M$26)/SUMIF($A$7:$A$26,A10,$G$7:$G$26),K10>=0.7/COUNTIF($A$7:$A$26,A10)),"Star",IF(K10>=0.7/COUNTIF($A$7:$A$26,A10),"Plowhorse",IF(F10>=SUMIF($A$7:$A$26,A10,$M$7:$M$26)/SUMIF($A$7:$A$26,A10,$G$7:$G$26),"Puzzle","Dog"))) -> Plowhorse | M10: =F10*G10 -> 536000 | N10: =C10*(1+Inputs!$H$17) -> 104500 | O10: S46: in-zone pasta venue medians avg ~133k (9 venues), mid-premium tier 80–165k; PBTP Blok M ~80k; S33 Pasta, Bitte! 86k, Toscana 155k | P10: Cost 29% vs S50 food 28–35%; S49 FSR max 30.3% → within range. Item cost itself = estimate, recipe costing pending. | Q10: Partly sourced
A11: Pasta | B11: Truffle cream | C11: 135000 | D11: 45000 | E11: =D11/C11 -> 0.33333333 | F11: =C11-D11 -> 90000 | G11: 5 | H11: =C11*G11 -> 675000 | I11: =D11*G11 -> 225000 | J11: =H11/SUM($H$7:$H$26) -> 0.067419097 | K11: =G11/SUMIF($A$7:$A$26,A11,$G$7:$G$26) -> 0.090909091 | L11: =IF(AND(F11>=SUMIF($A$7:$A$26,A11,$M$7:$M$26)/SUMIF($A$7:$A$26,A11,$G$7:$G$26),K11>=0.7/COUNTIF($A$7:$A$26,A11)),"Star",IF(K11>=0.7/COUNTIF($A$7:$A$26,A11),"Plowhorse",IF(F11>=SUMIF($A$7:$A$26,A11,$M$7:$M$26)/SUMIF($A$7:$A$26,A11,$G$7:$G$26),"Puzzle","Dog"))) -> Puzzle | M11: =F11*G11 -> 450000 | N11: =C11*(1+Inputs!$H$17) -> 148500 | O11: S46: in-zone pasta venue medians avg ~133k (9 venues), mid-premium tier 80–165k; PBTP Blok M ~80k; S33 Pasta, Bitte! 86k, Toscana 155k | P11: Cost 33% vs S50 food 28–35%; S49 FSR max 30.3% → within range. Item cost itself = estimate, recipe costing pending. | Q11: Partly sourced
A12: Pasta | B12: Arrabbiata (vegan) | C12: 82000 | D12: 20000 | E12: =D12/C12 -> 0.24390244 | F12: =C12-D12 -> 62000 | G12: 4 | H12: =C12*G12 -> 328000 | I12: =D12*G12 -> 80000 | J12: =H12/SUM($H$7:$H$26) -> 0.032760687 | K12: =G12/SUMIF($A$7:$A$26,A12,$G$7:$G$26) -> 0.072727273 | L12: =IF(AND(F12>=SUMIF($A$7:$A$26,A12,$M$7:$M$26)/SUMIF($A$7:$A$26,A12,$G$7:$G$26),K12>=0.7/COUNTIF($A$7:$A$26,A12)),"Star",IF(K12>=0.7/COUNTIF($A$7:$A$26,A12),"Plowhorse",IF(F12>=SUMIF($A$7:$A$26,A12,$M$7:$M$26)/SUMIF($A$7:$A$26,A12,$G$7:$G$26),"Puzzle","Dog"))) -> Dog | M12: =F12*G12 -> 248000 | N12: =C12*(1+Inputs!$H$17) -> 90200 | O12: S46: in-zone pasta venue medians avg ~133k (9 venues), mid-premium tier 80–165k; PBTP Blok M ~80k; S33 Pasta, Bitte! 86k, Toscana 155k | P12: Cost 24% vs S50 food 28–35%; S49 FSR max 30.3% → below range. Item cost itself = estimate, recipe costing pending. | Q12: Partly sourced
A13: Coffee | B13: Espresso | C13: 32000 | D13: 6000 | E13: =D13/C13 -> 0.1875 | F13: =C13-D13 -> 26000 | G13: 5 | H13: =C13*G13 -> 160000 | I13: =D13*G13 -> 30000 | J13: =H13/SUM($H$7:$H$26) -> 0.015980823 | K13: =G13/SUMIF($A$7:$A$26,A13,$G$7:$G$26) -> 0.1 | L13: =IF(AND(F13>=SUMIF($A$7:$A$26,A13,$M$7:$M$26)/SUMIF($A$7:$A$26,A13,$G$7:$G$26),K13>=0.7/COUNTIF($A$7:$A$26,A13)),"Star",IF(K13>=0.7/COUNTIF($A$7:$A$26,A13),"Plowhorse",IF(F13>=SUMIF($A$7:$A$26,A13,$M$7:$M$26)/SUMIF($A$7:$A$26,A13,$G$7:$G$26),"Puzzle","Dog"))) -> Dog | M13: =F13*G13 -> 130000 | N13: =C13*(1+Inputs!$H$17) -> 35200 | O13: S31: Common Grounds espresso 32k (= model price) | P13: Cost 19% vs S49 coffee bev. cost 15–20%; S50 beverage 15–25% → within range. Item cost itself = estimate, recipe costing pending. | Q13: Partly sourced
A14: Coffee | B14: Americano (hot/iced) | C14: 40000 | D14: 7000 | E14: =D14/C14 -> 0.175 | F14: =C14-D14 -> 33000 | G14: 12 | H14: =C14*G14 -> 480000 | I14: =D14*G14 -> 84000 | J14: =H14/SUM($H$7:$H$26) -> 0.047942469 | K14: =G14/SUMIF($A$7:$A$26,A14,$G$7:$G$26) -> 0.24 | L14: =IF(AND(F14>=SUMIF($A$7:$A$26,A14,$M$7:$M$26)/SUMIF($A$7:$A$26,A14,$G$7:$G$26),K14>=0.7/COUNTIF($A$7:$A$26,A14)),"Star",IF(K14>=0.7/COUNTIF($A$7:$A$26,A14),"Plowhorse",IF(F14>=SUMIF($A$7:$A$26,A14,$M$7:$M$26)/SUMIF($A$7:$A$26,A14,$G$7:$G$26),"Puzzle","Dog"))) -> Plowhorse | M14: =F14*G14 -> 396000 | N14: =C14*(1+Inputs!$H$17) -> 44000 | O14: S46: latte 27–30k casual, 38–48k smart-casual/specialty, 55–60k mall; S31 Common Grounds latte 45–52k, espresso 32k | P14: Cost 18% vs S49 coffee bev. cost 15–20%; S50 beverage 15–25% → within range. Item cost itself = estimate, recipe costing pending. | Q14: Partly sourced
A15: Coffee | B15: Latte / flat white | C15: 50000 | D15: 12000 | E15: =D15/C15 -> 0.24 | F15: =C15-D15 -> 38000 | G15: 19 | H15: =C15*G15 -> 950000 | I15: =D15*G15 -> 228000 | J15: =H15/SUM($H$7:$H$26) -> 0.094886137 | K15: =G15/SUMIF($A$7:$A$26,A15,$G$7:$G$26) -> 0.38 | L15: =IF(AND(F15>=SUMIF($A$7:$A$26,A15,$M$7:$M$26)/SUMIF($A$7:$A$26,A15,$G$7:$G$26),K15>=0.7/COUNTIF($A$7:$A$26,A15)),"Star",IF(K15>=0.7/COUNTIF($A$7:$A$26,A15),"Plowhorse",IF(F15>=SUMIF($A$7:$A$26,A15,$M$7:$M$26)/SUMIF($A$7:$A$26,A15,$G$7:$G$26),"Puzzle","Dog"))) -> Star | M15: =F15*G15 -> 722000 | N15: =C15*(1+Inputs!$H$17) -> 55000 | O15: S46: latte 27–30k casual, 38–48k smart-casual/specialty, 55–60k mall; S31 Common Grounds latte 45–52k, espresso 32k | P15: Cost 24% vs S49 coffee bev. cost 15–20%; S50 beverage 15–25% → within range. Item cost itself = estimate, recipe costing pending. | Q15: Partly sourced
A16: Coffee | B16: Signature iced coffee | C16: 58000 | D16: 14000 | E16: =D16/C16 -> 0.24137931 | F16: =C16-D16 -> 44000 | G16: 10 | H16: =C16*G16 -> 580000 | I16: =D16*G16 -> 140000 | J16: =H16/SUM($H$7:$H$26) -> 0.057930483 | K16: =G16/SUMIF($A$7:$A$26,A16,$G$7:$G$26) -> 0.2 | L16: =IF(AND(F16>=SUMIF($A$7:$A$26,A16,$M$7:$M$26)/SUMIF($A$7:$A$26,A16,$G$7:$G$26),K16>=0.7/COUNTIF($A$7:$A$26,A16)),"Star",IF(K16>=0.7/COUNTIF($A$7:$A$26,A16),"Plowhorse",IF(F16>=SUMIF($A$7:$A$26,A16,$M$7:$M$26)/SUMIF($A$7:$A$26,A16,$G$7:$G$26),"Puzzle","Dog"))) -> Star | M16: =F16*G16 -> 440000 | N16: =C16*(1+Inputs!$H$17) -> 63800 | O16: S46: latte 27–30k casual, 38–48k smart-casual/specialty, 55–60k mall; S31 Common Grounds latte 45–52k, espresso 32k | P16: Cost 24% vs S49 coffee bev. cost 15–20%; S50 beverage 15–25% → within range. Item cost itself = estimate, recipe costing pending. | Q16: Partly sourced
A17: Coffee | B17: Filter / manual brew | C17: 55000 | D17: 12000 | E17: =D17/C17 -> 0.21818182 | F17: =C17-D17 -> 43000 | G17: 4 | H17: =C17*G17 -> 220000 | I17: =D17*G17 -> 48000 | J17: =H17/SUM($H$7:$H$26) -> 0.021973632 | K17: =G17/SUMIF($A$7:$A$26,A17,$G$7:$G$26) -> 0.08 | L17: =IF(AND(F17>=SUMIF($A$7:$A$26,A17,$M$7:$M$26)/SUMIF($A$7:$A$26,A17,$G$7:$G$26),K17>=0.7/COUNTIF($A$7:$A$26,A17)),"Star",IF(K17>=0.7/COUNTIF($A$7:$A$26,A17),"Plowhorse",IF(F17>=SUMIF($A$7:$A$26,A17,$M$7:$M$26)/SUMIF($A$7:$A$26,A17,$G$7:$G$26),"Puzzle","Dog"))) -> Puzzle | M17: =F17*G17 -> 172000 | N17: =C17*(1+Inputs!$H$17) -> 60500 | O17: S46: latte 27–30k casual, 38–48k smart-casual/specialty, 55–60k mall; S31 Common Grounds latte 45–52k, espresso 32k | P17: Cost 22% vs S49 coffee bev. cost 15–20%; S50 beverage 15–25% → within range. Item cost itself = estimate, recipe costing pending. | Q17: Partly sourced
A18: Functional drinks | B18: Matcha / protein shake | C18: 55000 | D18: 15000 | E18: =D18/C18 -> 0.27272727 | F18: =C18-D18 -> 40000 | G18: 6 | H18: =C18*G18 -> 330000 | I18: =D18*G18 -> 90000 | J18: =H18/SUM($H$7:$H$26) -> 0.032960447 | K18: =G18/SUMIF($A$7:$A$26,A18,$G$7:$G$26) -> 0.6 | L18: =IF(AND(F18>=SUMIF($A$7:$A$26,A18,$M$7:$M$26)/SUMIF($A$7:$A$26,A18,$G$7:$G$26),K18>=0.7/COUNTIF($A$7:$A$26,A18)),"Star",IF(K18>=0.7/COUNTIF($A$7:$A$26,A18),"Plowhorse",IF(F18>=SUMIF($A$7:$A$26,A18,$M$7:$M$26)/SUMIF($A$7:$A$26,A18,$G$7:$G$26),"Puzzle","Dog"))) -> Star | M18: =F18*G18 -> 240000 | N18: =C18*(1+Inputs!$H$17) -> 60500 | O18: S46: non-coffee drinks in-zone avg ~44k (5 venues); S46 PBTP matcha latte 55k | P18: Cost 27% vs S50 beverage 15–25% → ABOVE range. Item cost itself = estimate, recipe costing pending. | Q18: Partly sourced
... A26: Add-ons | B26: Oat milk / extra shot | C26: 9000 | D26: 3000 | E26: =D26/C26 -> 0.33333333 | F26: =C26-D26 -> 6000 | G26: 6 | H26: =C26*G26 -> 54000 | I26: =D26*G26 -> 18000 | J26: =H26/SUM($H$7:$H$26) -> 0.0053935278 | K26: =G26/SUMIF($A$7:$A$26,A26,$G$7:$G$26) -> 0.4 | L26: =IF(AND(F26>=SUMIF($A$7:$A$26,A26,$M$7:$M$26)/SUMIF($A$7:$A$26,A26,$G$7:$G$26),K26>=0.7/COUNTIF($A$7:$A$26,A26)),"Star",IF(K26>=0.7/COUNTIF($A$7:$A$26,A26),"Plowhorse",IF(F26>=SUMIF($A$7:$A$26,A26,$M$7:$M$26)/SUMIF($A$7:$A$26,A26,$G$7:$G$26),"Puzzle","Dog"))) -> Plowhorse | M26: =F26*G26 -> 36000 | N26: =C26*(1+Inputs!$H$17) -> 9900 | O26: No direct benchmark – priced as % uplift on mains | P26: Cost 33% vs S50 food 28–35% → within range. Item cost itself = estimate, recipe costing pending. | Q26: Partly sourced
B27: TOTAL / BLENDED | G27: =SUM(G7:G26) -> 155 | H27: =SUM(H7:H26) -> 10012000 | I27: =SUM(I7:I26) -> 2865000
B29: Blended F&B food & beverage cost % (feeds the model) | E29: =I27/H27 -> 0.28615661
B30: Implied average net spend per guest (menu mix) | E30: =H27/100 -> 100120 | F30: vs. revenue model blended spend → | H30: =Revenue!$E$16 -> 103375 | I30: =IF(ABS(E30/H30-1)>0.15,"Check: >15% gap","OK") -> OK
A32: Category | B32: Revenue share | C32: Cost %
A33: Pasta | B33: =SUMIF($A$7:$A$26,A33,$H$7:$H$26)/$H$27 -> 0.54494606 | C33: =SUMIF($A$7:$A$26,A33,$I$7:$I$26)/SUMIF($A$7:$A$26,A33,$H$7:$H$26) -> 0.30076979
A34: Coffee | B34: =SUMIF($A$7:$A$26,A34,$H$7:$H$26)/$H$27 -> 0.23871354 | C34: =SUMIF($A$7:$A$26,A34,$I$7:$I$26)/SUMIF($A$7:$A$26,A34,$H$7:$H$26) -> 0.22175732
A35: Functional drinks | B35: =SUMIF($A$7:$A$26,A35,$H$7:$H$26)/$H$27 -> 0.052137435 | C35: =SUMIF($A$7:$A$26,A35,$I$7:$I$26)/SUMIF($A$7:$A$26,A35,$H$7:$H$26) -> 0.27969349
A36: Breakfast & snacks | B36: =SUMIF($A$7:$A$26,A36,$H$7:$H$26)/$H$27 -> 0.1363364 | C36: =SUMIF($A$7:$A$26,A36,$I$7:$I$26)/SUMIF($A$7:$A$26,A36,$H$7:$H$26) -> 0.31794872
A37: Add-ons | B37: =SUMIF($A$7:$A$26,A37,$H$7:$H$26)/$H$27 -> 0.02786656 | C37: =SUMIF($A$7:$A$26,A37,$I$7:$I$26)/SUMIF($A$7:$A$26,A37,$H$7:$H$26) -> 0.40860215
A39: COMPETITOR PRICE BENCHMARKS (collect 10–15 comparables; dine-in prices preferred over delivery-app prices)
A40: Venue | B40: Item | C40: Price (IDR) | D40: Channel | E40: Area | F40: Source
A41: Common Grounds | B41: Latte | C41: 48000 | D41: Dine-in (range 45–52k) | E41: Various | F41: S31
A42: Common Grounds | B42: Espresso | C42: 32000 | D42: Dine-in | E42: Various | F42: S31
A43: Common Grounds | B43: Tobiko truffle pasta | C43: 97500 | D43: Dine-in (85–110k) | E43: Various | F43: S31
A44: Common Grounds Citywalk | B44: Café latte | C44: 61100 | D44: Delivery app | E44: Sudirman | F44: S32
A45: Common Grounds Citywalk | B45: Mac and cheese | C45: 113600 | D45: Delivery app | E45: Sudirman | F45: S32
A46: Pasta, Bitte! | B46: Smoked beef carbonara | C46: 86000 | D46: Dine-in | E46: Kemang | F46: S33
A47: Toscana | B47: Spaghetti con vongole | C47: 155000 | D47: Dine-in | E47: Kemang | F47: S33
A48: Caffè Milano | B48: Per person band | C48: 75000 | D48: Mid-point of 50–100k | E48: Grand Indonesia | F48: S34
A49: Warung Pasta | B49: Pasta | C49: 32500 | D49: Mid-point of 18–47k (value) | E49: Kemang | F49: S34
A51: Kasavana–Smith rule: Star = high contribution & popularity ≥ 70% of fair share in its category; Plowhorse = popular/low CM; Puzzle = high CM/unpopular; Dog = both low (S39).
A54: SOURCES & CALCULATION BASIS – Menu
A55: Figure / cells | C55: Value used (live) | E55: Source ID(s) → Sources sheet | H55: How the figure was derived from the source | O55: Evidence status
A56: Net prices C5:C24 | C56: =Menu!E30 -> 100120 | E56: S46, S31, S33, S34 | H56: Placeholder prices positioned against competitor medians (col O). Typical pasta 98k is ~26% below the in-zone average of ~133k (S46 Price_Summary). | O56: Partly sourced
A57: Food costs D5:D24 | C57: =Menu!E29 -> 0.28615661 | E57: S49, S50 | H57: Unit costs are estimates; their cost % is checked against category benchmarks (col P). Blended cost % (E27) feeds the model. | O57: Partly sourced
A58: Units per 100 guests G5:G24 | C58: =Menu!G27 -> 155 | E58: — | H58: Menu mix is an assumption; replace with POS data from the Zurich pop-up. | O58: Assumption – validate
A59: Guest price incl. PBJT (col N) | C59: =Inputs!H17 -> 0.1 | E59: S13 | H59: Net price × (1 + 10% PBJT). | O59: Sourced
A60: Competitor benchmark table A38:F47 | C60: — | E60: S31–S34 | H60: Prices as published (dine-in or delivery app, marked in col D). | O60: Sourced
A61: Menu-engineering classes (col L) | C61: — | E61: S39 | H61: Kasavana–Smith: contribution vs category average, popularity vs 70% rule. | O61: Model formula

Sheet Revenue
A1: Revenue Build-up & Capacity Check (RevPASH logic, Kimes)
A2: Mature daily demand by daypart (from Inputs) tested against seat capacity. Dwell times are blue inputs – measure them at comparable venues.
A3: Notes from Jonas: | B3: To estimate the revenue per daypart, I need informations on Indonesian coutumes: what times do they eat? what kind of F/B at what time of the day?
B4: Additionally, how large is the demande for delivery in Jakarta, which part of the sales will come from this mode of consumption? Needs further research
A5: Seats (dining area ÷ m² per seat) | C5: =ROUNDDOWN(Inputs!$H$21*Inputs!$H$23/Inputs!$H$24,0) -> 60
A7: Daypart | B7: Hours | C7: Guests / day | D7: Avg net spend | E7: Daily revenue (IDR) | F7: Take-away share | G7: Dine-in guests | H7: Avg dwell (min) | I7: Seat capacity (guests) | J7: Seat utilisation | K7: RevPASH (IDR / seat-hour)
A8: Morning 07–11 | B8: 4 | C8: =Inputs!$H$33 -> 45 | D8: =Inputs!$H$34 -> 65000 | E8: =C8*D8 -> 2925000 | F8: =Inputs!$H$43 -> 0.3 | G8: =C8*(1-F8) -> 31.5 | H8: 30 | I8: =$C$5*B8*60/H8 -> 480 | J8: =G8/I8 -> 0.065625 | K8: =E8*(1-F8)/($C$5*B8) -> 8531.25
A9: Lunch 11–15 | B9: 4 | C9: =Inputs!$H$35 -> 75 | D9: =Inputs!$H$36 -> 120000 | E9: =C9*D9 -> 9000000 | F9: =Inputs!$H$43 -> 0.3 | G9: =C9*(1-F9) -> 52.5 | H9: 50 | I9: =$C$5*B9*60/H9 -> 288 | J9: =G9/I9 -> 0.18229167 | K9: =E9*(1-F9)/($C$5*B9) -> 26250
A10: Afternoon 15–18 | B10: 3 | C10: =Inputs!$H$37 -> 35 | D10: =Inputs!$H$38 -> 70000 | E10: =C10*D10 -> 2450000 | F10: =Inputs!$H$43 -> 0.3 | G10: =C10*(1-F10) -> 24.5 | H10: 45 | I10: =$C$5*B10*60/H10 -> 240 | J10: =G10/I10 -> 0.10208333 | K10: =E10*(1-F10)/($C$5*B10) -> 9527.7778
A11: Dinner 18–22 | B11: 4 | C11: =Inputs!$H$39 -> 45 | D11: =Inputs!$H$40 -> 140000 | E11: =C11*D11 -> 6300000 | F11: =Inputs!$H$43 -> 0.3 | G11: =C11*(1-F11) -> 31.5 | H11: 75 | I11: =$C$5*B11*60/H11 -> 192 | J11: =G11/I11 -> 0.1640625 | K11: =E11*(1-F11)/($C$5*B11) -> 18375
A12: In-store total | B12: =SUM(B8:B11) -> 15 | C12: =SUM(C8:C11) -> 200 | E12: =SUM(E8:E11) -> 20675000 | G12: =SUM(G8:G11) -> 140 | I12: =SUM(I8:I11) -> 1200 | J12: =G12/I12 -> 0.11666667 | K12: =SUMPRODUCT(E8:E11,1-F8:F11)/($C$5*B12) -> 16080.556
A13: Delivery (orders × gross app value) | C13: =Inputs!$H$41 -> 25 | D13: =Inputs!$H$42 -> 115000 | E13: =C13*D13 -> 2875000
A14: TOTAL F&B per trading day | E14: =E12+E13 -> 23550000
A16: Blended avg net spend per in-store guest | E16: =E12/C12 -> 103375
A18: MATURE MONTHLY REVENUE (year-1 prices)
A19: F&B in-store | E19: =E12*Inputs!$H$12 -> 620250000
A20: F&B delivery | E20: =E13*Inputs!$H$12 -> 86250000
A21: Events & B2B | E21: =Inputs!$H$44 -> 15000000
A22: Retail | E22: =(E19+E20)*Inputs!$H$45 -> 14130000
A23: Total monthly revenue | E23: =SUM(E19:E22) -> 735630000 | F23: =E23/Inputs!$H$10 -> 34056.944
A24: Annualised revenue | E24: =E23*12 -> 8827560000 | F24: =E24/Inputs!$H$10 -> 408683.33
A26: Capacity check | E26: =IF(MAX(J8:J11)>0.85,"Peak daypart >85% seat utilisation – demand may exceed capacity","OK – demand fits seat capacity") -> OK – demand fits seat capacity
A28: Notes: utilisation = dine-in guests ÷ (seats × hours × 60 / dwell). Real seat occupancy is lower than 100% because party sizes don't fill tables (typically 70–85% max). RevPASH = dine-in revenue per available seat-hour (Kimes, S37).
A29: Low utilisation at base demand suggests the 150 m² / 60 seats could be smaller – test 120 m² in Inputs (rent & CAPEX fall).
A32: SOURCES & CALCULATION BASIS – Revenue
A33: Figure / cells | C33: Value used (live) | E33: Source ID(s) → Sources sheet | H33: How the figure was derived from the source | O33: Evidence status
A34: Seats (C4) | C34: =Revenue!C5 -> 60 | E34: S35 | H34: 150 m² × 60% dining ÷ 1.5 m²/seat. | O34: Derived from sources
A35: Daypart hours (B7:B10) | C35: =Revenue!B12 -> 15 | E35: — | H35: Opening 07:00–22:00 = 15 hours. Assumption. | O35: Assumption – validate
A36: Guests & spend per daypart (C, D) | C36: =Revenue!C12 -> 200 | E36: See Inputs rows 31–38 (S46, S43, S31, S33) | H36: Linked from Inputs – derivations are in Inputs col K. | O36: Partly sourced
A37: Dwell times (H7:H10: 30 / 50 / 45 / 75 min) | C37: =Revenue!H9 -> 50 | E37: S77 (operators: ~1 hour typical, 30 min for a quarter); S37/S38 (measure duration) | H37: Lunch 50 and dinner 75 min bracket the ~1-hour typical stay; morning 30 min matches the café visit. To be measured at comparables (Kimes method). | O37: Partly sourced
A38: Delivery orders & value (row 12) | C38: =Revenue!E13 -> 2875000 | E38: S30, S46 | H38: Linked from Inputs rows 39–40. | O38: Partly sourced
A39: Capacity threshold 85% (E25) | C39: — | E39: S37 (RevPASH logic) | H39: Peak-daypart seat utilisation above 85% treated as unrealistic – practical rule of thumb. | O39: Assumption – validate

Sheet Staffing
A1: Staff Structure & Payroll Cost
A2: Two shifts covering ~15 opening hours, 7 days. Headcount & base salaries are blue inputs; on-costs from Inputs. Salaries must be ≥ UMP.
A3: Note from Jonas | B3: The minimal wage is know for Jakarta (~5'900'000/ month), the other wages will depend on the expertise required (depends on the complexity of the dishes and beverages…)
B4: The Headcount will depends on factors such as the level of robotization, the surface of the restaurant
A5: Role | B5: Headcount | C5: Base salary / month (IDR) | D5: Salary after level factor | E5: UMP check | F5: Gross salaries | G5: BPJS employer | H5: THR accrual | I5: Meals/uniform/transport | J5: Total monthly cost | K5: Source ID(s) & key facts | L5: How the salary was derived | M5: Evidence status
A6: Store / general manager | B6: 1 | C6: 16000000 | D6: =C6*Inputs!$H$62 -> 16000000 | E6: =IF(D6<Inputs!$H$61,"Below UMP!","OK") -> OK | F6: =B6*D6 -> 16000000 | G6: =F6*Inputs!$H$63 -> 1840000 | H6: =F6*Inputs!$H$64 -> 1332800 | I6: =B6*Inputs!$H$65 -> 1000000 | J6: =SUM(F6:I6) -> 20172800 | K6: S75 (store manager 10–20m; F&B manager 12–25m); S73 (restaurant mgmt ads Jaksel avg 6.3m = supervisor level) | L6: 16m ≈ mid-point of S75 store-manager range (10–20m), +1m for a flagship. | M6: Derived from sources
A7: Head chef | B7: 1 | C7: 13000000 | D7: =C7*Inputs!$H$62 -> 13000000 | E7: =IF(D7<Inputs!$H$61,"Below UMP!","OK") -> OK | F7: =B7*D7 -> 13000000 | G7: =F7*Inputs!$H$63 -> 1495000 | H7: =F7*Inputs!$H$64 -> 1082900 | I7: =B7*Inputs!$H$65 -> 1000000 | J7: =SUM(F7:I7) -> 16577900 | K7: S09 (exec chef 11–14m); S08 (head chef avg 7.3m, n=11) | L7: 13m = upper part of S09 exec-chef band (concept chef for pasta/Italian). | M7: Derived from sources
A8: Sous chef / chef de partie | B8: 1 | C8: 9000000 | D8: =C8*Inputs!$H$62 -> 9000000 | E8: =IF(D8<Inputs!$H$61,"Below UMP!","OK") -> OK | F8: =B8*D8 -> 9000000 | G8: =F8*Inputs!$H$63 -> 1035000 | H8: =F8*Inputs!$H$64 -> 749700 | I8: =B8*Inputs!$H$65 -> 1000000 | J8: =SUM(F8:I8) -> 11784700 | K8: S09 (sous chef 5–9m) | L8: 9m = top of S09 sous-chef range (Jakarta premium). | M8: Derived from sources
A9: Line cooks (pasta station, grill) | B9: 3 | C9: 6500000 | D9: =C9*Inputs!$H$62 -> 6500000 | E9: =IF(D9<Inputs!$H$61,"Below UMP!","OK") -> OK | F9: =B9*D9 -> 19500000 | G9: =F9*Inputs!$H$63 -> 2242500 | H9: =F9*Inputs!$H$64 -> 1624350 | I9: =B9*Inputs!$H$65 -> 3000000 | J9: =SUM(F9:I9) -> 26366850 | K9: S04 (UMP 5.73m); S09 (CDP 3–6m outside Jakarta) | L9: UMP 5.73m + ~13% skill premium ≈ 6.5m. | M9: Derived from sources
A10: Kitchen helper / steward | B10: 2 | C10: 5800000 | D10: =C10*Inputs!$H$62 -> 5800000 | E10: =IF(D10<Inputs!$H$61,"Below UMP!","OK") -> OK | F10: =B10*D10 -> 11600000 | G10: =F10*Inputs!$H$63 -> 1334000 | H10: =F10*Inputs!$H$64 -> 966280 | I10: =B10*Inputs!$H$65 -> 2000000 | J10: =SUM(F10:I10) -> 15900280 | K10: S04 (UMP 5.73m) | L10: ≈ UMP rounded up (5.8m). | M10: Derived from sources
A11: Head barista | B11: 1 | C11: 8500000 | D11: =C11*Inputs!$H$62 -> 8500000 | E11: =IF(D11<Inputs!$H$61,"Below UMP!","OK") -> OK | F11: =B11*D11 -> 8500000 | G11: =F11*Inputs!$H$63 -> 977500 | H11: =F11*Inputs!$H$64 -> 708050 | I11: =B11*Inputs!$H$65 -> 1000000 | J11: =SUM(F11:I11) -> 11185550 | K11: S06 (head barista 6.5–10m) | L11: 8.5m ≈ mid-point (8.25m) of S06 range. | M11: Derived from sources
A12: Baristas | B12: 3 | C12: 6000000 | D12: =C12*Inputs!$H$62 -> 6000000 | E12: =IF(D12<Inputs!$H$61,"Below UMP!","OK") -> OK | F12: =B12*D12 -> 18000000 | G12: =F12*Inputs!$H$63 -> 2070000 | H12: =F12*Inputs!$H$64 -> 1499400 | I12: =B12*Inputs!$H$65 -> 3000000 | J12: =SUM(F12:I12) -> 24569400 | K12: S06 (barista 3.5–7.5m); S07 (avg 3.21m self-reported); S04 UMP floor | L12: 6.0m = UMP 5.73m + small premium; S06/S07 values below UMP are not legal for full-time staff. | M12: Derived from sources
A13: Floor / service staff | B13: 4 | C13: 5900000 | D13: =C13*Inputs!$H$62 -> 5900000 | E13: =IF(D13<Inputs!$H$61,"Below UMP!","OK") -> OK | F13: =B13*D13 -> 23600000 | G13: =F13*Inputs!$H$63 -> 2714000 | H13: =F13*Inputs!$H$64 -> 1965880 | I13: =B13*Inputs!$H$65 -> 4000000 | J13: =SUM(F13:I13) -> 32279880 | K13: S04 (UMP 5.73m); S74 (waiter ads avg 2.8m – below UMP) | L13: 5.9m ≈ UMP. Job-ad wages (S74) are below UMP → not usable for full-time compliant staffing. | M13: Derived from sources
A14: Cashier / host | B14: 1 | C14: 5900000 | D14: =C14*Inputs!$H$62 -> 5900000 | E14: =IF(D14<Inputs!$H$61,"Below UMP!","OK") -> OK | F14: =B14*D14 -> 5900000 | G14: =F14*Inputs!$H$63 -> 678500 | H14: =F14*Inputs!$H$64 -> 491470 | I14: =B14*Inputs!$H$65 -> 1000000 | J14: =SUM(F14:I14) -> 8069970 | K14: S04 (UMP 5.73m) | L14: 5.9m ≈ UMP. | M14: Derived from sources
A15: TOTAL | B15: =SUM(B6:B14) -> 17 | F15: =SUM(F6:F14) -> 125100000 | G15: =SUM(G6:G14) -> 14386500 | H15: =SUM(H6:H14) -> 10420830 | I15: =SUM(I6:I14) -> 17000000 | J15: =SUM(J6:J14) -> 166907330 | K15: =J15/Inputs!$H$10 -> 7727.1912
A17: Helper: Σ headcount × base salary (before level factor) – used by Scenarios | J17: =SUMPRODUCT(B6:B14,C6:C14) -> 125100000
A18: Labour hours check: staff × 173 h ÷ (opening hours × 30) | J18: =B15*173/(15*30) -> 6.5355556 | K18: ≈ average staff on duty per opening hour (40 h/week contracts)
A20: Notes: Indonesian law (UU 13/2003 as amended) – 40 h/week; overtime premium; THR = 1 month salary before Lebaran; BPJS per S05. Expat GM (KITAS, higher salary) would add ~IDR 40–60m/month – not included.
A23: SOURCES & CALCULATION BASIS – Staffing
A24: Figure / cells | B24: Value used (live) | D24: Source ID(s) → Sources sheet | G24: How the figure was derived from the source | L24: Evidence status
A25: Headcount B5:B13 | B25: =Staffing!B15 -> 17 | D25: — | G25: Team staffing plan: 2 shifts × ~15 opening hours × 7 days; check J17 (≈ 6.5 staff on duty per opening hour). Validate with 2–3 Jakarta operators. | L25: Assumption – validate
A26: Salary floor (UMP) used in col E | B26: =Inputs!H61 -> 5729876 | D26: S04 | G26: Jakarta UMP 2026 IDR 5,729,876 – every full-time salary must be ≥ this. | L26: Sourced
A27: BPJS employer % (col G) | B27: =Inputs!H63 -> 0.115 | D27: S05 | G27: 3.7 + 2 + 0.3 + 4 = 10% + JKK 0.24–1.74% → 10.2–11.7%; see Inputs row 61. | L27: Derived from sources
A28: THR accrual (col H) | B28: =Inputs!H64 -> 0.0833 | D28: S76 | G28: 1 month wage ÷ 12 months = 8.33%. | L28: Sourced
A29: Meals/uniform/transport (col I) | B29: =Inputs!H65 -> 1000000 | D29: — | G29: IDR per head per month – assumption (Inputs row 63). | L29: Assumption – validate
A30: Labour-hours check (J17) | B30: =Staffing!J18 -> 6.5355556 | D30: UU 13/2003 (40 h/week ≈ 173 h/month) | G30: Staff × 173 h ÷ (15 opening hours × 30 days) = average staff on duty per hour. | L30: Model formula
A31: Benchmark cross-check: staff % revenue | B31: =Scenarios!F38 -> 0.22689033 | D31: S49 (labour 29.4% FSR); S51 (prime ≤60–65%) | G31: Model staff cost ÷ revenue at maturity, to compare with the 26.9–29.4% benchmark range. | L31: Derived from sources

Sheet OPEX
A1: Operating Costs – Fixed & Variable (active scenario, year-1 prices)
A2: Fixed lines link to Inputs; variable lines are % drivers applied in PnL_Monthly. Rent & staff shown for completeness.
A3: Jonas Note: | B3: this sheet helps me to have an idea of the different operating costs. For now it relies on assumptions that I have not confirmed.
B4: I want to check the fixed costs and give a range instead of a number.
A5: Cost line | B5: Monthly (IDR) | C5: Driver | D5: Comment
A6: Fixed overheads
A7: =Inputs!$C$67 -> Local management / area oversight (part-time) | B7: =Inputs!$H$67 -> 25000000 | C7: Fixed
A8: =Inputs!$C$68 -> Accounting, tax, payroll & legal retainer | B8: =Inputs!$H$68 -> 9000000 | C8: Fixed
A9: =Inputs!$C$69 -> Insurance | B9: =Inputs!$H$69 -> 3000000 | C9: Fixed
A10: =Inputs!$C$70 -> POS/software, internet, music licence | B10: =Inputs!$H$70 -> 3000000 | C10: Fixed
A11: =Inputs!$C$71 -> Cleaning, pest control, waste & laundry | B11: =Inputs!$H$71 -> 5000000 | C11: Fixed
A12: =Inputs!$C$72 -> Other admin (bank, permits renewal, travel) | B12: =Inputs!$H$72 -> 4000000 | C12: Fixed
A13: Sub-total fixed overheads | B13: =SUM(B7:B12) -> 49000000
A15: Utilities
A16: Electricity (kWh × B-2 tariff) | B16: =Inputs!$H$73*Inputs!$H$74 -> 13002300 | C16: kWh × tariff
A17: Water & gas | B17: =Inputs!$H$75 -> 6000000
A18: Sub-total utilities | B18: =B16+B17 -> 19002300
A19: Equipment leases, rentals & sponsor premiums (Lease mode, months 1–36) | B19: =IF(Inputs!$H$4=2,'CAPEX (Rent)'!$H$47,0) -> 18483150 | C19: CAPEX (Rent) col U | D19: Booked in PnL_Monthly row 34 (ends per contract term)
A20: Occupancy & staff (from other sheets)
A21: Rent (rate × m² × GFA factor, incl. gross-up) | B21: =Inputs!$H$25*Inputs!$H$21*Inputs!$H$22*(1+Inputs!$H$27) -> 37774219 | D21: Escalates yearly in PnL_Monthly
A22: Service charge / CAM | B22: =Inputs!$H$26*Inputs!$H$21*Inputs!$H$22 -> 0
A23: Staff (Staffing sheet) | B23: =Staffing!$J$15 -> 166907330
A25: Variable cost drivers (% – applied in PnL_Monthly)
A26: =Inputs!$C$49 -> Food & beverage cost adjustment vs Menu sheet (pp) | B26: =Inputs!$H$49 -> 0 | C26: F&B revenue (added to Menu blended cost)
A27: =Inputs!$C$52 -> Packaging % of take-away + delivery revenue | B27: =Inputs!$H$52 -> 0.05 | C27: Take-away + delivery revenue
A28: =Inputs!$C$53 -> Waste & spoilage % of F&B revenue | B28: =Inputs!$H$53 -> 0.015 | C28: F&B revenue
A29: =Inputs!$C$54 -> Delivery platform commission % of delivery revenue | B29: =Inputs!$H$54 -> 0.23 | C29: Delivery revenue (+ VAT on fee)
A30: =Inputs!$C$55 -> Payment fees % of in-store revenue | B30: =Inputs!$H$55 -> 0.012 | C30: In-store revenue
A31: =Inputs!$C$56 -> Marketing % of revenue (post-opening) | B31: =Inputs!$H$56 -> 0.03 | C31: Total revenue
A32: =Inputs!$C$57 -> Repairs & maintenance % of revenue | B32: =Inputs!$H$57 -> 0.015 | C32: Total revenue
A33: =Inputs!$C$58 -> Miscellaneous operating costs % of revenue | B33: =Inputs!$H$58 -> 0.01 | C33: Total revenue
A34: =Inputs!$C$59 -> Brand/royalty fee to CORSA CH % of revenue | B34: =Inputs!$H$59 -> 0 | C34: Total revenue
A35: Blended F&B cost % (Menu + adjustment) | B35: =Menu!$E$29+Inputs!$H$49 -> 0.28615661
A38: SOURCES & CALCULATION BASIS – OPEX
A39: Figure / cells | B39: Value used (live) | C39: Source ID(s) → Sources sheet | E39: How the figure was derived from the source | N39: Evidence status
A40: Local management (B6) | B40: =OPEX!B7 -> 25000000 | C40: S75 | E40: See Inputs row 65. | N40: Partly sourced
A41: Accounting, insurance, software, cleaning, other (B7:B11) | B41: =SUM(OPEX!B8:B12) -> 24000000 | C41: S67 (POS only); S03/S15 | E41: Mostly assumptions – quotes needed (Inputs rows 66–70). | N41: Assumption – validate
A42: Electricity (B15) | B42: =OPEX!B16 -> 13002300 | C42: S55, S11 | E42: ≈ 9,000 kWh (S55 benchmark, 70% electric) × IDR 1,444.70/kWh. | N42: Derived from sources
A43: Water & gas (B16) | B43: =OPEX!B17 -> 6000000 | C43: S56, S57 | E43: ~120 m³ water + ~15 LPG cylinders per month. | N43: Derived from sources
A44: Rent & service charge (B20:B21) | B44: =OPEX!B21+OPEX!B22 -> 37774219 | C44: S20–S27, S14 | E44: Rate × 150 m² × GFA factor (× gross-up) – Location/Rent_Data. | N44: Derived from sources
A45: Staff (B22) | B45: =OPEX!B23 -> 166907330 | C45: S04–S09, S73–S76 | E45: Staffing sheet total. | N45: Derived from sources
A46: Variable % drivers (B25:B33) | B46: — | C46: S12, S47–S49, S52–S54 | E46: Food-cost adj., packaging, waste, delivery commission, payment fees, marketing, R&M, misc. – see Inputs rows 47–57. | N46: Partly sourced
A47: Blended F&B cost (B34) | B47: =OPEX!B35 -> 0.28615661 | C47: S49, S50 | E47: Menu blended cost % + scenario adjustment. | N47: Partly sourced

Sheet CAPEX (Buy)
A1: Investment Requirement (CAPEX & pre-opening)
A2: Blue = base quantities/unit costs (get 3 quotes each). Final amount applies the scenario cost factor (hard costs) and non-recoverable VAT.
A3: Note from Jonas: | B3: This modelling assumes that the material is bought. However I want to consider leasing some materials, which can significantly impact this sheet.
B4: I now want to evaluate the tradeoffs of buying/ leasing some of these items, and compare different brands to get the best value for money
B5: Seats (from Revenue sheet) | C5: =Revenue!$C$5 -> 60
A7: Block | B7: Item | C7: Quantity | D7: Unit cost (IDR) | E7: Base amount (IDR) | F7: Cost factor? (1/0) | G7: VAT? (1/0) | H7: Final amount (IDR) | I7: Final (CHF) | J7: % of total | K7: Source ID(s) & key facts | L7: How the amount was derived / check vs source | M7: Evidence status
A8: A Hard | B8: Civil works, MEP, AC, kitchen exhaust & grease trap | C8: =Inputs!$H$21 -> 150 | D8: 3200000 | E8: =C8*D8 -> 480000000 | F8: 1 | G8: 1 | H8: =E8*IF(F8=1,Inputs!$H$77,1)*(1+Inputs!$H$18*G8) -> 5.328e+08 | I8: =H8/Inputs!$H$10 -> 24666.667 | J8: =H8/$H$37 -> 0.10463015 | K8: S10 (premium café fit-out IDR 4.5–6.5m/m²; civil 20–30% + MEP 15–20%) | L8: (20–30% + 15–20%) × 4.5–6.5m/m² = 1.6–3.25m/m²; 3.2m/m² = top of range because kitchen exhaust, grease trap and AC are included. | M8: Derived from sources
A9: A Hard | B9: Interior, furniture & decor | C9: =C5 -> 60 | D9: 5000000 | E9: =C9*D9 -> 300000000 | F9: 1 | G9: 1 | H9: =E9*IF(F9=1,Inputs!$H$77,1)*(1+Inputs!$H$18*G9) -> 333000000 | I9: =H9/Inputs!$H$10 -> 15416.667 | J9: =H9/$H$37 -> 0.065393844 | K9: S10 (furniture & fit-out 35–45% of premium budget) | L9: 35–45% × 4.5–6.5m/m² × 150 m² = IDR 236–439m ÷ 60 seats = 3.9–7.3m/seat → 5.0m/seat mid-range. | M9: Derived from sources
A10: A Hard | B10: Design & supervision fee | C10: 1 | D10: =0.1*(E8+E9) -> 78000000 | E10: =C10*D10 -> 78000000 | F10: 1 | G10: 1 | H10: =E10*IF(F10=1,Inputs!$H$77,1)*(1+Inputs!$H$18*G10) -> 86580000 | I10: =H10/Inputs!$H$10 -> 4008.3333 | J10: =H10/$H$37 -> 0.017002399 | K10: S10 (design ~10% of build) | L10: 10% × (civil/MEP + interior). | M10: Sourced
A11: A Hard | B11: Kitchen: combi oven | C11: 1 | D11: 280000000 | E11: =C11*D11 -> 280000000 | F11: 1 | G11: 1 | H11: =E11*IF(F11=1,Inputs!$H$77,1)*(1+Inputs!$H$18*G11) -> 310800000 | I11: =H11/Inputs!$H$10 -> 14388.889 | J11: =H11/$H$37 -> 0.061034254 | K11: S68 (iCombi Pro 6-1/1E GBP 5,519 ex VAT); S71 (GBP/IDR 23,680) | L11: 5,519 × 23,680 = IDR 130.7m UK dealer price; + ~30–40% import duty, freight, local margin & installation ≈ IDR 170–185m. ⚠ v0.1 value (280m) is ~50% above this – review or justify (stand, water softener?). | M11: Partly sourced
A12: A Hard | B12: Kitchen: pasta cookers / induction range | C12: 1 | D12: 120000000 | E12: =C12*D12 -> 120000000 | F12: 1 | G12: 1 | H12: =E12*IF(F12=1,Inputs!$H$77,1)*(1+Inputs!$H$18*G12) -> 1.332e+08 | I12: =H12/Inputs!$H$10 -> 6166.6667 | J12: =H12/$H$37 -> 0.026157538 | K12: No source | L12: Quote needed (pasta boilers, induction range). | M12: Assumption – validate
A13: A Hard | B13: Kitchen: refrigeration (reach-in, under-counter, chiller) | C13: 1 | D13: 150000000 | E13: =C13*D13 -> 150000000 | F13: 1 | G13: 1 | H13: =E13*IF(F13=1,Inputs!$H$77,1)*(1+Inputs!$H$18*G13) -> 166500000 | I13: =H13/Inputs!$H$10 -> 7708.3333 | J13: =H13/$H$37 -> 0.032696922 | K13: No source | L13: Quote needed. | M13: Assumption – validate
A14: A Hard | B14: Kitchen: hood, ventilation & fire suppression | C14: 1 | D14: 120000000 | E14: =C14*D14 -> 120000000 | F14: 1 | G14: 1 | H14: =E14*IF(F14=1,Inputs!$H$77,1)*(1+Inputs!$H$18*G14) -> 1.332e+08 | I14: =H14/Inputs!$H$10 -> 6166.6667 | J14: =H14/$H$37 -> 0.026157538 | K14: No source | L14: Quote needed – may be landlord scope. | M14: Assumption – validate
A15: A Hard | B15: Kitchen: prep tables, sinks, dishwasher | C15: 1 | D15: 110000000 | E15: =C15*D15 -> 110000000 | F15: 1 | G15: 1 | H15: =E15*IF(F15=1,Inputs!$H$77,1)*(1+Inputs!$H$18*G15) -> 1.221e+08 | I15: =H15/Inputs!$H$10 -> 5652.7778 | J15: =H15/$H$37 -> 0.023977743 | K15: No source | L15: Quote needed. | M15: Assumption – validate
A16: A Hard | B16: Coffee: espresso machine (2-group, premium) | C16: 1 | D16: 220000000 | E16: =C16*D16 -> 220000000 | F16: 1 | G16: 1 | H16: =E16*IF(F16=1,Inputs!$H$77,1)*(1+Inputs!$H$18*G16) -> 2.442e+08 | I16: =H16/Inputs!$H$10 -> 11305.556 | J16: =H16/$H$37 -> 0.047955485 | K16: S69 (La Marzocco Linea PB 2-group GBP 11,748 ex VAT); S71 | L16: 11,748 × 23,680 = IDR 278m UK dealer price. ⚠ v0.1 value (220m) is ~20% below – OK only with a cheaper model (e.g. Linea Classic) or local distributor price. | M16: Partly sourced
A17: A Hard | B17: Coffee: grinders (espresso + filter) | C17: 2 | D17: 40000000 | E17: =C17*D17 -> 80000000 | F17: 1 | G17: 1 | H17: =E17*IF(F17=1,Inputs!$H$77,1)*(1+Inputs!$H$18*G17) -> 88800000 | I17: =H17/Inputs!$H$10 -> 4111.1111 | J17: =H17/$H$37 -> 0.017438358 | K17: S70 (Mahlkönig E65S USD 2,949; EK43 USD 3,899); S72 (USD/IDR 17,895) | L17: E65S 2,949 × 17,895 = IDR 52.8m; EK43 3,899 × 17,895 = 69.8m; average ≈ 61m per grinder before import costs. ⚠ v0.1 (40m each) looks ~35% low. | M17: Partly sourced
A18: A Hard | B18: Coffee: brew bar, water filtration | C18: 1 | D18: 35000000 | E18: =C18*D18 -> 35000000 | F18: 1 | G18: 1 | H18: =E18*IF(F18=1,Inputs!$H$77,1)*(1+Inputs!$H$18*G18) -> 38850000 | I18: =H18/Inputs!$H$10 -> 1798.6111 | J18: =H18/$H$37 -> 0.0076292818 | K18: No source | L18: Quote needed. | M18: Assumption – validate
A19: A Hard | B19: Drinks: blenders, juicer, ice machine | C19: 1 | D19: 70000000 | E19: =C19*D19 -> 70000000 | F19: 1 | G19: 1 | H19: =E19*IF(F19=1,Inputs!$H$77,1)*(1+Inputs!$H$18*G19) -> 77700000 | I19: =H19/Inputs!$H$10 -> 3597.2222 | J19: =H19/$H$37 -> 0.015258564 | K19: No source | L19: Quote needed (functional-drink equipment). | M19: Assumption – validate
A20: A Hard | B20: Smallwares, tableware, uniforms | C20: 1 | D20: 90000000 | E20: =C20*D20 -> 90000000 | F20: 1 | G20: 1 | H20: =E20*IF(F20=1,Inputs!$H$77,1)*(1+Inputs!$H$18*G20) -> 99900000 | I20: =H20/Inputs!$H$10 -> 4625 | J20: =H20/$H$37 -> 0.019618153 | K20: No source | L20: Assumption. | M20: Assumption – validate
A21: A Hard | B21: Branding & signage (facade, menu boards) | C21: 1 | D21: 120000000 | E21: =C21*D21 -> 120000000 | F21: 1 | G21: 1 | H21: =E21*IF(F21=1,Inputs!$H$77,1)*(1+Inputs!$H$18*G21) -> 1.332e+08 | I21: =H21/Inputs!$H$10 -> 6166.6667 | J21: =H21/$H$37 -> 0.026157538 | K21: No source (reklame permit: Jakarta Bapenda) | L21: Quote needed. | M21: Assumption – validate
A22: A Hard | B22: POS & technology (POS, KDS, Wi-Fi, CCTV, sound) | C22: 1 | D22: 85000000 | E22: =C22*D22 -> 85000000 | F22: 1 | G22: 1 | H22: =E22*IF(F22=1,Inputs!$H$77,1)*(1+Inputs!$H$18*G22) -> 94350000 | I22: =H22/Inputs!$H$10 -> 4368.0556 | J22: =H22/$H$37 -> 0.018528256 | K22: S67 (Moka POS subscription – opex only) | L22: Hardware (POS terminals, KDS, Wi-Fi, CCTV, sound) – quote needed. | M22: Assumption – validate
B23: Sub-total A – hard costs | H23: =SUM(H8:H22) -> 2595180000 | I23: =H23/Inputs!$H$10 -> 120147.22 | J23: =H23/$H$37 -> 0.50963602
A24: B Soft | B24: Company setup: PT PMA, notary, OSS, consultant | C24: 1 | D24: 90000000 | E24: =C24*D24 -> 90000000 | F24: 0 | G24: 1 | H24: =E24*IF(F24=1,Inputs!$H$77,1)*(1+Inputs!$H$18*G24) -> 99900000 | I24: =H24/Inputs!$H$10 -> 4625 | J24: =H24/$H$37 -> 0.019618153 | K24: S65 (PT PMA setup IDR 45.7–113m incl. KITAS) | L24: 90m = upper-middle of S65 range (incl. one KITAS and consultant). | M24: Derived from sources
A25: B Soft | B25: Licences & permits (SLHS, halal, PBG/SLF, fire, reklame) | C25: 1 | D25: 60000000 | E25: =C25*D25 -> 60000000 | F25: 0 | G25: 1 | H25: =E25*IF(F25=1,Inputs!$H$77,1)*(1+Inputs!$H$18*G25) -> 66600000 | I25: =H25/Inputs!$H$10 -> 3083.3333 | J25: =H25/$H$37 -> 0.013078769 | K25: S66 (halal: 12.5m registration + 3.68m LPH inspection); S03 (SLHS, PBG/SLF, fire, environment) | L25: Halal ≈ 16.2m sourced; remaining ~44m for SLHS, PBG/SLF, fire certificate, reklame is an assumption. | M25: Partly sourced
A26: B Soft | B26: Pre-opening marketing & launch | C26: 1 | D26: 180000000 | E26: =C26*D26 -> 180000000 | F26: 0 | G26: 1 | H26: =E26*IF(F26=1,Inputs!$H$77,1)*(1+Inputs!$H$18*G26) -> 1.998e+08 | I26: =H26/Inputs!$H$10 -> 9250 | J26: =H26/$H$37 -> 0.039236306 | K26: Brief; S52 (marketing 3–6%) | L26: 180m ≈ 25% of one mature month's revenue (IDR 736m). Launch budget is an assumption. | M26: Assumption – validate
A27: B Soft | B27: Recruitment & training (incl. trainer travel from CH) | C27: 1 | D27: 120000000 | E27: =C27*D27 -> 120000000 | F27: 0 | G27: 1 | H27: =E27*IF(F27=1,Inputs!$H$77,1)*(1+Inputs!$H$18*G27) -> 1.332e+08 | I27: =H27/Inputs!$H$10 -> 6166.6667 | J27: =H27/$H$37 -> 0.026157538 | K27: Brief | L27: Recruitment + trainer flights/stay from Switzerland – assumption. | M27: Assumption – validate
A28: B Soft | B28: Opening inventory (food, coffee, packaging) | C28: 1 | D28: 120000000 | E28: =C28*D28 -> 120000000 | F28: 0 | G28: 1 | H28: =E28*IF(F28=1,Inputs!$H$77,1)*(1+Inputs!$H$18*G28) -> 1.332e+08 | I28: =H28/Inputs!$H$10 -> 6166.6667 | J28: =H28/$H$37 -> 0.026157538 | K28: Brief; Menu sheet food cost | L28: ≈ 2–3 weeks of mature COGS (≈ IDR 200m/month) → 120m. Approximation. | M28: Derived from sources
A29: B Soft | B29: Pre-opening utilities, deposits & misc. | C29: 1 | D29: 40000000 | E29: =C29*D29 -> 40000000 | F29: 0 | G29: 1 | H29: =E29*IF(F29=1,Inputs!$H$77,1)*(1+Inputs!$H$18*G29) -> 44400000 | I29: =H29/Inputs!$H$10 -> 2055.5556 | J29: =H29/$H$37 -> 0.0087191792 | K29: No source | L29: Assumption. | M29: Assumption – validate
A30: B Soft | B30: Pre-opening payroll (months × full staff cost) | C30: =Inputs!$H$79 -> 1 | D30: =Staffing!$J$15 -> 166907330 | E30: =C30*D30 -> 166907330 | F30: 0 | G30: 0 | H30: =E30 -> 166907330 | I30: =H30/Inputs!$H$10 -> 7727.1912 | J30: =H30/$H$37 -> 0.032776913 | K30: Staffing sheet; Inputs preopen_pay | L30: Months × full monthly staff cost (formula). | M30: Derived from sources
B31: Sub-total B – soft / pre-opening | H31: =SUM(H24:H30) -> 8.4400733e+08 | I31: =H31/Inputs!$H$10 -> 39074.413 | J31: =H31/$H$37 -> 0.1657444
A32: C Cont. | B32: Contingency reserve (% of A + B) | C32: =Inputs!$H$78 -> 0.1 | H32: =C32*(H23+H31) -> 343918733 | I32: =H32/Inputs!$H$10 -> 15922.164 | J32: =H32/$H$37 -> 0.067538042 | K32: S64 via Inputs contingency | L32: % × (hard + soft) – formula. | M32: Derived from sources
A33: D Lease | B33: Rent during fit-out (before opening) | C33: =Inputs!$H$31 -> 2 | D33: =OPEX!$B$21+OPEX!$B$22 -> 37774219 | E33: =C33*D33 -> 75548438 | H33: =E33 -> 75548438 | I33: =H33/Inputs!$H$10 -> 3497.6128 | J33: =H33/$H$37 -> 0.014836044 | K33: Inputs fitout_m; Rent_Data/Location | L33: Formula: months × monthly rent + SC. | M33: Derived from sources
A34: D Lease | B34: Rent prepayment – first block | C34: =Inputs!$H$29 -> 12 | D34: =OPEX!$B$21 -> 37774219 | E34: =C34*D34 -> 453290625 | H34: =E34 -> 453290625 | I34: =H34/Inputs!$H$10 -> 20985.677 | J34: =H34/$H$37 -> 0.089016265 | K34: Inputs prepay_m; S20/S21 | L34: Formula: months × monthly rent. | M34: Derived from sources
A35: D Lease | B35: Security deposit (refundable) | C35: =Inputs!$H$30 -> 2 | D35: =OPEX!$B$21 -> 37774219 | E35: =C35*D35 -> 75548438 | H35: =E35 -> 75548438 | I35: =H35/Inputs!$H$10 -> 3497.6128 | J35: =H35/$H$37 -> 0.014836044 | K35: Inputs deposit_m | L35: Formula: months × monthly rent. | M35: Derived from sources
A36: E WC | B36: Working-capital reserve (staff + fixed opex + utilities) | C36: =Inputs!$H$80 -> 3 | D36: =Staffing!$J$15+OPEX!$B$13+OPEX!$B$18 -> 234909630 | E36: =C36*D36 -> 704728890 | H36: =E36 -> 704728890 | I36: =H36/Inputs!$H$10 -> 32626.338 | J36: =H36/$H$37 -> 0.13839319 | K36: Inputs wc_months | L36: Formula: months × (staff + fixed opex + utilities). | M36: Derived from sources
B37: TOTAL INVESTMENT REQUIREMENT | H37: =H23+H31+H32+SUM(H33:H35)+H36 -> 5092222453 | I37: =H37/Inputs!$H$10 -> 235751.04 | J37: =H37/$H$37 -> 1
B39: Helpers for Scenarios / PnL
B40: Hard costs before cost factor, incl. VAT | H40: =SUMPRODUCT(E8:E22,1+Inputs!$H$18*G8:G22) -> 2595180000
B41: Soft costs excl. pre-opening payroll, incl. VAT | H41: =SUM(H24:H29) -> 6.771e+08
B42: Depreciable base (hard costs + their contingency share) | H42: =H23*(1+C32) -> 2854698000
B43: Cash spent before opening (total less WC reserve) | H43: =H37-H36 -> 4387493563
B45: Note: pre-opening soft costs are expensed under IFRS; here they are treated as part of the investment (cash view). Only hard costs are depreciated.
A48: SOURCES & CALCULATION BASIS – CAPEX (sheet-level parameters)
A49: Figure / cells | C49: Value used (live) | E49: Source ID(s) → Sources sheet | H49: How the figure was derived from the source | L49: Evidence status
A50: Cost factor applied to hard costs (col F) | C50: =Inputs!H77 -> 1 | E50: S64 | H50: Overrun/savings factor from Inputs row 75. | L50: Assumption – validate
A51: Non-recoverable VAT (col G) | C51: =Inputs!H18 -> 0.11 | E51: S03 | H51: 11% VAT added because restaurants (PBJT regime) cannot reclaim input VAT. | L51: Sourced
A52: Contingency % (row 31) | C52: =Inputs!H78 -> 0.1 | E52: S64 | H52: 10% = renovation benchmark (5% ground-up). | L52: Derived from sources
A53: Seats driving interior cost (C4) | C53: ='CAPEX (Buy)'!C5 -> 60 | E53: S35 | H53: Dining area ÷ 1.5 m²/seat (Revenue!C4). | L53: Derived from sources
A54: CHF conversion (col I) | C54: =Inputs!H10 -> 21600 | E54: S16 | H54: IDR ÷ FX rate. | L54: Sourced
A55: ⚠ Equipment checks vs dealer prices | C55: — | E55: S68, S69, S70 | H55: Combi oven looks ~50% high, espresso ~20% low, grinders ~35% low vs converted UK/US dealer prices (rows 10, 15, 16). Net effect small, but get Jakarta distributor quotes before 22 Oct. | L55: Partly sourced

Sheet CAPEX (Rent)
A1: Investment Requirement – LEASE / SPONSOR view (CAPEX & pre-opening)
A2: Same items and values as CAPEX (Buy). Each equipment line picks a financing route in column N; upfront cash goes into the investment, monthly payments go into the P&L (Inputs!H4 = 2 switches the whole model to this sheet).
A3: Note from Jonas: | B3: This modelling assumes that the material is leased .
A4: v0.6: | B4: Completed 16 Oct 2026 – leasing/rental/sponsorship researched per item (S83–S104). Routes: 1 = Buy (cash) · 2 = Finance lease (sewa guna usaha, BFI-type) · 3 = Operating rental (sewa) · 4 = Sponsored / supplier loan (pinjam pakai). Yellow col N = your choice per line.
B5: Seats (from Revenue sheet) | C5: =Revenue!$C$5 -> 60
A7: Block | B7: Item | C7: Quantity | D7: Unit value (IDR) – = Buy sheet | E7: Base amount (IDR) | F7: Cost factor? (1/0) | G7: VAT? (1/0) | H7: UPFRONT CASH (IDR) | I7: Upfront (CHF) | J7: % of upfront total | K7: Source ID(s) & key facts | L7: How the amount was derived / check vs source | M7: Evidence status | N7: Route (1–4) | O7: Route name | P7: Provider / company | Q7: Rental fee / month excl. VAT (route 3) | R7: Sponsor cost / month excl. VAT (route 4) | S7: Refundable deposit (routes 3–4) | T7: Equipment value incl. VAT (= cash price if bought) | U7: Monthly payment (IDR, incl. VAT) | V7: Term (months) | W7: 5-year cash cost (IDR) | X7: 5-yr premium (+) / saving (−) vs buying | Y7: Upfront cash freed vs buying | Z7: Owned at end? | AA7: Check
A8: A Hard | B8: Civil works, MEP, AC, kitchen exhaust & grease trap | C8: ='CAPEX (Buy)'!C8 -> 150 | D8: ='CAPEX (Buy)'!D8 -> 3200000 | E8: =C8*D8 -> 480000000 | F8: ='CAPEX (Buy)'!F8 -> 1 | G8: ='CAPEX (Buy)'!G8 -> 1 | H8: =CHOOSE(N8,T8,T8*$C$68+T8*(1-$C$68)*($C$69+$C$70)+$C$71+T8*$C$72*$C$66/12,S8,S8) -> 5.328e+08 | I8: =H8/Inputs!$H$10 -> 24666.667 | J8: =IFERROR(H8/$H$40,0) -> 0.12488731 | K8: S10 (via CAPEX (Buy) row 8) | L8: Not leasable – fixed to the building; paid in contractor stages. Biggest remaining cash lever = landlord fit-out contribution / rent-free months (not modelled). | M8: Derived from sources | N8: 1 | O8: =CHOOSE(N8,"Buy (cash)","Finance lease","Operating rental","Sponsored / supplier loan") -> Buy (cash) | P8: Fit-out contractor (3 quotes) | S8: =IF(N8=3,Q8*$C$91,0) -> 0 | T8: =E8*IF(F8=1,Inputs!$H$77,1)*(1+Inputs!$H$18*G8) -> 5.328e+08 | U8: =CHOOSE(N8,0,T8*(1-$C$68)*(1/$C$66+$C$67/12),Q8*(1+Inputs!$H$18*G8),R8*(1+Inputs!$H$18*G8)) -> 0 | V8: =CHOOSE(N8,0,$C$66,$C$75,$C$75) -> 0 | W8: =H8+U8*MIN(V8,$C$75)-IF(N8>=3,S8,0) -> 5.328e+08 | X8: =W8-T8 -> 0 | Y8: =T8-H8 -> 0 | Z8: =CHOOSE(N8,"Yes","Yes – after last instalment","No – returned","No – supplier's asset") -> Yes | AA8: =IF(N8<>1,"⚠ not leasable (fixture/service/consumable)",IF(AND(N8=2,T8<$C$73),"⚠ below BFI min. – bundle with kitchen package",IF(AND(N8=3,Q8=0),"⚠ no rental quote – enter fee in col Q","OK"))) -> OK
A9: A Hard | B9: Interior: built-in joinery, finishes, lighting & decor | C9: 1 | D9: ='CAPEX (Buy)'!E9*(1-$C$92) -> 180000000 | E9: =C9*D9 -> 180000000 | F9: ='CAPEX (Buy)'!F9 -> 1 | G9: ='CAPEX (Buy)'!G9 -> 1 | H9: =CHOOSE(N9,T9,T9*$C$68+T9*(1-$C$68)*($C$69+$C$70)+$C$71+T9*$C$72*$C$66/12,S9,S9) -> 1.998e+08 | I9: =H9/Inputs!$H$10 -> 9250 | J9: =IFERROR(H9/$H$40,0) -> 0.046832741 | K9: S10 (via Buy row 9) | L9: (1 − loose-furniture share) × Buy row 9. Custom-built – no rental market. | M9: Derived from sources | N9: 1 | O9: =CHOOSE(N9,"Buy (cash)","Finance lease","Operating rental","Sponsored / supplier loan") -> Buy (cash) | P9: Interior contractor | S9: =IF(N9=3,Q9*$C$91,0) -> 0 | T9: =E9*IF(F9=1,Inputs!$H$77,1)*(1+Inputs!$H$18*G9) -> 1.998e+08 | U9: =CHOOSE(N9,0,T9*(1-$C$68)*(1/$C$66+$C$67/12),Q9*(1+Inputs!$H$18*G9),R9*(1+Inputs!$H$18*G9)) -> 0 | V9: =CHOOSE(N9,0,$C$66,$C$75,$C$75) -> 0 | W9: =H9+U9*MIN(V9,$C$75)-IF(N9>=3,S9,0) -> 1.998e+08 | X9: =W9-T9 -> 0 | Y9: =T9-H9 -> 0 | Z9: =CHOOSE(N9,"Yes","Yes – after last instalment","No – returned","No – supplier's asset") -> Yes | AA9: =IF(N9<>1,"⚠ not leasable (fixture/service/consumable)",IF(AND(N9=2,T9<$C$73),"⚠ below BFI min. – bundle with kitchen package",IF(AND(N9=3,Q9=0),"⚠ no rental quote – enter fee in col Q","OK"))) -> OK
A10: A Hard | B10: Interior: loose furniture (chairs, tables, stools) | C10: 1 | D10: ='CAPEX (Buy)'!E9*$C$92 -> 120000000 | E10: =C10*D10 -> 120000000 | F10: ='CAPEX (Buy)'!F9 -> 1 | G10: ='CAPEX (Buy)'!G9 -> 1 | H10: =CHOOSE(N10,T10,T10*$C$68+T10*(1-$C$68)*($C$69+$C$70)+$C$71+T10*$C$72*$C$66/12,S10,S10) -> 1.332e+08 | I10: =H10/Inputs!$H$10 -> 6166.6667 | J10: =IFERROR(H10/$H$40,0) -> 0.031221827 | K10: S86 (GoWork IDR 150k/unit/month excl. tax, min. 50 units) | L10: Share × Buy row 9. Rental in col Q ≈ seats × 1.33 × IDR 150k ≈ IDR 12m/month → ≈ 6× the purchase price over 5 years, and GoWork stock is office furniture. Kept as Buy – set N = 3 to test. | M10: Partly sourced | N10: 1 | O10: =CHOOSE(N10,"Buy (cash)","Finance lease","Operating rental","Sponsored / supplier loan") -> Buy (cash) | P10: Buy; rental alt.: GoWork | Q10: =ROUND($C$5*$C$82,0)*$C$81 -> 12000000 | S10: =IF(N10=3,Q10*$C$91,0) -> 0 | T10: =E10*IF(F10=1,Inputs!$H$77,1)*(1+Inputs!$H$18*G10) -> 1.332e+08 | U10: =CHOOSE(N10,0,T10*(1-$C$68)*(1/$C$66+$C$67/12),Q10*(1+Inputs!$H$18*G10),R10*(1+Inputs!$H$18*G10)) -> 0 | V10: =CHOOSE(N10,0,$C$66,$C$75,$C$75) -> 0 | W10: =H10+U10*MIN(V10,$C$75)-IF(N10>=3,S10,0) -> 1.332e+08 | X10: =W10-T10 -> 0 | Y10: =T10-H10 -> 0 | Z10: =CHOOSE(N10,"Yes","Yes – after last instalment","No – returned","No – supplier's asset") -> Yes | AA10: =IF(AND(N10=2,T10<$C$73),"⚠ below BFI min. – bundle with kitchen package",IF(AND(N10=3,Q10=0),"⚠ no rental quote – enter fee in col Q","OK")) -> OK
A11: A Hard | B11: Design & supervision fee | C11: ='CAPEX (Buy)'!C10 -> 1 | D11: ='CAPEX (Buy)'!D10 -> 78000000 | E11: =C11*D11 -> 78000000 | F11: ='CAPEX (Buy)'!F10 -> 1 | G11: ='CAPEX (Buy)'!G10 -> 1 | H11: =CHOOSE(N11,T11,T11*$C$68+T11*(1-$C$68)*($C$69+$C$70)+$C$71+T11*$C$72*$C$66/12,S11,S11) -> 86580000 | I11: =H11/Inputs!$H$10 -> 4008.3333 | J11: =IFERROR(H11/$H$40,0) -> 0.020294188 | K11: S10 (via Buy row 10) | L11: Service – cannot be leased. | M11: Sourced | N11: 1 | O11: =CHOOSE(N11,"Buy (cash)","Finance lease","Operating rental","Sponsored / supplier loan") -> Buy (cash) | P11: Architect / designer | S11: =IF(N11=3,Q11*$C$91,0) -> 0 | T11: =E11*IF(F11=1,Inputs!$H$77,1)*(1+Inputs!$H$18*G11) -> 86580000 | U11: =CHOOSE(N11,0,T11*(1-$C$68)*(1/$C$66+$C$67/12),Q11*(1+Inputs!$H$18*G11),R11*(1+Inputs!$H$18*G11)) -> 0 | V11: =CHOOSE(N11,0,$C$66,$C$75,$C$75) -> 0 | W11: =H11+U11*MIN(V11,$C$75)-IF(N11>=3,S11,0) -> 86580000 | X11: =W11-T11 -> 0 | Y11: =T11-H11 -> 0 | Z11: =CHOOSE(N11,"Yes","Yes – after last instalment","No – returned","No – supplier's asset") -> Yes | AA11: =IF(N11<>1,"⚠ not leasable (fixture/service/consumable)",IF(AND(N11=2,T11<$C$73),"⚠ below BFI min. – bundle with kitchen package",IF(AND(N11=3,Q11=0),"⚠ no rental quote – enter fee in col Q","OK"))) -> OK
A12: A Hard | B12: Kitchen: combi oven | C12: ='CAPEX (Buy)'!C11 -> 1 | D12: ='CAPEX (Buy)'!D11 -> 280000000 | E12: =C12*D12 -> 280000000 | F12: ='CAPEX (Buy)'!F11 -> 1 | G12: ='CAPEX (Buy)'!G11 -> 1 | H12: =CHOOSE(N12,T12,T12*$C$68+T12*(1-$C$68)*($C$69+$C$70)+$C$71+T12*$C$72*$C$66/12,S12,S12) -> 100816100 | I12: =H12/Inputs!$H$10 -> 4667.412 | J12: =IFERROR(H12/$H$40,0) -> 0.023631103 | K12: S83 (BFI: 30% DP, 9.4% flat/36 m, 1.25% provision); S90 (Unox 5-tray IDR 113.5m) | L12: Finance lease on the Buy-sheet value. ⚠ A local Unox 5-tray is IDR 113.5m vs IDR 280m in the Buy sheet – choosing Unox cuts the cash and the lease cost by ~60%. | M12: Partly sourced | N12: 2 | O12: =CHOOSE(N12,"Buy (cash)","Finance lease","Operating rental","Sponsored / supplier loan") -> Finance lease | P12: BFI Finance (alt.: Mitsubishi HC Capital, SMFL); supplier Astro Mesin / Gastro | S12: =IF(N12=3,Q12*$C$91,0) -> 0 | T12: =E12*IF(F12=1,Inputs!$H$77,1)*(1+Inputs!$H$18*G12) -> 310800000 | U12: =CHOOSE(N12,0,T12*(1-$C$68)*(1/$C$66+$C$67/12),Q12*(1+Inputs!$H$18*G12),R12*(1+Inputs!$H$18*G12)) -> 7747553.3 | V12: =CHOOSE(N12,0,$C$66,$C$75,$C$75) -> 36 | W12: =H12+U12*MIN(V12,$C$75)-IF(N12>=3,S12,0) -> 3.7972802e+08 | X12: =W12-T12 -> 68928020 | Y12: =T12-H12 -> 209983900 | Z12: =CHOOSE(N12,"Yes","Yes – after last instalment","No – returned","No – supplier's asset") -> Yes – after last instalment | AA12: =IF(AND(N12=2,T12<$C$73),"⚠ below BFI min. – bundle with kitchen package",IF(AND(N12=3,Q12=0),"⚠ no rental quote – enter fee in col Q","OK")) -> OK
A13: A Hard | B13: Kitchen: pasta cookers / induction range | C13: ='CAPEX (Buy)'!C12 -> 1 | D13: ='CAPEX (Buy)'!D12 -> 120000000 | E13: =C13*D13 -> 120000000 | F13: ='CAPEX (Buy)'!F12 -> 1 | G13: ='CAPEX (Buy)'!G12 -> 1 | H13: =CHOOSE(N13,T13,T13*$C$68+T13*(1-$C$68)*($C$69+$C$70)+$C$71+T13*$C$72*$C$66/12,S13,S13) -> 43406900 | I13: =H13/Inputs!$H$10 -> 2009.5787 | J13: =IFERROR(H13/$H$40,0) -> 0.010174495 | K13: S83 | L13: Above the IDR 100m BFI minimum; bundle with combi oven and refrigeration in one kitchen-package contract. | M13: Assumption – validate | N13: 2 | O13: =CHOOSE(N13,"Buy (cash)","Finance lease","Operating rental","Sponsored / supplier loan") -> Finance lease | P13: BFI Finance – same contract as combi oven | S13: =IF(N13=3,Q13*$C$91,0) -> 0 | T13: =E13*IF(F13=1,Inputs!$H$77,1)*(1+Inputs!$H$18*G13) -> 1.332e+08 | U13: =CHOOSE(N13,0,T13*(1-$C$68)*(1/$C$66+$C$67/12),Q13*(1+Inputs!$H$18*G13),R13*(1+Inputs!$H$18*G13)) -> 3320380 | V13: =CHOOSE(N13,0,$C$66,$C$75,$C$75) -> 36 | W13: =H13+U13*MIN(V13,$C$75)-IF(N13>=3,S13,0) -> 162940580 | X13: =W13-T13 -> 29740580 | Y13: =T13-H13 -> 89793100 | Z13: =CHOOSE(N13,"Yes","Yes – after last instalment","No – returned","No – supplier's asset") -> Yes – after last instalment | AA13: =IF(AND(N13=2,T13<$C$73),"⚠ below BFI min. – bundle with kitchen package",IF(AND(N13=3,Q13=0),"⚠ no rental quote – enter fee in col Q","OK")) -> OK
A14: A Hard | B14: Kitchen: refrigeration (reach-in, under-counter, freezer) | C14: 1 | D14: ='CAPEX (Buy)'!E13*(1-$C$93) -> 112500000 | E14: =C14*D14 -> 112500000 | F14: ='CAPEX (Buy)'!F13 -> 1 | G14: ='CAPEX (Buy)'!G13 -> 1 | H14: =CHOOSE(N14,T14,T14*$C$68+T14*(1-$C$68)*($C$69+$C$70)+$C$71+T14*$C$72*$C$66/12,S14,S14) -> 40715844 | I14: =H14/Inputs!$H$10 -> 1884.9928 | J14: =IFERROR(H14/$H$40,0) -> 0.0095437165 | K14: S83; S87 (Refcon upright IDR 0.88–1.58m/month) | L14: (1 − display share) × Buy row 13. Rental (col Q) = 3 × 1.58m + 2 × 0.7m ≈ IDR 6.1m/month → ~2.9× buy over 5 years, so finance lease is preferred. | M14: Partly sourced | N14: 2 | O14: =CHOOSE(N14,"Buy (cash)","Finance lease","Operating rental","Sponsored / supplier loan") -> Finance lease | P14: BFI Finance; rental alt.: Refcon YukSewa | Q14: =$C$84*$C$83+$C$86*$C$85 -> 6140000 | S14: =IF(N14=3,Q14*$C$91,0) -> 0 | T14: =E14*IF(F14=1,Inputs!$H$77,1)*(1+Inputs!$H$18*G14) -> 1.24875e+08 | U14: =CHOOSE(N14,0,T14*(1-$C$68)*(1/$C$66+$C$67/12),Q14*(1+Inputs!$H$18*G14),R14*(1+Inputs!$H$18*G14)) -> 3112856.2 | V14: =CHOOSE(N14,0,$C$66,$C$75,$C$75) -> 36 | W14: =H14+U14*MIN(V14,$C$75)-IF(N14>=3,S14,0) -> 1.5277867e+08 | X14: =W14-T14 -> 27903669 | Y14: =T14-H14 -> 84159156 | Z14: =CHOOSE(N14,"Yes","Yes – after last instalment","No – returned","No – supplier's asset") -> Yes – after last instalment | AA14: =IF(AND(N14=2,T14<$C$73),"⚠ below BFI min. – bundle with kitchen package",IF(AND(N14=3,Q14=0),"⚠ no rental quote – enter fee in col Q","OK")) -> OK
A15: A Hard | B15: Drinks display chiller (front of house) | C15: 1 | D15: ='CAPEX (Buy)'!E13*$C$93 -> 37500000 | E15: =C15*D15 -> 37500000 | F15: ='CAPEX (Buy)'!F13 -> 1 | G15: ='CAPEX (Buy)'!G13 -> 1 | H15: =CHOOSE(N15,T15,T15*$C$68+T15*(1-$C$68)*($C$69+$C$70)+$C$71+T15*$C$72*$C$66/12,S15,S15) -> 0 | I15: =H15/Inputs!$H$10 -> 0 | J15: =IFERROR(H15/$H$40,0) -> 0 | K15: S94 (drink brands lend showcases against sales volume); S104; S87/S98 rental fallback | L15: Brand lends the chiller against listing + minimum volume. ⚠ Brand logo on the unit – check fit with CORSA premium look. Fallback rental in col Q. | M15: Partly sourced | N15: 4 | O15: =CHOOSE(N15,"Buy (cash)","Finance lease","Operating rental","Sponsored / supplier loan") -> Sponsored / supplier loan | P15: Beverage brand (e.g. CCEP Indonesia / Coca-Cola, water or dairy brands) | Q15: =$C$88*$C$87 -> 780000 | R15: 0 | S15: =IF(N15=3,Q15*$C$91,0) -> 0 | T15: =E15*IF(F15=1,Inputs!$H$77,1)*(1+Inputs!$H$18*G15) -> 41625000 | U15: =CHOOSE(N15,0,T15*(1-$C$68)*(1/$C$66+$C$67/12),Q15*(1+Inputs!$H$18*G15),R15*(1+Inputs!$H$18*G15)) -> 0 | V15: =CHOOSE(N15,0,$C$66,$C$75,$C$75) -> 60 | W15: =H15+U15*MIN(V15,$C$75)-IF(N15>=3,S15,0) -> 0 | X15: =W15-T15 -> -41625000 | Y15: =T15-H15 -> 41625000 | Z15: =CHOOSE(N15,"Yes","Yes – after last instalment","No – returned","No – supplier's asset") -> No – supplier's asset | AA15: =IF(AND(N15=2,T15<$C$73),"⚠ below BFI min. – bundle with kitchen package",IF(AND(N15=3,Q15=0),"⚠ no rental quote – enter fee in col Q","OK")) -> OK
A16: A Hard | B16: Kitchen: hood, ventilation & fire suppression | C16: ='CAPEX (Buy)'!C14 -> 1 | D16: ='CAPEX (Buy)'!D14 -> 120000000 | E16: =C16*D16 -> 120000000 | F16: ='CAPEX (Buy)'!F14 -> 1 | G16: ='CAPEX (Buy)'!G14 -> 1 | H16: =CHOOSE(N16,T16,T16*$C$68+T16*(1-$C$68)*($C$69+$C$70)+$C$71+T16*$C$72*$C$66/12,S16,S16) -> 1.332e+08 | I16: =H16/Inputs!$H$10 -> 6166.6667 | J16: =IFERROR(H16/$H$40,0) -> 0.031221827 | K16: Buy row 14 | L16: Fixed installation (ducting) – not financeable. | M16: Assumption – validate | N16: 1 | O16: =CHOOSE(N16,"Buy (cash)","Finance lease","Operating rental","Sponsored / supplier loan") -> Buy (cash) | P16: MEP contractor (may be landlord scope) | S16: =IF(N16=3,Q16*$C$91,0) -> 0 | T16: =E16*IF(F16=1,Inputs!$H$77,1)*(1+Inputs!$H$18*G16) -> 1.332e+08 | U16: =CHOOSE(N16,0,T16*(1-$C$68)*(1/$C$66+$C$67/12),Q16*(1+Inputs!$H$18*G16),R16*(1+Inputs!$H$18*G16)) -> 0 | V16: =CHOOSE(N16,0,$C$66,$C$75,$C$75) -> 0 | W16: =H16+U16*MIN(V16,$C$75)-IF(N16>=3,S16,0) -> 1.332e+08 | X16: =W16-T16 -> 0 | Y16: =T16-H16 -> 0 | Z16: =CHOOSE(N16,"Yes","Yes – after last instalment","No – returned","No – supplier's asset") -> Yes | AA16: =IF(N16<>1,"⚠ not leasable (fixture/service/consumable)",IF(AND(N16=2,T16<$C$73),"⚠ below BFI min. – bundle with kitchen package",IF(AND(N16=3,Q16=0),"⚠ no rental quote – enter fee in col Q","OK"))) -> OK
A17: A Hard | B17: Kitchen: stainless prep tables & sinks | C17: 1 | D17: ='CAPEX (Buy)'!E15*(1-$C$94) -> 71500000 | E17: =C17*D17 -> 71500000 | F17: ='CAPEX (Buy)'!F15 -> 1 | G17: ='CAPEX (Buy)'!G15 -> 1 | H17: =CHOOSE(N17,T17,T17*$C$68+T17*(1-$C$68)*($C$69+$C$70)+$C$71+T17*$C$72*$C$66/12,S17,S17) -> 79365000 | I17: =H17/Inputs!$H$10 -> 3674.3056 | J17: =IFERROR(H17/$H$40,0) -> 0.018603005 | K17: S97 (SeADa rents worktables/sinks – event use) | L17: (1 − dishwasher share) × Buy row 15. Low value, custom sizes → buy. | M17: Assumption – validate | N17: 1 | O17: =CHOOSE(N17,"Buy (cash)","Finance lease","Operating rental","Sponsored / supplier loan") -> Buy (cash) | P17: Stainless fabricator | S17: =IF(N17=3,Q17*$C$91,0) -> 0 | T17: =E17*IF(F17=1,Inputs!$H$77,1)*(1+Inputs!$H$18*G17) -> 79365000 | U17: =CHOOSE(N17,0,T17*(1-$C$68)*(1/$C$66+$C$67/12),Q17*(1+Inputs!$H$18*G17),R17*(1+Inputs!$H$18*G17)) -> 0 | V17: =CHOOSE(N17,0,$C$66,$C$75,$C$75) -> 0 | W17: =H17+U17*MIN(V17,$C$75)-IF(N17>=3,S17,0) -> 79365000 | X17: =W17-T17 -> 0 | Y17: =T17-H17 -> 0 | Z17: =CHOOSE(N17,"Yes","Yes – after last instalment","No – returned","No – supplier's asset") -> Yes | AA17: =IF(AND(N17=2,T17<$C$73),"⚠ below BFI min. – bundle with kitchen package",IF(AND(N17=3,Q17=0),"⚠ no rental quote – enter fee in col Q","OK")) -> OK
A18: A Hard | B18: Kitchen: dishwasher (glass & dish) | C18: 1 | D18: ='CAPEX (Buy)'!E15*$C$94 -> 38500000 | E18: =C18*D18 -> 38500000 | F18: ='CAPEX (Buy)'!F15 -> 1 | G18: ='CAPEX (Buy)'!G15 -> 1 | H18: =CHOOSE(N18,T18,T18*$C$68+T18*(1-$C$68)*($C$69+$C$70)+$C$71+T18*$C$72*$C$66/12,S18,S18) -> 0 | I18: =H18/Inputs!$H$10 -> 0 | J18: =IFERROR(H18/$H$40,0) -> 0 | K18: S89 (Ecolab dishmachine rental: no upfront, 24/7 service & parts) | L18: Machine placed by chemical supplier, recovered through detergent contract. Premium IDR 1.5m/month = assumption; confirm programme exists in Jakarta. | M18: Assumption – validate | N18: 4 | O18: =CHOOSE(N18,"Buy (cash)","Finance lease","Operating rental","Sponsored / supplier loan") -> Sponsored / supplier loan | P18: Ecolab / Diversey chemical programme | R18: =$C$90 -> 1500000 | S18: =IF(N18=3,Q18*$C$91,0) -> 0 | T18: =E18*IF(F18=1,Inputs!$H$77,1)*(1+Inputs!$H$18*G18) -> 42735000 | U18: =CHOOSE(N18,0,T18*(1-$C$68)*(1/$C$66+$C$67/12),Q18*(1+Inputs!$H$18*G18),R18*(1+Inputs!$H$18*G18)) -> 1665000 | V18: =CHOOSE(N18,0,$C$66,$C$75,$C$75) -> 60 | W18: =H18+U18*MIN(V18,$C$75)-IF(N18>=3,S18,0) -> 99900000 | X18: =W18-T18 -> 57165000 | Y18: =T18-H18 -> 42735000 | Z18: =CHOOSE(N18,"Yes","Yes – after last instalment","No – returned","No – supplier's asset") -> No – supplier's asset | AA18: =IF(AND(N18=2,T18<$C$73),"⚠ below BFI min. – bundle with kitchen package",IF(AND(N18=3,Q18=0),"⚠ no rental quote – enter fee in col Q","OK")) -> OK
A19: A Hard | B19: Coffee: espresso machine (2-group, premium) | C19: ='CAPEX (Buy)'!C16 -> 1 | D19: ='CAPEX (Buy)'!D16 -> 220000000 | E19: =C19*D19 -> 220000000 | F19: ='CAPEX (Buy)'!F16 -> 1 | G19: ='CAPEX (Buy)'!G16 -> 1 | H19: =CHOOSE(N19,T19,T19*$C$68+T19*(1-$C$68)*($C$69+$C$70)+$C$71+T19*$C$72*$C$66/12,S19,S19) -> 0 | I19: =H19/Inputs!$H$10 -> 0 | J19: =IFERROR(H19/$H$40,0) -> 0 | K19: S85 (free machine for 15 kg/month, 6-month min.); S84/S88 (rental IDR 3.5–3.65m/month); S91 (Linea PB IDR 163.3m) | L19: Sponsor cost = coffee kg/month × bean premium (params). Roasters usually lend a mid-range 2-group; a Linea PB-level machine needs ≥ ~50 kg/month. ⚠ Buy value 220m vs local Linea PB 163.3m. | M19: Partly sourced | N19: 4 | O19: =CHOOSE(N19,"Buy (cash)","Finance lease","Operating rental","Sponsored / supplier loan") -> Sponsored / supplier loan | P19: Jakarta roaster bean contract (Empo, Delta, specialty roasters); rental alt.: Cafémaker / Serviamo | Q19: =$C$89 -> 3650000 | R19: =$C$78*$C$79 -> 2376000 | S19: =IF(N19=3,Q19*$C$91,0) -> 0 | T19: =E19*IF(F19=1,Inputs!$H$77,1)*(1+Inputs!$H$18*G19) -> 2.442e+08 | U19: =CHOOSE(N19,0,T19*(1-$C$68)*(1/$C$66+$C$67/12),Q19*(1+Inputs!$H$18*G19),R19*(1+Inputs!$H$18*G19)) -> 2637360 | V19: =CHOOSE(N19,0,$C$66,$C$75,$C$75) -> 60 | W19: =H19+U19*MIN(V19,$C$75)-IF(N19>=3,S19,0) -> 158241600 | X19: =W19-T19 -> -85958400 | Y19: =T19-H19 -> 2.442e+08 | Z19: =CHOOSE(N19,"Yes","Yes – after last instalment","No – returned","No – supplier's asset") -> No – supplier's asset | AA19: =IF(AND(N19=2,T19<$C$73),"⚠ below BFI min. – bundle with kitchen package",IF(AND(N19=3,Q19=0),"⚠ no rental quote – enter fee in col Q",IF(AND(N19=4,$C$78<$C$80),"⚠ coffee volume below roaster minimum","OK"))) -> OK
A20: A Hard | B20: Coffee: grinders (espresso + filter) | C20: ='CAPEX (Buy)'!C17 -> 2 | D20: ='CAPEX (Buy)'!D17 -> 40000000 | E20: =C20*D20 -> 80000000 | F20: ='CAPEX (Buy)'!F17 -> 1 | G20: ='CAPEX (Buy)'!G17 -> 1 | H20: =CHOOSE(N20,T20,T20*$C$68+T20*(1-$C$68)*($C$69+$C$70)+$C$71+T20*$C$72*$C$66/12,S20,S20) -> 0 | I20: =H20/Inputs!$H$10 -> 0 | J20: =IFERROR(H20/$H$40,0) -> 0 | K20: S85 | L20: Included with the machine (cost on espresso row). If renting instead, ask whether grinder is in the package. | M20: Assumption – validate | N20: 4 | O20: =CHOOSE(N20,"Buy (cash)","Finance lease","Operating rental","Sponsored / supplier loan") -> Sponsored / supplier loan | P20: Included in roaster package | R20: 0 | S20: =IF(N20=3,Q20*$C$91,0) -> 0 | T20: =E20*IF(F20=1,Inputs!$H$77,1)*(1+Inputs!$H$18*G20) -> 88800000 | U20: =CHOOSE(N20,0,T20*(1-$C$68)*(1/$C$66+$C$67/12),Q20*(1+Inputs!$H$18*G20),R20*(1+Inputs!$H$18*G20)) -> 0 | V20: =CHOOSE(N20,0,$C$66,$C$75,$C$75) -> 60 | W20: =H20+U20*MIN(V20,$C$75)-IF(N20>=3,S20,0) -> 0 | X20: =W20-T20 -> -88800000 | Y20: =T20-H20 -> 88800000 | Z20: =CHOOSE(N20,"Yes","Yes – after last instalment","No – returned","No – supplier's asset") -> No – supplier's asset | AA20: =IF(AND(N20=2,T20<$C$73),"⚠ below BFI min. – bundle with kitchen package",IF(AND(N20=3,Q20=0),"⚠ no rental quote – enter fee in col Q","OK")) -> OK
A21: A Hard | B21: Coffee: brew bar, water filtration | C21: ='CAPEX (Buy)'!C18 -> 1 | D21: ='CAPEX (Buy)'!D18 -> 35000000 | E21: =C21*D21 -> 35000000 | F21: ='CAPEX (Buy)'!F18 -> 1 | G21: ='CAPEX (Buy)'!G18 -> 1 | H21: =CHOOSE(N21,T21,T21*$C$68+T21*(1-$C$68)*($C$69+$C$70)+$C$71+T21*$C$72*$C$66/12,S21,S21) -> 38850000 | I21: =H21/Inputs!$H$10 -> 1798.6111 | J21: =IFERROR(H21/$H$40,0) -> 0.0091063663 | K21: Buy row 18 | L21: Low value; cartridges are opex. Often included in roaster packages – ask. | M21: Assumption – validate | N21: 1 | O21: =CHOOSE(N21,"Buy (cash)","Finance lease","Operating rental","Sponsored / supplier loan") -> Buy (cash) | P21: Buy (ask roaster to include filter) | S21: =IF(N21=3,Q21*$C$91,0) -> 0 | T21: =E21*IF(F21=1,Inputs!$H$77,1)*(1+Inputs!$H$18*G21) -> 38850000 | U21: =CHOOSE(N21,0,T21*(1-$C$68)*(1/$C$66+$C$67/12),Q21*(1+Inputs!$H$18*G21),R21*(1+Inputs!$H$18*G21)) -> 0 | V21: =CHOOSE(N21,0,$C$66,$C$75,$C$75) -> 0 | W21: =H21+U21*MIN(V21,$C$75)-IF(N21>=3,S21,0) -> 38850000 | X21: =W21-T21 -> 0 | Y21: =T21-H21 -> 0 | Z21: =CHOOSE(N21,"Yes","Yes – after last instalment","No – returned","No – supplier's asset") -> Yes | AA21: =IF(AND(N21=2,T21<$C$73),"⚠ below BFI min. – bundle with kitchen package",IF(AND(N21=3,Q21=0),"⚠ no rental quote – enter fee in col Q","OK")) -> OK
A22: A Hard | B22: Drinks: blenders, juicer, ice machine | C22: ='CAPEX (Buy)'!C19 -> 1 | D22: ='CAPEX (Buy)'!D19 -> 70000000 | E22: =C22*D22 -> 70000000 | F22: ='CAPEX (Buy)'!F19 -> 1 | G22: ='CAPEX (Buy)'!G19 -> 1 | H22: =CHOOSE(N22,T22,T22*$C$68+T22*(1-$C$68)*($C$69+$C$70)+$C$71+T22*$C$72*$C$66/12,S22,S22) -> 77700000 | I22: =H22/Inputs!$H$10 -> 3597.2222 | J22: =IFERROR(H22/$H$40,0) -> 0.018212733 | K22: Buy row 19; S101 (ice ≈ IDR 1–4k/kg) | L22: Below BFI minimum on its own. Alternative: no ice machine, daily tube-ice delivery (~IDR 4–6m/month at 50 kg/day) – costlier than buying within a year. | M22: Assumption – validate | N22: 1 | O22: =CHOOSE(N22,"Buy (cash)","Finance lease","Operating rental","Sponsored / supplier loan") -> Buy (cash) | P22: Buy | S22: =IF(N22=3,Q22*$C$91,0) -> 0 | T22: =E22*IF(F22=1,Inputs!$H$77,1)*(1+Inputs!$H$18*G22) -> 77700000 | U22: =CHOOSE(N22,0,T22*(1-$C$68)*(1/$C$66+$C$67/12),Q22*(1+Inputs!$H$18*G22),R22*(1+Inputs!$H$18*G22)) -> 0 | V22: =CHOOSE(N22,0,$C$66,$C$75,$C$75) -> 0 | W22: =H22+U22*MIN(V22,$C$75)-IF(N22>=3,S22,0) -> 77700000 | X22: =W22-T22 -> 0 | Y22: =T22-H22 -> 0 | Z22: =CHOOSE(N22,"Yes","Yes – after last instalment","No – returned","No – supplier's asset") -> Yes | AA22: =IF(AND(N22=2,T22<$C$73),"⚠ below BFI min. – bundle with kitchen package",IF(AND(N22=3,Q22=0),"⚠ no rental quote – enter fee in col Q","OK")) -> OK
A23: A Hard | B23: Smallwares, tableware, uniforms | C23: ='CAPEX (Buy)'!C20 -> 1 | D23: ='CAPEX (Buy)'!D20 -> 90000000 | E23: =C23*D23 -> 90000000 | F23: ='CAPEX (Buy)'!F20 -> 1 | G23: ='CAPEX (Buy)'!G20 -> 1 | H23: =CHOOSE(N23,T23,T23*$C$68+T23*(1-$C$68)*($C$69+$C$70)+$C$71+T23*$C$72*$C$66/12,S23,S23) -> 99900000 | I23: =H23/Inputs!$H$10 -> 4625 | J23: =IFERROR(H23/$H$40,0) -> 0.02341637 | K23: Buy row 20 | L23: Consumables – buy. | M23: Assumption – validate | N23: 1 | O23: =CHOOSE(N23,"Buy (cash)","Finance lease","Operating rental","Sponsored / supplier loan") -> Buy (cash) | P23: Buy | S23: =IF(N23=3,Q23*$C$91,0) -> 0 | T23: =E23*IF(F23=1,Inputs!$H$77,1)*(1+Inputs!$H$18*G23) -> 99900000 | U23: =CHOOSE(N23,0,T23*(1-$C$68)*(1/$C$66+$C$67/12),Q23*(1+Inputs!$H$18*G23),R23*(1+Inputs!$H$18*G23)) -> 0 | V23: =CHOOSE(N23,0,$C$66,$C$75,$C$75) -> 0 | W23: =H23+U23*MIN(V23,$C$75)-IF(N23>=3,S23,0) -> 99900000 | X23: =W23-T23 -> 0 | Y23: =T23-H23 -> 0 | Z23: =CHOOSE(N23,"Yes","Yes – after last instalment","No – returned","No – supplier's asset") -> Yes | AA23: =IF(N23<>1,"⚠ not leasable (fixture/service/consumable)",IF(AND(N23=2,T23<$C$73),"⚠ below BFI min. – bundle with kitchen package",IF(AND(N23=3,Q23=0),"⚠ no rental quote – enter fee in col Q","OK"))) -> OK
A24: A Hard | B24: Branding & signage (facade, menu boards) | C24: ='CAPEX (Buy)'!C21 -> 1 | D24: ='CAPEX (Buy)'!D21 -> 120000000 | E24: =C24*D24 -> 120000000 | F24: ='CAPEX (Buy)'!F21 -> 1 | G24: ='CAPEX (Buy)'!G21 -> 1 | H24: =CHOOSE(N24,T24,T24*$C$68+T24*(1-$C$68)*($C$69+$C$70)+$C$71+T24*$C$72*$C$66/12,S24,S24) -> 1.332e+08 | I24: =H24/Inputs!$H$10 -> 6166.6667 | J24: =IFERROR(H24/$H$40,0) -> 0.031221827 | K24: Buy row 21 | L24: Custom & permitted (reklame) – not leasable. | M24: Assumption – validate | N24: 1 | O24: =CHOOSE(N24,"Buy (cash)","Finance lease","Operating rental","Sponsored / supplier loan") -> Buy (cash) | P24: Signage contractor | S24: =IF(N24=3,Q24*$C$91,0) -> 0 | T24: =E24*IF(F24=1,Inputs!$H$77,1)*(1+Inputs!$H$18*G24) -> 1.332e+08 | U24: =CHOOSE(N24,0,T24*(1-$C$68)*(1/$C$66+$C$67/12),Q24*(1+Inputs!$H$18*G24),R24*(1+Inputs!$H$18*G24)) -> 0 | V24: =CHOOSE(N24,0,$C$66,$C$75,$C$75) -> 0 | W24: =H24+U24*MIN(V24,$C$75)-IF(N24>=3,S24,0) -> 1.332e+08 | X24: =W24-T24 -> 0 | Y24: =T24-H24 -> 0 | Z24: =CHOOSE(N24,"Yes","Yes – after last instalment","No – returned","No – supplier's asset") -> Yes | AA24: =IF(N24<>1,"⚠ not leasable (fixture/service/consumable)",IF(AND(N24=2,T24<$C$73),"⚠ below BFI min. – bundle with kitchen package",IF(AND(N24=3,Q24=0),"⚠ no rental quote – enter fee in col Q","OK"))) -> OK
A25: A Hard | B25: POS & technology (POS, KDS, Wi-Fi, CCTV, sound) | C25: ='CAPEX (Buy)'!C22 -> 1 | D25: ='CAPEX (Buy)'!D22 -> 85000000 | E25: =C25*D25 -> 85000000 | F25: ='CAPEX (Buy)'!F22 -> 1 | G25: ='CAPEX (Buy)'!G22 -> 1 | H25: =CHOOSE(N25,T25,T25*$C$68+T25*(1-$C$68)*($C$69+$C$70)+$C$71+T25*$C$72*$C$66/12,S25,S25) -> 94350000 | I25: =H25/Inputs!$H$10 -> 4368.0556 | J25: =IFERROR(H25/$H$40,0) -> 0.022115461 | K25: S96 (Moka devices IDR 0.2–6m); S95 (POS rental IDR 3.5m/month); S92 (ORIX IT operating lease 1–4 yrs) | L25: Renting a POS (IDR 3.5m/month) costs more than the hardware within a year → buy. | M25: Partly sourced | N25: 1 | O25: =CHOOSE(N25,"Buy (cash)","Finance lease","Operating rental","Sponsored / supplier loan") -> Buy (cash) | P25: Buy; rental alt.: MTM Solusindo / ORIX IT lease | S25: =IF(N25=3,Q25*$C$91,0) -> 0 | T25: =E25*IF(F25=1,Inputs!$H$77,1)*(1+Inputs!$H$18*G25) -> 94350000 | U25: =CHOOSE(N25,0,T25*(1-$C$68)*(1/$C$66+$C$67/12),Q25*(1+Inputs!$H$18*G25),R25*(1+Inputs!$H$18*G25)) -> 0 | V25: =CHOOSE(N25,0,$C$66,$C$75,$C$75) -> 0 | W25: =H25+U25*MIN(V25,$C$75)-IF(N25>=3,S25,0) -> 94350000 | X25: =W25-T25 -> 0 | Y25: =T25-H25 -> 0 | Z25: =CHOOSE(N25,"Yes","Yes – after last instalment","No – returned","No – supplier's asset") -> Yes | AA25: =IF(AND(N25=2,T25<$C$73),"⚠ below BFI min. – bundle with kitchen package",IF(AND(N25=3,Q25=0),"⚠ no rental quote – enter fee in col Q","OK")) -> OK
B26: Sub-total A – hard costs (upfront cash) | H26: =SUM(H8:H25) -> 1.7938838e+09 | I26: =H26/Inputs!$H$10 -> 83050.178 | J26: =IFERROR(H26/$H$40,0) -> 0.42048297 | T26: =SUM(T8:T25) -> 2595180000 | U26: =SUM(U8:U25) -> 18483150 | W26: =SUM(W8:W25) -> 2.5625339e+09 | X26: =SUM(X8:X25) -> -32646131 | Y26: =SUM(Y8:Y25) -> 8.0129616e+08
A27: B Soft | B27: ='CAPEX (Buy)'!B24 -> Company setup: PT PMA, notary, OSS, consultant | C27: ='CAPEX (Buy)'!C24 -> 1 | D27: ='CAPEX (Buy)'!D24 -> 90000000 | E27: =C27*D27 -> 90000000 | F27: ='CAPEX (Buy)'!F24 -> 0 | G27: ='CAPEX (Buy)'!G24 -> 1 | H27: =E27*IF(F27=1,Inputs!$H$77,1)*(1+Inputs!$H$18*G27) -> 99900000 | I27: =H27/Inputs!$H$10 -> 4625 | J27: =IFERROR(H27/$H$40,0) -> 0.02341637 | K27: ='CAPEX (Buy)'!K24 -> S65 (PT PMA setup IDR 45.7–113m incl. KITAS) | L27: Same as Buy sheet – soft costs are cash in both views. | M27: ='CAPEX (Buy)'!M24 -> Derived from sources
A28: B Soft | B28: ='CAPEX (Buy)'!B25 -> Licences & permits (SLHS, halal, PBG/SLF, fire, reklame) | C28: ='CAPEX (Buy)'!C25 -> 1 | D28: ='CAPEX (Buy)'!D25 -> 60000000 | E28: =C28*D28 -> 60000000 | F28: ='CAPEX (Buy)'!F25 -> 0 | G28: ='CAPEX (Buy)'!G25 -> 1 | H28: =E28*IF(F28=1,Inputs!$H$77,1)*(1+Inputs!$H$18*G28) -> 66600000 | I28: =H28/Inputs!$H$10 -> 3083.3333 | J28: =IFERROR(H28/$H$40,0) -> 0.015610914 | K28: ='CAPEX (Buy)'!K25 -> S66 (halal: 12.5m registration + 3.68m LPH inspection); S03 (SLHS, PBG/SLF, fire, environment) | L28: Same as Buy sheet – soft costs are cash in both views. | M28: ='CAPEX (Buy)'!M25 -> Partly sourced
A29: B Soft | B29: ='CAPEX (Buy)'!B26 -> Pre-opening marketing & launch | C29: ='CAPEX (Buy)'!C26 -> 1 | D29: ='CAPEX (Buy)'!D26 -> 180000000 | E29: =C29*D29 -> 180000000 | F29: ='CAPEX (Buy)'!F26 -> 0 | G29: ='CAPEX (Buy)'!G26 -> 1 | H29: =E29*IF(F29=1,Inputs!$H$77,1)*(1+Inputs!$H$18*G29) -> 1.998e+08 | I29: =H29/Inputs!$H$10 -> 9250 | J29: =IFERROR(H29/$H$40,0) -> 0.046832741 | K29: ='CAPEX (Buy)'!K26 -> Brief; S52 (marketing 3–6%) | L29: Same as Buy sheet – soft costs are cash in both views. | M29: ='CAPEX (Buy)'!M26 -> Assumption – validate
A30: B Soft | B30: ='CAPEX (Buy)'!B27 -> Recruitment & training (incl. trainer travel from CH) | C30: ='CAPEX (Buy)'!C27 -> 1 | D30: ='CAPEX (Buy)'!D27 -> 120000000 | E30: =C30*D30 -> 120000000 | F30: ='CAPEX (Buy)'!F27 -> 0 | G30: ='CAPEX (Buy)'!G27 -> 1 | H30: =E30*IF(F30=1,Inputs!$H$77,1)*(1+Inputs!$H$18*G30) -> 1.332e+08 | I30: =H30/Inputs!$H$10 -> 6166.6667 | J30: =IFERROR(H30/$H$40,0) -> 0.031221827 | K30: ='CAPEX (Buy)'!K27 -> Brief | L30: Same as Buy sheet – soft costs are cash in both views. | M30: ='CAPEX (Buy)'!M27 -> Assumption – validate
A31: B Soft | B31: ='CAPEX (Buy)'!B28 -> Opening inventory (food, coffee, packaging) | C31: ='CAPEX (Buy)'!C28 -> 1 | D31: ='CAPEX (Buy)'!D28 -> 120000000 | E31: =C31*D31 -> 120000000 | F31: ='CAPEX (Buy)'!F28 -> 0 | G31: ='CAPEX (Buy)'!G28 -> 1 | H31: =E31*IF(F31=1,Inputs!$H$77,1)*(1+Inputs!$H$18*G31) -> 1.332e+08 | I31: =H31/Inputs!$H$10 -> 6166.6667 | J31: =IFERROR(H31/$H$40,0) -> 0.031221827 | K31: ='CAPEX (Buy)'!K28 -> Brief; Menu sheet food cost | L31: Same as Buy sheet – soft costs are cash in both views. | M31: ='CAPEX (Buy)'!M28 -> Derived from sources
A32: B Soft | B32: ='CAPEX (Buy)'!B29 -> Pre-opening utilities, deposits & misc. | C32: ='CAPEX (Buy)'!C29 -> 1 | D32: ='CAPEX (Buy)'!D29 -> 40000000 | E32: =C32*D32 -> 40000000 | F32: ='CAPEX (Buy)'!F29 -> 0 | G32: ='CAPEX (Buy)'!G29 -> 1 | H32: =E32*IF(F32=1,Inputs!$H$77,1)*(1+Inputs!$H$18*G32) -> 44400000 | I32: =H32/Inputs!$H$10 -> 2055.5556 | J32: =IFERROR(H32/$H$40,0) -> 0.010407276 | K32: ='CAPEX (Buy)'!K29 -> No source | L32: Same as Buy sheet – soft costs are cash in both views. | M32: ='CAPEX (Buy)'!M29 -> Assumption – validate
A33: B Soft | B33: ='CAPEX (Buy)'!B30 -> Pre-opening payroll (months × full staff cost) | C33: ='CAPEX (Buy)'!C30 -> 1 | D33: ='CAPEX (Buy)'!D30 -> 166907330 | E33: =C33*D33 -> 166907330 | F33: ='CAPEX (Buy)'!F30 -> 0 | G33: ='CAPEX (Buy)'!G30 -> 0 | H33: =E33 -> 166907330 | I33: =H33/Inputs!$H$10 -> 7727.1912 | J33: =IFERROR(H33/$H$40,0) -> 0.039122762 | K33: ='CAPEX (Buy)'!K30 -> Staffing sheet; Inputs preopen_pay | L33: Same as Buy sheet – soft costs are cash in both views. | M33: ='CAPEX (Buy)'!M30 -> Derived from sources
B34: Sub-total B – soft / pre-opening | H34: =SUM(H27:H33) -> 8.4400733e+08 | I34: =H34/Inputs!$H$10 -> 39074.413 | J34: =IFERROR(H34/$H$40,0) -> 0.19783372
A35: C Cont. | B35: Contingency reserve (% of A + B upfront cash) | C35: =Inputs!$H$78 -> 0.1 | H35: =C35*(H26+H34) -> 2.6378912e+08 | I35: =H35/Inputs!$H$10 -> 12212.459 | J35: =IFERROR(H35/$H$40,0) -> 0.061831669 | K35: S64 via Inputs contingency | L35: % × upfront hard + soft. Lower base than Buy because leased/sponsored items carry little overrun risk. | M35: Derived from sources
A36: D Lease | B36: Rent during fit-out (before opening) | C36: ='CAPEX (Buy)'!C33 -> 2 | D36: ='CAPEX (Buy)'!D33 -> 37774219 | E36: =C36*D36 -> 75548438 | H36: =E36 -> 75548438 | I36: =H36/Inputs!$H$10 -> 3497.6128 | J36: =IFERROR(H36/$H$40,0) -> 0.01770841 | K36: ='CAPEX (Buy)'!K33 -> Inputs fitout_m; Rent_Data/Location | L36: ='CAPEX (Buy)'!L33 -> Formula: months × monthly rent + SC. | M36: ='CAPEX (Buy)'!M33 -> Derived from sources
A37: D Lease | B37: Rent prepayment – first block | C37: ='CAPEX (Buy)'!C34 -> 12 | D37: ='CAPEX (Buy)'!D34 -> 37774219 | E37: =C37*D37 -> 453290625 | H37: =E37 -> 453290625 | I37: =H37/Inputs!$H$10 -> 20985.677 | J37: =IFERROR(H37/$H$40,0) -> 0.10625046 | K37: ='CAPEX (Buy)'!K34 -> Inputs prepay_m; S20/S21 | L37: ='CAPEX (Buy)'!L34 -> Formula: months × monthly rent. | M37: ='CAPEX (Buy)'!M34 -> Derived from sources
A38: D Lease | B38: Security deposit (refundable) | C38: ='CAPEX (Buy)'!C35 -> 2 | D38: ='CAPEX (Buy)'!D35 -> 37774219 | E38: =C38*D38 -> 75548438 | H38: =E38 -> 75548438 | I38: =H38/Inputs!$H$10 -> 3497.6128 | J38: =IFERROR(H38/$H$40,0) -> 0.01770841 | K38: ='CAPEX (Buy)'!K35 -> Inputs deposit_m | L38: ='CAPEX (Buy)'!L35 -> Formula: months × monthly rent. | M38: ='CAPEX (Buy)'!M35 -> Derived from sources
A39: E WC | B39: Working-capital reserve (staff + fixed opex + utilities + equipment payments) | C39: =Inputs!$H$80 -> 3 | D39: =Staffing!$J$15+OPEX!$B$13+OPEX!$B$18+H47 -> 2.5339278e+08 | E39: =C39*D39 -> 7.6017834e+08 | H39: =E39 -> 7.6017834e+08 | I39: =H39/Inputs!$H$10 -> 35193.442 | J39: =IFERROR(H39/$H$40,0) -> 0.17818436 | K39: Inputs wc_months | L39: Months × (staff + fixed opex + utilities + monthly lease/rental/sponsor payments). | M39: Derived from sources
B40: TOTAL INVESTMENT REQUIREMENT – LEASE VIEW | H40: =H26+H34+H35+SUM(H36:H38)+H39 -> 4.2662461e+09 | I40: =H40/Inputs!$H$10 -> 197511.39 | J40: =IFERROR(H40/$H$40,0) -> 1
B42: Helpers for Scenarios / PnL / Funding (read by other sheets when Inputs!H4 = 2)
B43: Hard costs upfront before cost factor, incl. VAT (→ Scenarios row 48) | H43: =H26/Inputs!$H$77 -> 1.7938838e+09
B44: Soft costs excl. pre-opening payroll, incl. VAT (→ Scenarios row 49) | H44: =SUM(H27:H32) -> 6.771e+08
B45: Depreciable base: bought items only + contingency share (→ PnL row 37) | H45: =SUMPRODUCT((N8:N25=1)*H8:H25)*(1+C35) -> 1.7698395e+09
B46: Cash spent before opening (total less WC reserve) | H46: =H40-H39 -> 3.5060678e+09
B47: Monthly equipment payments – months 1 to tenor (→ PnL row 34, OPEX row 19) | H47: =SUM(U8:U25) -> 18483150
B48: Monthly equipment payments after finance leases end | H48: =SUMIFS(U8:U25,V8:V25,">"&$C$66) -> 4302360
B49: Upfront cash freed vs CAPEX (Buy) total | H49: ='CAPEX (Buy)'!$H$37-H40 -> 8.2597632e+08
B50: 5-year extra cost of leasing/sponsorship vs buying (sum col X) | H50: =X26 -> -32646131
A52: BUY vs LEASE – SUMMARY (both views live, independent of the switch)
B53: Metric | C53: Buy (cash) | D53: Lease / sponsor | E53: Difference (Lease − Buy)
B54: Total investment requirement (IDR) | C54: ='CAPEX (Buy)'!$H$37 -> 5092222453 | D54: =$H$40 -> 4.2662461e+09 | E54: =D54-C54 -> -8.2597632e+08
B55: Total investment requirement (CHF) | C55: =C54/Inputs!$H$10 -> 235751.04 | D55: =D54/Inputs!$H$10 -> 197511.39 | E55: =D55-C55 -> -38239.645
B56: Gap vs CHF 200k founder equity (+ = bank/extra equity needed) | C56: =C55-Inputs!$H$82 -> 35751.039 | D56: =D55-Inputs!$H$82 -> -2488.6051 | E56: =D56-C56 -> -38239.645
B57: Hard-cost upfront cash (IDR) | C57: ='CAPEX (Buy)'!$H$23 -> 2595180000 | D57: =$H$26 -> 1.7938838e+09 | E57: =D57-C57 -> -8.0129616e+08
B58: Equipment payments per month – months 1–36 (IDR) | C58: 0 | D58: =$H$47 -> 18483150 | E58: =D58-C58 -> 18483150
B59: Equipment payments per month – months 37–60 (IDR) | C59: 0 | D59: =$H$48 -> 4302360 | E59: =D59-C59 -> 4302360
B60: 5-year equipment cash cost (IDR) | C60: ='CAPEX (Buy)'!$H$23 -> 2595180000 | D60: =$W$26 -> 2.5625339e+09 | E60: =D60-C60 -> -32646131
B61: Depreciation per month (IDR) | C61: ='CAPEX (Buy)'!$H$42/(Inputs!$H$81*12) -> 47578300 | D61: =$H$45/(Inputs!$H$81*12) -> 29497325 | E61: =D61-C61 -> -18080975
B62: Check: equipment values tie to CAPEX (Buy) hard costs | D62: =IF(ABS($T$26-'CAPEX (Buy)'!$H$23)<1,"OK","MISMATCH") -> OK
B63: Active CAPEX mode in the model (Inputs!H4) | D63: =Inputs!$I$4 -> Lease – CAPEX (Rent)
A64: LEASE, RENTAL & SPONSORSHIP PARAMETERS (blue = input – edit here; feed columns H, Q–W above)
B65: Parameter | C65: Value | D65: Unit | E65: Source ID | F65: Note / how used
B66: Finance lease tenor | C66: 36 | D66: months | E66: S83 | F66: BFI machine leasing: 12–36 months. 36 = longest tenor, lowest monthly payment.
B67: Finance lease flat rate p.a. (on amount financed) | C67: 0.094 | D67: % flat | E67: S83 | F67: BFI example: 9.40% flat for 36 months (9.02% for 24 m). Published range 8–10% flat.
B68: Security deposit / down payment | C68: 0.3 | D68: % of value | E68: S83 | F68: BFI: 30–40% (30% for Chinese, Japanese & European machines). Treated as a down payment (offsets the residual).
B69: Provision fee | C69: 0.0125 | D69: % of financed | E69: S83 | F69: BFI: provisi 1.25% of amount financed.
B70: Commitment fee | C70: 0.01 | D70: % of financed | E70: S83 | F70: BFI example: 1% of net-to-finance (another part of the page says 2%).
B71: Fixed fees (tagging + policy) | C71: 350000 | D71: IDR/contract | E71: S83 | F71: Tagging fee IDR 300k + insurance policy fee IDR 50k.
B72: Equipment insurance (paid upfront, full tenor) | C72: 0.0025 | D72: % p.a. of value | E72: S83 | F72: 0.25% p.a. of unit price; BFI example charges 0.75% for 3 years upfront.
B73: Minimum unit price financed | C73: 100000000 | D73: IDR | E73: S83 | F73: BFI minimum; smaller items must be bundled into one kitchen-package contract.
B74: → Equivalent effective rate p.a. (computed) | C74: =RATE($C$66,-(1/$C$66+$C$67/12),1)*12 -> 0.16916352 | D74: % p.a. | E74: S83 | F74: RATE() on the flat-rate instalment: 9.4% flat over 36 months ≈ 17% effective. Compare: bank loan in Inputs row 84.
B75: Comparison horizon | C75: 60 | D75: months | E75: Model | F75: 5-year model life (= depreciation life, Inputs row 81). Rentals & sponsor deals assumed to run the whole horizon.
B76: Coffee dose per cup | C76: 18 | D76: g | E76: Assumption | F76: Double shot 18 g (filter 15 g) – barista standard.
B77: Coffee waste (calibration, purges) | C77: 0.1 | D77: % | E77: Assumption | F77: Dial-in & waste allowance.
B78: → Coffee volume at maturity (computed) | C78: =Scenarios!$F$6*SUM(Menu!$G$13:$G$17)/100*$C$76/1000*(1+$C$77)*Inputs!$H$12 -> 59.4 | D78: kg/month | E78: Menu, Scenarios | F78: Guests/day × coffee units per guest (Menu G13:G17) × dose × (1+waste) × trading days.
B79: Bean price premium charged by roaster for machine loan | C79: 40000 | D79: IDR/kg | E79: Assumption (S85) | F79: KEY ASSUMPTION – the roaster recovers the machine through the bean price. Get 3 written offers (Empo, Delta, specialty roasters).
B80: Typical roaster minimum volume for a commercial machine loan | C80: 30 | D80: kg/month | E80: Assumption (S85) | F80: Cafémaker lends an office machine for 15 kg/month; a 2-group commercial machine usually needs more.
B81: Furniture rental rate | C81: 150000 | D81: IDR/unit/month | E81: S86 | F81: GoWork: IDR 150k per chair or table per month, excl. tax, min. 50 units, deposit at signing.
B82: Furniture units per seat | C82: 1.33 | D82: units/seat | E82: Assumption | F82: 1 chair per seat + 1 table per 3 seats.
B83: Upright chiller/freezer rental | C83: 1580000 | D83: IDR/unit/month | E83: S87 | F83: Refcon YukSewa: IDR 880k–1.58m/month (deposit IDR 1.1–1.3m). Top type used for commercial duty.
B84: Number of upright units | C84: 3 | D84: # | E84: Assumption | F84: 2 chillers + 1 freezer for a 60-seat pasta kitchen.
B85: Smaller fridge rental | C85: 700000 | D85: IDR/unit/month | E85: S87 | F85: Refcon kulkas: IDR 310k–700k/month.
B86: Number of smaller units | C86: 2 | D86: # | E86: Assumption | F86: Under-counter / bar fridges.
B87: Display chiller rental (fallback if no sponsor) | C87: 390000 | D87: IDR/unit/month | E87: S87, S98 | F87: Refcon showcase IDR 260–390k; Jagoan Sewa 500–650k (180–280 L).
B88: Number of display chillers | C88: 2 | D88: # | E88: Assumption | F88: Front-of-house drinks & retail fridge.
B89: Espresso machine rental (fallback if no roaster deal) | C89: 3650000 | D89: IDR/month | E89: S84, S88 | F89: Cafémaker IDR 3.65m/month (maintenance + backup machine); Serviamo coffee-shop package from IDR 3.5m/month, min. 6 months.
B90: Dishwasher programme – premium over normal chemical spend | C90: 1500000 | D90: IDR/month | E90: Assumption (S89) | F90: Ecolab-type programme: no upfront, service & parts included, paid through the chemical contract. Confirm with Ecolab/Diversey Indonesia.
... B96: Local price check – La Marzocco Linea PB AV 2-group | C96: 163300000 | D96: IDR | E96: S91 | F96: Otten Coffee price list (2024). Buy sheet uses IDR 220m.
A99: PROVIDER DIRECTORY – who can lease, rent or sponsor what in Jakarta (contact for 3 quotes each)
B100: Company / provider | C100: Route | D100: Items it can cover | K100: Offer & terms found | L100: Price evidence | M100: Source ID
B101: PT BFI Finance Indonesia Tbk | C101: 2 | D101: Combi oven, pasta station, kitchen refrigeration (fallback: espresso machine) | K101: Machine finance lease, 12–36 months, 30–40% security deposit, machine is sole collateral, Java & Bali only, min. unit IDR 100m. Needs deed, NPWP, licences + 6 months bank statements → a brand-new PT PMA may need a director/parent guarantee. | L101: 8–10% flat p.a. (9.40% flat/36 m ≈ 17% effective); provision 1.25%; commitment 1–2%; insurance 0.25% p.a. | M101: S83
B102: PT Mitsubishi HC Capital and Finance Indonesia | C102: 2 | D102: Kitchen package (alternative lessor) | K102: Japanese-owned multifinance; used to foreign-owned clients. No public rates – request quote. | L102: Quote needed | M102: S99
B103: PT SMFL Leasing Indonesia (Sumitomo Mitsui) | C103: 2 | D103: Kitchen package (alternative lessor) | K103: Japanese-owned equipment lessor. No public rates – request quote. | L103: Quote needed | M103: S100
B104: PT ORIX Indonesia Finance | C104: 3 | D104: POS terminals, laptops, IT (and vehicles) | K104: Operating lease of vehicles & IT equipment, 1–4 years, IDR only, PT or CV with 6 months bank statements. Machinery not covered. | L104: Rates on request | M104: S92
B105: PT Cafe Maker Indonesia (Cafémaker, Bekasi) + Eleven Thirty Roastery | C105: 3 / 4 | D105: Espresso machine, grinder, beans | K105: Monthly machine rental with free routine maintenance and backup machine if repair > 24 h; special buy-out price after 3 years. Office programme: free machine against 15 kg/month beans, 6-month minimum. | L105: IDR 3.65m/month (model not stated); free machine for 15 kg/month | M105: S84, S85
B106: Serviamo (serviamo.id) | C106: 3 | D106: Espresso machine (coffee-shop package) | K106: Coffee-shop package from IDR 3.5m/month, min. 6 months (monthly billing needs ≥ 1-year contract); service every 3–4 months; barista training. | L106: From IDR 3.5m/month | M106: S88
B107: Jakarta roasters – Empo Coffee Roastery, Delta Coffee (+ specialty roasters to approach) | C107: 4 | D107: Espresso machine + grinders against a bean contract | K107: B2B/HORECA supply desks listed; machine-loan terms not published → ask for written offer: machine model, kg minimum, bean price, contract length, exit fee. | L107: Model assumption: +IDR 40k/kg | M107: S102, S103
B108: Refcon Indonesia – YukSewa | C108: 3 | D108: Upright chiller/freezer, fridges, display chillers | K108: Monthly rental with deposit per unit. | L108: Upright IDR 0.88–1.58m/month (deposit 1.1–1.3m); fridge 0.31–0.70m; showcase 0.26–0.39m | M108: S87
B109: Jagoan Sewa | C109: 3 | D109: Display chillers (short term) | K109: Event-oriented; deposit IDR 300k/unit; delivery IDR 185–200k. | L109: Showcase 180–280 L: IDR 500–650k/month | M109: S98
B110: Beverage brands – PT Coca-Cola Europacific Partners Indonesia and other drink brands | C110: 4 | D110: Drinks display chiller | K110: Showcases lent free to outlets that meet sales-volume / listing conditions, via sales rep proposal. | L110: Free (conditional) | M110: S94, S104
...

Sheet Funding
A1: Funding, Bank Need & PT PMA Capital Check
A2: Is CHF 200k enough? Does the bank have to be involved? Compares investment need with equity and Indonesian foreign-investment rules.
A3: Jonas note; | B3: I had a brief look at what a PT PMA is but have not been into details
B4: Funding is also a questions where I have little information for the moment, and therefore I did not
B5: spend much time on. @Sam: What scope is expected from us
A6: Item | B6: IDR | C6: CHF | D6: Comment
A7: Total investment requirement (active CAPEX sheet – Inputs!H4) | B7: =CHOOSE(Inputs!$H$4,'CAPEX (Buy)'!$H$37,'CAPEX (Rent)'!$H$40) -> 4.2662461e+09 | C7: =B7/Inputs!$H$10 -> 197511.39
A8: Founder equity | B8: =Inputs!$H$82*Inputs!$H$10 -> 4320000000 | C8: =B8/Inputs!$H$10 -> 200000 | D8: Brief: CHF 200k
A9: Funding gap (+) / surplus (−) | B9: =B7-B8 -> -53753870 | C9: =B9/Inputs!$H$10 -> -2488.6051
A10: Bank loan (if switched on) | B10: =IF(Inputs!$H$83=1,MAX(0,B9),0) -> 0 | C10: =B10/Inputs!$H$10 -> 0 | D10: Local banks rarely lend to a new PT PMA without collateral/track record – likely a Swiss loan to the parent or shareholder loan
A11: Additional equity still required | B11: =MAX(0,B7-B8-B10) -> 0 | C11: =B11/Inputs!$H$10 -> 0 | D11: Must be zero for the plan to be funded
A12: Cash surplus at opening (equity beyond need) | B12: =MAX(0,B8-B7) -> 53753870 | C12: =B12/Inputs!$H$10 -> 2488.6051
A13: Opening cash at month 1 (WC reserve + surplus) | B13: =CHOOSE(Inputs!$H$4,'CAPEX (Buy)'!$H$36,'CAPEX (Rent)'!$H$39)+B12 -> 8.1393221e+08 | C13: =B13/Inputs!$H$10 -> 37682.047 | D13: Feeds PnL_Monthly
A15: Loan terms
A16: Interest rate p.a. | B16: =Inputs!$H$84 -> 0.105
A17: Tenor (months) | B17: =Inputs!$H$85 -> 48
A18: Monthly annuity payment | B18: =IF(B10>0,PMT(B16/12,B17,-B10),0) -> 0 | C18: =B18/Inputs!$H$10 -> 0
A19: Debt service cover (year-2 EBITDA ÷ year-2 debt service) | B19: =IFERROR(Annual!D11/(B18*12),"n/a") -> n/a | D19: Banks usually want ≥ 1.25–1.5x
A21: PT PMA CAPITAL RULES (BKPM Reg. 5/2025 – confirm with Indonesian lawyer)
A22: Required minimum paid-up capital (IDR 2.5bn × KBLI codes) | B22: =Inputs!$H$87*Inputs!$H$86 -> 2500000000 | C22: =B22/Inputs!$H$10 -> 115740.74
A23: Founder equity vs paid-up requirement | B23: =IF(B8>=B22,"OK – equity covers paid-up capital","SHORT by "&TEXT(B22-B8,"#,##0")&" IDR") -> OK – equity covers paid-up capital
A24: Required investment plan declared in OSS (IDR 10bn × KBLI) | B24: =Inputs!$H$88*Inputs!$H$86 -> 10000000000 | C24: =B24/Inputs!$H$10 -> 462962.96
A25: Model investment vs. investment plan | B25: =B7/B24 -> 0.42662461 | D25: If <100%: the plan must be realised over time (more outlets) or another structure is needed – key legal question
A27: Structuring options to discuss with a lawyer (not verified): local partner PT (PMDN) with licence/franchise from CORSA; JV; master franchise; PT PMA sized for a multi-outlet roll-out.
A32: SOURCES & CALCULATION BASIS – Funding
A33: Figure / cells | B33: Value used (live) | C33: Source ID(s) → Sources sheet | E33: How the figure was derived from the source | N33: Evidence status
A34: Total investment (B5) | B34: =Funding!B7 -> 4.2662461e+09 | C34: CAPEX sheet (S10, S64–S70) | E34: Linked from CAPEX!H36. | N34: Partly sourced
A35: Founder equity (B6) | B35: =Funding!B8 -> 4320000000 | C35: Brief; S16 | E35: CHF 200,000 × FX rate. | N35: Decision / policy
A36: Loan rate & tenor (B14:B15) | B36: =Funding!B16 -> 0.105 | C36: S19, S17, S49 | E36: 8.01% SBDK + ~2.5 pp risk premium; tenor 48 months within 3–5 yr benchmark. | N36: Derived from sources
A37: Debt service cover target (D17: 1.25–1.5x) | B37: =Funding!B19 -> n/a | C37: — | E37: Common bank covenant level – confirm with lender. | N37: Assumption – validate
A38: PT PMA paid-up capital & investment plan (rows 20–23) | B38: =Funding!B22 -> 2500000000 | C38: S01, S02 | E38: IDR 2.5bn paid-up and IDR 10bn plan per KBLI (BKPM Reg. 5/2025). | N38: Sourced

Sheet Scenarios
A1: Scenario Comparison – Steady-State Unit Economics (mature month, year-1 prices)
A2: Each column reads its own scenario column in Inputs, so all three are always live. Column F = active scenario. Full monthly dynamics → PnL_Monthly.
A3: As mentionned previously: the scenarios need further refinements and confirmation
A4: Line | B4: Unit | C4: Conservative | D4: Base | E4: Optimistic | F4: ACTIVE | G4: Comment
A5: Volume & revenue
A6: Guests per day (in-store) | B6: # | C6: =Inputs!$E$33+Inputs!$E$35+Inputs!$E$37+Inputs!$E$39 -> 155 | D6: =Inputs!$F$33+Inputs!$F$35+Inputs!$F$37+Inputs!$F$39 -> 200 | E6: =Inputs!$G$33+Inputs!$G$35+Inputs!$G$37+Inputs!$G$39 -> 255 | F6: =CHOOSE(Inputs!$D$4,C6,D6,E6) -> 200
A7: In-store revenue per day | B7: IDR | C7: =Inputs!$E$33*Inputs!$E$34+Inputs!$E$35*Inputs!$E$36+Inputs!$E$37*Inputs!$E$38+Inputs!$E$39*Inputs!$E$40 -> 14400000 | D7: =Inputs!$F$33*Inputs!$F$34+Inputs!$F$35*Inputs!$F$36+Inputs!$F$37*Inputs!$F$38+Inputs!$F$39*Inputs!$F$40 -> 20675000 | E7: =Inputs!$G$33*Inputs!$G$34+Inputs!$G$35*Inputs!$G$36+Inputs!$G$37*Inputs!$G$38+Inputs!$G$39*Inputs!$G$40 -> 29550000 | F7: =CHOOSE(Inputs!$D$4,C7,D7,E7) -> 20675000
A8: Avg net spend per guest | B8: IDR | C8: =C7/C6 -> 92903.226 | D8: =D7/D6 -> 103375 | E8: =E7/E6 -> 115882.35 | F8: =CHOOSE(Inputs!$D$4,C8,D8,E8) -> 103375
A9: Delivery revenue per day | B9: IDR | C9: =Inputs!$E$41*Inputs!$E$42 -> 1500000 | D9: =Inputs!$F$41*Inputs!$F$42 -> 2875000 | E9: =Inputs!$G$41*Inputs!$G$42 -> 4550000 | F9: =CHOOSE(Inputs!$D$4,C9,D9,E9) -> 2875000
A10: F&B revenue per month | B10: IDR | C10: =(C7+C9)*Inputs!$E$12 -> 477000000 | D10: =(D7+D9)*Inputs!$F$12 -> 706500000 | E10: =(E7+E9)*Inputs!$G$12 -> 1023000000 | F10: =CHOOSE(Inputs!$D$4,C10,D10,E10) -> 706500000
A11: Events & B2B | B11: IDR | C11: =Inputs!$E$44 -> 0 | D11: =Inputs!$F$44 -> 15000000 | E11: =Inputs!$G$44 -> 25000000 | F11: =CHOOSE(Inputs!$D$4,C11,D11,E11) -> 15000000
A12: Retail | B12: IDR | C12: =C10*Inputs!$E$45 -> 4770000 | D12: =D10*Inputs!$F$45 -> 14130000 | E12: =E10*Inputs!$G$45 -> 35805000 | F12: =CHOOSE(Inputs!$D$4,C12,D12,E12) -> 14130000
A13: TOTAL REVENUE / MONTH | B13: IDR | C13: =C10+C11+C12 -> 481770000 | D13: =D10+D11+D12 -> 735630000 | E13: =E10+E11+E12 -> 1083805000 | F13: =CHOOSE(Inputs!$D$4,C13,D13,E13) -> 735630000
A14: Total revenue / year | B14: CHF | C14: =C13*12/Inputs!$E$10 -> 282011.71 | D14: =D13*12/Inputs!$F$10 -> 408683.33 | E14: =E13*12/Inputs!$G$10 -> 578029.33 | F14: =CHOOSE(Inputs!$D$4,C14,D14,E14) -> 408683.33
A15: Variable costs
A16: COGS (F&B + events + retail) | B16: IDR | C16: =C10*(Menu!$E$29+Inputs!$E$49)+C11*Inputs!$E$50+C12*Inputs!$E$51 -> 1.536687e+08 | D16: =D10*(Menu!$E$29+Inputs!$F$49)+D11*Inputs!$F$50+D12*Inputs!$F$51 -> 2.1519115e+08 | E16: =E10*(Menu!$E$29+Inputs!$G$49)+E11*Inputs!$G$50+E12*Inputs!$G$51 -> 2.9768071e+08 | F16: =CHOOSE(Inputs!$D$4,C16,D16,E16) -> 2.1519115e+08
A17: Packaging | B17: IDR | C17: =(C7*Inputs!$E$43+C9)*Inputs!$E$12*Inputs!$E$52 -> 10476000 | D17: =(D7*Inputs!$F$43+D9)*Inputs!$F$12*Inputs!$F$52 -> 13616250 | E17: =(E7*Inputs!$G$43+E9)*Inputs!$G$12*Inputs!$G$52 -> 16098000 | F17: =CHOOSE(Inputs!$D$4,C17,D17,E17) -> 13616250
A18: Waste & spoilage | B18: IDR | C18: =C10*Inputs!$E$53 -> 9540000 | D18: =D10*Inputs!$F$53 -> 10597500 | E18: =E10*Inputs!$G$53 -> 10230000 | F18: =CHOOSE(Inputs!$D$4,C18,D18,E18) -> 10597500
A19: Delivery commission (+VAT on fee) | B19: IDR | C19: =C9*Inputs!$E$12*Inputs!$E$54*(1+Inputs!$E$18) -> 13986000 | D19: =D9*Inputs!$F$12*Inputs!$F$54*(1+Inputs!$F$18) -> 22019625 | E19: =E9*Inputs!$G$12*Inputs!$G$54*(1+Inputs!$G$18) -> 30303000 | F19: =CHOOSE(Inputs!$D$4,C19,D19,E19) -> 22019625
A20: Payment fees | B20: IDR | C20: =(C13-C9*Inputs!$E$12)*Inputs!$E$55 -> 6551550 | D20: =(D13-D9*Inputs!$F$12)*Inputs!$F$55 -> 7792560 | E20: =(E13-E9*Inputs!$G$12)*Inputs!$G$55 -> 8525745 | F20: =CHOOSE(Inputs!$D$4,C20,D20,E20) -> 7792560
A21: Marketing, maintenance, misc., royalty | B21: IDR | C21: =C13*(Inputs!$E$56+Inputs!$E$57+Inputs!$E$58+Inputs!$E$59) -> 36132750 | D21: =D13*(Inputs!$F$56+Inputs!$F$57+Inputs!$F$58+Inputs!$F$59) -> 40459650 | E21: =E13*(Inputs!$G$56+Inputs!$G$57+Inputs!$G$58+Inputs!$G$59) -> 43352200 | F21: =CHOOSE(Inputs!$D$4,C21,D21,E21) -> 40459650
A22: Total variable costs | B22: IDR | C22: =SUM(C16:C21) -> 2.30355e+08 | D22: =SUM(D16:D21) -> 3.0967673e+08 | E22: =SUM(E16:E21) -> 4.0618966e+08 | F22: =CHOOSE(Inputs!$D$4,C22,D22,E22) -> 3.0967673e+08
A23: Contribution margin | B23: IDR | C23: =C13-C22 -> 2.51415e+08 | D23: =D13-D22 -> 4.2595327e+08 | E23: =E13-E22 -> 6.7761534e+08 | F23: =CHOOSE(Inputs!$D$4,C23,D23,E23) -> 4.2595327e+08
A24: Contribution margin % | B24: % | C24: =C23/C13 -> 0.52185689 | D24: =D23/D13 -> 0.57903194 | E24: =E23/E13 -> 0.62521887 | F24: =CHOOSE(Inputs!$D$4,C24,D24,E24) -> 0.57903194
A25: Fixed costs
A26: Staff (incl. BPJS, THR, benefits) | B26: IDR | C26: =Staffing!$J$17*Inputs!$E$62*(1+Inputs!$E$63+Inputs!$E$64)+Staffing!$B$15*Inputs!$E$65 -> 185573283 | D26: =Staffing!$J$17*Inputs!$F$62*(1+Inputs!$F$63+Inputs!$F$64)+Staffing!$B$15*Inputs!$F$65 -> 166907330 | E26: =Staffing!$J$17*Inputs!$G$62*(1+Inputs!$G$63+Inputs!$G$64)+Staffing!$B$15*Inputs!$G$65 -> 161881030 | F26: =CHOOSE(Inputs!$D$4,C26,D26,E26) -> 166907330
A27: Rent (incl. gross-up) | B27: IDR | C27: =Inputs!$E$25*Inputs!$E$21*Inputs!$E$22*(1+Inputs!$E$27) -> 70364536 | D27: =Inputs!$F$25*Inputs!$F$21*Inputs!$F$22*(1+Inputs!$F$27) -> 37774219 | E27: =Inputs!$G$25*Inputs!$G$21*Inputs!$G$22*(1+Inputs!$G$27) -> 30774208 | F27: =CHOOSE(Inputs!$D$4,C27,D27,E27) -> 37774219
A28: Service charge / CAM | B28: IDR | C28: =Inputs!$E$26*Inputs!$E$21*Inputs!$E$22 -> 0 | D28: =Inputs!$F$26*Inputs!$F$21*Inputs!$F$22 -> 0 | E28: =Inputs!$G$26*Inputs!$G$21*Inputs!$G$22 -> 0 | F28: =CHOOSE(Inputs!$D$4,C28,D28,E28) -> 0
A29: Utilities | B29: IDR | C29: =Inputs!$E$73*Inputs!$E$74+Inputs!$E$75 -> 23891700 | D29: =Inputs!$F$73*Inputs!$F$74+Inputs!$F$75 -> 19002300 | E29: =Inputs!$G$73*Inputs!$G$74+Inputs!$G$75 -> 15835250 | F29: =CHOOSE(Inputs!$D$4,C29,D29,E29) -> 19002300
A30: Fixed overheads (mgmt, accounting, insurance…) + equipment payments in Lease mode | B30: IDR | C30: =SUM(Inputs!E67:E72)+IF(Inputs!$H$4=2,'CAPEX (Rent)'!$H$47,0) -> 79483150 | D30: =SUM(Inputs!F67:F72)+IF(Inputs!$H$4=2,'CAPEX (Rent)'!$H$47,0) -> 67483150 | E30: =SUM(Inputs!G67:G72)+IF(Inputs!$H$4=2,'CAPEX (Rent)'!$H$47,0) -> 57483150 | F30: =CHOOSE(Inputs!$D$4,C30,D30,E30) -> 67483150
A31: Total fixed costs | B31: IDR | C31: =SUM(C26:C30) -> 3.5931267e+08 | D31: =SUM(D26:D30) -> 2.91167e+08 | E31: =SUM(E26:E30) -> 2.6597364e+08 | F31: =CHOOSE(Inputs!$D$4,C31,D31,E31) -> 2.91167e+08
A32: Fixed costs excl. rent & service charge | B32: IDR | C32: =C31-C27-C28 -> 2.8894813e+08 | D32: =D31-D27-D28 -> 2.5339278e+08 | E32: =E31-E27-E28 -> 2.3519943e+08 | F32: =CHOOSE(Inputs!$D$4,C32,D32,E32) -> 2.5339278e+08
A33: Profitability
A34: EBITDA / month (steady state) | B34: IDR | C34: =C23-C31 -> -1.0789767e+08 | D34: =D23-D31 -> 1.3478627e+08 | E34: =E23-E31 -> 4.116417e+08 | F34: =CHOOSE(Inputs!$D$4,C34,D34,E34) -> 1.3478627e+08
A35: EBITDA margin | B35: % | C35: =C34/C13 -> -0.22396096 | D35: =D34/D13 -> 0.18322563 | E35: =E34/E13 -> 0.37981159 | F35: =CHOOSE(Inputs!$D$4,C35,D35,E35) -> 0.18322563
A36: EBITDA / year | B36: CHF | C36: =C34*12/Inputs!$E$10 -> -63159.613 | D36: =D34*12/Inputs!$F$10 -> 74881.261 | E36: =E34*12/Inputs!$G$10 -> 219542.24 | F36: =CHOOSE(Inputs!$D$4,C36,D36,E36) -> 74881.261
A37: Food & beverage cost % of revenue | B37: % | C37: =C16/C13 -> 0.31896694 | D37: =D16/D13 -> 0.29252633 | E37: =E16/E13 -> 0.27466261 | F37: =CHOOSE(Inputs!$D$4,C37,D37,E37) -> 0.29252633
A38: Staff cost % of revenue | B38: % | C38: =C26/C13 -> 0.38519062 | D38: =D26/D13 -> 0.22689033 | E38: =E26/E13 -> 0.14936361 | F38: =CHOOSE(Inputs!$D$4,C38,D38,E38) -> 0.22689033
A39: Prime cost % (COGS + staff) | B39: % | C39: =(C16+C26)/C13 -> 0.70415756 | D39: =(D16+D26)/D13 -> 0.51941666 | E39: =(E16+E26)/E13 -> 0.42402623 | F39: =CHOOSE(Inputs!$D$4,C39,D39,E39) -> 0.51941666 | G39: Benchmark ≤ 60–65%
A40: Occupancy cost % (rent + SC) | B40: % | C40: =(C27+C28)/C13 -> 0.14605421 | D40: =(D27+D28)/D13 -> 0.051349481 | E40: =(E27+E28)/E13 -> 0.028394598 | F40: =CHOOSE(Inputs!$D$4,C40,D40,E40) -> 0.051349481 | G40: Benchmark ≤ 10–12%
A41: Break-even
A42: Break-even revenue / month | B42: IDR | C42: =IFERROR(C31/C24,0) -> 6.885272e+08 | D42: =IFERROR(D31/D24,0) -> 5.0285136e+08 | E42: =IFERROR(E31/E24,0) -> 4.2540884e+08 | F42: =CHOOSE(Inputs!$D$4,C42,D42,E42) -> 5.0285136e+08
A43: Break-even revenue / trading day | B43: IDR | C43: =C42/Inputs!$E$12 -> 22950907 | D43: =D42/Inputs!$F$12 -> 16761712 | E43: =E42/Inputs!$G$12 -> 14180295 | F43: =CHOOSE(Inputs!$D$4,C43,D43,E43) -> 16761712
A44: Break-even revenue / day | B44: CHF | C44: =C43/Inputs!$E$10 -> 1119.5564 | D44: =D43/Inputs!$F$10 -> 776.00518 | E44: =E43/Inputs!$G$10 -> 630.23532 | F44: =CHOOSE(Inputs!$D$4,C44,D44,E44) -> 776.00518
A45: Break-even guests / day (at current channel mix) | B45: # | C45: =C6*C42/C13 -> 221.52005 | D45: =D6*D42/D13 -> 136.71312 | E45: =E6*E42/E13 -> 100.09112 | F45: =CHOOSE(Inputs!$D$4,C45,D45,E45) -> 136.71312
A46: Margin of safety (revenue above break-even) | B46: % | C46: =1-C42/C13 -> -0.42916164 | D46: =1-D42/D13 -> 0.31643441 | E46: =1-E42/E13 -> 0.60748581 | F46: =CHOOSE(Inputs!$D$4,C46,D46,E46) -> 0.31643441
A47: Investment & payback
A48: Hard costs (incl. VAT, cost factor) | B48: IDR | C48: =CHOOSE(Inputs!$H$4,'CAPEX (Buy)'!$H$40,'CAPEX (Rent)'!$H$43)*Inputs!$E$77 -> 2.0629664e+09 | D48: =CHOOSE(Inputs!$H$4,'CAPEX (Buy)'!$H$40,'CAPEX (Rent)'!$H$43)*Inputs!$F$77 -> 1.7938838e+09 | E48: =CHOOSE(Inputs!$H$4,'CAPEX (Buy)'!$H$40,'CAPEX (Rent)'!$H$43)*Inputs!$G$77 -> 1.7041897e+09 | F48: =CHOOSE(Inputs!$D$4,C48,D48,E48) -> 1.7938838e+09
A49: Soft costs incl. pre-opening payroll | B49: IDR | C49: =CHOOSE(Inputs!$H$4,'CAPEX (Buy)'!$H$41,'CAPEX (Rent)'!$H$44)+Inputs!$E$79*C26 -> 9.5545992e+08 | D49: =CHOOSE(Inputs!$H$4,'CAPEX (Buy)'!$H$41,'CAPEX (Rent)'!$H$44)+Inputs!$F$79*D26 -> 8.4400733e+08 | E49: =CHOOSE(Inputs!$H$4,'CAPEX (Buy)'!$H$41,'CAPEX (Rent)'!$H$44)+Inputs!$G$79*E26 -> 7.9851077e+08 | F49: =CHOOSE(Inputs!$D$4,C49,D49,E49) -> 8.4400733e+08
A50: Contingency | B50: IDR | C50: =Inputs!$E$78*(C48+C49) -> 4.5276395e+08 | D50: =Inputs!$F$78*(D48+D49) -> 2.6378912e+08 | E50: =Inputs!$G$78*(E48+E49) -> 1.8770253e+08 | F50: =CHOOSE(Inputs!$D$4,C50,D50,E50) -> 2.6378912e+08
A51: Lease (fit-out rent, prepayment, deposit) | B51: IDR | C51: =C27*(Inputs!$E$31+Inputs!$E$29+Inputs!$E$30)+C28*Inputs!$E$31 -> 2.1109361e+09 | D51: =D27*(Inputs!$F$31+Inputs!$F$29+Inputs!$F$30)+D28*Inputs!$F$31 -> 604387500 | E51: =E27*(Inputs!$G$31+Inputs!$G$29+Inputs!$G$30)+E28*Inputs!$G$31 -> 4.3083891e+08 | F51: =CHOOSE(Inputs!$D$4,C51,D51,E51) -> 604387500
A52: Working-capital reserve | B52: IDR | C52: =Inputs!$E$80*(C26+C30+C29) -> 8.668444e+08 | D52: =Inputs!$F$80*(D26+D30+D29) -> 7.6017834e+08 | E52: =Inputs!$G$80*(E26+E30+E29) -> 4.7039886e+08 | F52: =CHOOSE(Inputs!$D$4,C52,D52,E52) -> 7.6017834e+08
A53: TOTAL INVESTMENT | B53: IDR | C53: =SUM(C48:C52) -> 6.4489708e+09 | D53: =SUM(D48:D52) -> 4.2662461e+09 | E53: =SUM(E48:E52) -> 3.5916407e+09 | F53: =CHOOSE(Inputs!$D$4,C53,D53,E53) -> 4.2662461e+09
A54: Total investment | B54: CHF | C54: =C53/Inputs!$E$10 -> 314583.94 | D54: =D53/Inputs!$F$10 -> 197511.39 | E54: =E53/Inputs!$G$10 -> 159628.48 | F54: =CHOOSE(Inputs!$D$4,C54,D54,E54) -> 197511.39
A55: Gap vs founder equity (+ = need bank/extra equity) | B55: CHF | C55: =C54-Inputs!$E$82 -> 114583.94 | D55: =D54-Inputs!$F$82 -> -2488.6051 | E55: =E54-Inputs!$G$82 -> -40371.523 | F55: =CHOOSE(Inputs!$D$4,C55,D55,E55) -> -2488.6051
A56: Simple payback (years) = investment ÷ annual EBITDA after tax | B56: years | C56: =IF(C34>0,C53/(C34*12*(1-Inputs!$E$16)),"never") -> never | D56: =IF(D34>0,D53/(D34*12*(1-Inputs!$F$16)),"never") -> 3.3816169 | E56: =IF(E34>0,E53/(E34*12*(1-Inputs!$G$16)),"never") -> 0.93217547 | F56: =CHOOSE(Inputs!$D$4,C56,D56,E56) -> 3.3816169 | G56: Steady state – ignores ramp-up; see Dashboard for full-model payback
A58: Check: ACTIVE investment equals CAPEX sheet total | F58: =IF(ABS(F53-CHOOSE(Inputs!$H$4,'CAPEX (Buy)'!$H$37,'CAPEX (Rent)'!$H$40))<1,"OK","MISMATCH") -> OK
A59: Check: ACTIVE revenue equals Revenue sheet total | F59: =IF(ABS(F13-Revenue!$E$23)<1,"OK","MISMATCH") -> OK
A62: SOURCES & CALCULATION BASIS – Scenarios
A63: Figure / cells | B63: Value used (live) | D63: Source ID(s) → Sources sheet | H63: How the figure was derived from the source | Q63: Evidence status
A64: Scenario columns C/D/E | B64: — | D64: Inputs cols E/F/G | H64: Each column reads its own scenario column in Inputs – every number traces back to Inputs col I/K. | Q64: Model formula
A65: Revenue lines (rows 6–14) | B65: =Scenarios!F13 -> 735630000 | D65: S31, S33, S43, S46 | H65: Guests × spend per daypart + delivery + events + retail (Inputs rows 31–43). | Q65: Partly sourced
A66: Variable costs (rows 16–22) | B66: =Scenarios!F22 -> 3.0967673e+08 | D66: S12, S47–S54 | H66: % drivers from Inputs rows 47–57 × relevant revenue base. | Q66: Partly sourced
A67: Fixed costs (rows 26–31) | B67: =Scenarios!F31 -> 2.91167e+08 | D67: S04–S11, S20–S27, S55–S57, S73–S76 | H67: Staffing, rent, utilities, overheads. | Q67: Partly sourced
A68: Break-even (rows 42–46) | B68: =Scenarios!F43 -> 16761712 | D68: Methods sheet | H68: Fixed costs ÷ contribution margin % ÷ 30 days; guests = revenue ÷ blended spend. | Q68: Model formula
A69: Benchmarks for KPI rows 37–40 | B69: =Scenarios!F39 -> 0.51941666 | D69: S49 (food 28.5–30.3%, labour 26.9–29.4%, prime 55–60%); S51 (prime ≤60–65%, occupancy ≤8–10%) | H69: Use these ranges to judge the model's food %, staff %, prime cost % and occupancy %. | Q69: Derived from sources
A70: Payback after tax (row 56) | B70: =Scenarios!F56 -> 3.3816169 | D70: S15 (CIT 22%) | H70: Investment ÷ (annual EBITDA × (1 − 22%)). | Q70: Model formula

Sheet PnL_Monthly
A1: Monthly P&L and Cash Flow – 13 months (active scenario)
A2: Ramp-up, seasonality, price/wage/rent escalation, rent prepayment timing, loan and tax. All formulas – do not type over.
A4: Month # | C4: 1 | D4: 2 | E4: 3 | F4: 4 | G4: 5 | H4: 6 | I4: 7 | J4: 8 | K4: 9 | L4: 10 | M4: 11 | N4: 12 | O4: 13
A5: Month | C5: =EDATE(Inputs!$H$11,C4-1) -> 46569 | D5: =EDATE(Inputs!$H$11,D4-1) -> 46600 | E5: =EDATE(Inputs!$H$11,E4-1) -> 46631 | F5: =EDATE(Inputs!$H$11,F4-1) -> 46661 | G5: =EDATE(Inputs!$H$11,G4-1) -> 46692 | H5: =EDATE(Inputs!$H$11,H4-1) -> 46722 | I5: =EDATE(Inputs!$H$11,I4-1) -> 46753 | J5: =EDATE(Inputs!$H$11,J4-1) -> 46784 | ... O5: =EDATE(Inputs!$H$11,O4-1) -> 46935
A6: Operating year | C6: =INT((C4-1)/12)+1 -> 1 | D6: =INT((D4-1)/12)+1 -> 1 | E6: =INT((E4-1)/12)+1 -> 1 | F6: =INT((F4-1)/12)+1 -> 1 | G6: =INT((G4-1)/12)+1 -> 1 | H6: =INT((H4-1)/12)+1 -> 1 | I6: =INT((I4-1)/12)+1 -> 1 | J6: =INT((J4-1)/12)+1 -> 1 | ... O6: =INT((O4-1)/12)+1 -> 2
A7: Ramp-up % | C7: =MIN(1,Inputs!$H$46+(1-Inputs!$H$46)*(C4-1)/MAX(1,Inputs!$H$47-1)) -> 0.55 | D7: =MIN(1,Inputs!$H$46+(1-Inputs!$H$46)*(D4-1)/MAX(1,Inputs!$H$47-1)) -> 0.60625 | E7: =MIN(1,Inputs!$H$46+(1-Inputs!$H$46)*(E4-1)/MAX(1,Inputs!$H$47-1)) -> 0.6625 | F7: =MIN(1,Inputs!$H$46+(1-Inputs!$H$46)*(F4-1)/MAX(1,Inputs!$H$47-1)) -> 0.71875 | G7: =MIN(1,Inputs!$H$46+(1-Inputs!$H$46)*(G4-1)/MAX(1,Inputs!$H$47-1)) -> 0.775 | H7: =MIN(1,Inputs!$H$46+(1-Inputs!$H$46)*(H4-1)/MAX(1,Inputs!$H$47-1)) -> 0.83125 | I7: =MIN(1,Inputs!$H$46+(1-Inputs!$H$46)*(I4-1)/MAX(1,Inputs!$H$47-1)) -> 0.8875 | J7: =MIN(1,Inputs!$H$46+(1-Inputs!$H$46)*(J4-1)/MAX(1,Inputs!$H$47-1)) -> 0.94375 | ... O7: =MIN(1,Inputs!$H$46+(1-Inputs!$H$46)*(O4-1)/MAX(1,Inputs!$H$47-1)) -> 1
A8: Seasonality index | C8: =INDEX(Inputs!$H$92:$H$103,MONTH(C5)) -> 1 | D8: =INDEX(Inputs!$H$92:$H$103,MONTH(D5)) -> 1 | E8: =INDEX(Inputs!$H$92:$H$103,MONTH(E5)) -> 1 | F8: =INDEX(Inputs!$H$92:$H$103,MONTH(F5)) -> 1 | G8: =INDEX(Inputs!$H$92:$H$103,MONTH(G5)) -> 1 | H8: =INDEX(Inputs!$H$92:$H$103,MONTH(H5)) -> 1.08 | I8: =INDEX(Inputs!$H$92:$H$103,MONTH(I5)) -> 1 | J8: =INDEX(Inputs!$H$92:$H$103,MONTH(J5)) -> 0.92 | ... O8: =INDEX(Inputs!$H$92:$H$103,MONTH(O5)) -> 1
A9: Volume factor (ramp × season) | C9: =C7*C8 -> 0.55 | D9: =D7*D8 -> 0.60625 | E9: =E7*E8 -> 0.6625 | F9: =F7*F8 -> 0.71875 | G9: =G7*G8 -> 0.775 | H9: =H7*H8 -> 0.89775 | I9: =I7*I8 -> 0.8875 | J9: =J7*J8 -> 0.86825 | ... O9: =O7*O8 -> 1
A10: Price index | C10: =(1+Inputs!$H$13)^(C6-1) -> 1 | D10: =(1+Inputs!$H$13)^(D6-1) -> 1 | E10: =(1+Inputs!$H$13)^(E6-1) -> 1 | F10: =(1+Inputs!$H$13)^(F6-1) -> 1 | G10: =(1+Inputs!$H$13)^(G6-1) -> 1 | H10: =(1+Inputs!$H$13)^(H6-1) -> 1 | I10: =(1+Inputs!$H$13)^(I6-1) -> 1 | J10: =(1+Inputs!$H$13)^(J6-1) -> 1 | ... O10: =(1+Inputs!$H$13)^(O6-1) -> 1.04
A11: Wage index | C11: =(1+Inputs!$H$15)^(C6-1) -> 1 | D11: =(1+Inputs!$H$15)^(D6-1) -> 1 | E11: =(1+Inputs!$H$15)^(E6-1) -> 1 | F11: =(1+Inputs!$H$15)^(F6-1) -> 1 | G11: =(1+Inputs!$H$15)^(G6-1) -> 1 | H11: =(1+Inputs!$H$15)^(H6-1) -> 1 | I11: =(1+Inputs!$H$15)^(I6-1) -> 1 | J11: =(1+Inputs!$H$15)^(J6-1) -> 1 | ... O11: =(1+Inputs!$H$15)^(O6-1) -> 1.062
A12: Opex inflation index | C12: =(1+Inputs!$H$14)^(C6-1) -> 1 | D12: =(1+Inputs!$H$14)^(D6-1) -> 1 | E12: =(1+Inputs!$H$14)^(E6-1) -> 1 | F12: =(1+Inputs!$H$14)^(F6-1) -> 1 | G12: =(1+Inputs!$H$14)^(G6-1) -> 1 | H12: =(1+Inputs!$H$14)^(H6-1) -> 1 | I12: =(1+Inputs!$H$14)^(I6-1) -> 1 | J12: =(1+Inputs!$H$14)^(J6-1) -> 1 | ... O12: =(1+Inputs!$H$14)^(O6-1) -> 1.035
A13: REVENUE
A14: F&B in-store | C14: =Revenue!$E$19*C9*C10 -> 341137500 | D14: =Revenue!$E$19*D9*D10 -> 3.7602656e+08 | E14: =Revenue!$E$19*E9*E10 -> 4.1091563e+08 | F14: =Revenue!$E$19*F9*F10 -> 4.4580469e+08 | G14: =Revenue!$E$19*G9*G10 -> 480693750 | H14: =Revenue!$E$19*H9*H10 -> 5.5682944e+08 | I14: =Revenue!$E$19*I9*I10 -> 550471875 | J14: =Revenue!$E$19*J9*J10 -> 5.3853206e+08 | ... O14: =Revenue!$E$19*O9*O10 -> 645060000
A15: F&B delivery (gross) | C15: =Revenue!$E$20*C9*C10 -> 47437500 | D15: =Revenue!$E$20*D9*D10 -> 52289063 | E15: =Revenue!$E$20*E9*E10 -> 57140625 | F15: =Revenue!$E$20*F9*F10 -> 61992188 | G15: =Revenue!$E$20*G9*G10 -> 66843750 | H15: =Revenue!$E$20*H9*H10 -> 77430938 | I15: =Revenue!$E$20*I9*I10 -> 76546875 | J15: =Revenue!$E$20*J9*J10 -> 74886562 | ... O15: =Revenue!$E$20*O9*O10 -> 89700000
A16: Events & B2B | C16: =Revenue!$E$21*C7*C10 -> 8250000 | D16: =Revenue!$E$21*D7*D10 -> 9093750 | E16: =Revenue!$E$21*E7*E10 -> 9937500 | F16: =Revenue!$E$21*F7*F10 -> 10781250 | G16: =Revenue!$E$21*G7*G10 -> 11625000 | H16: =Revenue!$E$21*H7*H10 -> 12468750 | I16: =Revenue!$E$21*I7*I10 -> 13312500 | J16: =Revenue!$E$21*J7*J10 -> 14156250 | ... O16: =Revenue!$E$21*O7*O10 -> 15600000
A17: Retail | C17: =(C14+C15)*Inputs!$H$45 -> 7771500 | D17: =(D14+D15)*Inputs!$H$45 -> 8566312.5 | E17: =(E14+E15)*Inputs!$H$45 -> 9361125 | F17: =(F14+F15)*Inputs!$H$45 -> 10155938 | G17: =(G14+G15)*Inputs!$H$45 -> 10950750 | H17: =(H14+H15)*Inputs!$H$45 -> 12685208 | I17: =(I14+I15)*Inputs!$H$45 -> 12540375 | J17: =(J14+J15)*Inputs!$H$45 -> 12268372 | ... O17: =(O14+O15)*Inputs!$H$45 -> 14695200
A18: TOTAL REVENUE | B18: TOTAL REVENUE | C18: =SUM(C14:C17) -> 404596500 | D18: =SUM(D14:D17) -> 4.4597569e+08 | E18: =SUM(E14:E17) -> 4.8735488e+08 | F18: =SUM(F14:F17) -> 5.2873406e+08 | G18: =SUM(G14:G17) -> 570113250 | H18: =SUM(H14:H17) -> 6.5941433e+08 | I18: =SUM(I14:I17) -> 652871625 | J18: =SUM(J14:J17) -> 6.3984325e+08 | ... O18: =SUM(O14:O17) -> 765055200
A19: VARIABLE COSTS
A20: Food & beverage cost | C20: =(C14+C15)*OPEX!$B$35+C16*Inputs!$H$50+C17*Inputs!$H$51 -> 1.1835513e+08 | D20: =(D14+D15)*OPEX!$B$35+D16*Inputs!$H$50+D17*Inputs!$H$51 -> 1.3045963e+08 | E20: =(E14+E15)*OPEX!$B$35+E16*Inputs!$H$50+E17*Inputs!$H$51 -> 1.4256413e+08 | F20: =(F14+F15)*OPEX!$B$35+F16*Inputs!$H$50+F17*Inputs!$H$51 -> 1.5466864e+08 | G20: =(G14+G15)*OPEX!$B$35+G16*Inputs!$H$50+G17*Inputs!$H$51 -> 1.6677314e+08 | H20: =(H14+H15)*OPEX!$B$35+H16*Inputs!$H$50+H17*Inputs!$H$51 -> 1.9283873e+08 | I20: =(I14+I15)*OPEX!$B$35+I16*Inputs!$H$50+I17*Inputs!$H$51 -> 1.9098214e+08 | J20: =(J14+J15)*OPEX!$B$35+J16*Inputs!$H$50+J17*Inputs!$H$51 -> 1.8723609e+08 | ... O20: =(O14+O15)*OPEX!$B$35+O16*Inputs!$H$50+O17*Inputs!$H$51 -> 2.2379879e+08
A21: Packaging | C21: =(C14*Inputs!$H$43+C15)*Inputs!$H$52 -> 7488937.5 | D21: =(D14*Inputs!$H$43+D15)*Inputs!$H$52 -> 8254851.6 | E21: =(E14*Inputs!$H$43+E15)*Inputs!$H$52 -> 9020765.6 | F21: =(F14*Inputs!$H$43+F15)*Inputs!$H$52 -> 9786679.7 | G21: =(G14*Inputs!$H$43+G15)*Inputs!$H$52 -> 10552594 | H21: =(H14*Inputs!$H$43+H15)*Inputs!$H$52 -> 12223988 | I21: =(I14*Inputs!$H$43+I15)*Inputs!$H$52 -> 12084422 | J21: =(J14*Inputs!$H$43+J15)*Inputs!$H$52 -> 11822309 | ... O21: =(O14*Inputs!$H$43+O15)*Inputs!$H$52 -> 14160900
A22: Waste & spoilage | C22: =(C14+C15)*Inputs!$H$53 -> 5828625 | D22: =(D14+D15)*Inputs!$H$53 -> 6424734.4 | E22: =(E14+E15)*Inputs!$H$53 -> 7020843.8 | F22: =(F14+F15)*Inputs!$H$53 -> 7616953.1 | G22: =(G14+G15)*Inputs!$H$53 -> 8213062.5 | H22: =(H14+H15)*Inputs!$H$53 -> 9513905.6 | I22: =(I14+I15)*Inputs!$H$53 -> 9405281.2 | J22: =(J14+J15)*Inputs!$H$53 -> 9201279.4 | ... O22: =(O14+O15)*Inputs!$H$53 -> 11021400
A23: Delivery commission (+VAT) | C23: =C15*Inputs!$H$54*(1+Inputs!$H$18) -> 12110794 | D23: =D15*Inputs!$H$54*(1+Inputs!$H$18) -> 13349398 | E23: =E15*Inputs!$H$54*(1+Inputs!$H$18) -> 14588002 | F23: =F15*Inputs!$H$54*(1+Inputs!$H$18) -> 15826605 | G23: =G15*Inputs!$H$54*(1+Inputs!$H$18) -> 17065209 | H23: =H15*Inputs!$H$54*(1+Inputs!$H$18) -> 19768118 | I23: =I15*Inputs!$H$54*(1+Inputs!$H$18) -> 19542417 | J23: =J15*Inputs!$H$54*(1+Inputs!$H$18) -> 19118539 | ... O23: =O15*Inputs!$H$54*(1+Inputs!$H$18) -> 22900410
A24: Payment fees | C24: =(C18-C15)*Inputs!$H$55 -> 4285908 | D24: =(D18-D15)*Inputs!$H$55 -> 4724239.5 | E24: =(E18-E15)*Inputs!$H$55 -> 5162571 | F24: =(F18-F15)*Inputs!$H$55 -> 5600902.5 | G24: =(G18-G15)*Inputs!$H$55 -> 6039234 | H24: =(H18-H15)*Inputs!$H$55 -> 6983800.7 | I24: =(I18-I15)*Inputs!$H$55 -> 6915897 | J24: =(J18-J15)*Inputs!$H$55 -> 6779480.2 | ... O24: =(O18-O15)*Inputs!$H$55 -> 8104262.4
A25: Marketing | C25: =C18*Inputs!$H$56 -> 12137895 | D25: =D18*Inputs!$H$56 -> 13379271 | E25: =E18*Inputs!$H$56 -> 14620646 | F25: =F18*Inputs!$H$56 -> 15862022 | G25: =G18*Inputs!$H$56 -> 17103398 | H25: =H18*Inputs!$H$56 -> 19782430 | I25: =I18*Inputs!$H$56 -> 19586149 | J25: =J18*Inputs!$H$56 -> 19195297 | ... O25: =O18*Inputs!$H$56 -> 22951656
A26: Repairs & maintenance | C26: =C18*Inputs!$H$57 -> 6068947.5 | D26: =D18*Inputs!$H$57 -> 6689635.3 | E26: =E18*Inputs!$H$57 -> 7310323.1 | F26: =F18*Inputs!$H$57 -> 7931010.9 | G26: =G18*Inputs!$H$57 -> 8551698.8 | H26: =H18*Inputs!$H$57 -> 9891215 | I26: =I18*Inputs!$H$57 -> 9793074.4 | J26: =J18*Inputs!$H$57 -> 9597648.7 | ... O26: =O18*Inputs!$H$57 -> 11475828
A27: Miscellaneous + royalty | C27: =C18*(Inputs!$H$58+Inputs!$H$59) -> 4045965 | D27: =D18*(Inputs!$H$58+Inputs!$H$59) -> 4459756.9 | E27: =E18*(Inputs!$H$58+Inputs!$H$59) -> 4873548.8 | F27: =F18*(Inputs!$H$58+Inputs!$H$59) -> 5287340.6 | G27: =G18*(Inputs!$H$58+Inputs!$H$59) -> 5701132.5 | H27: =H18*(Inputs!$H$58+Inputs!$H$59) -> 6594143.3 | I27: =I18*(Inputs!$H$58+Inputs!$H$59) -> 6528716.2 | J27: =J18*(Inputs!$H$58+Inputs!$H$59) -> 6398432.5 | ... O27: =O18*(Inputs!$H$58+Inputs!$H$59) -> 7650552
A28: CONTRIBUTION AFTER VARIABLE COSTS | C28: =C18-SUM(C20:C27) -> 2.342743e+08 | D28: =D18-SUM(D20:D27) -> 2.5823417e+08 | E28: =E18-SUM(E20:E27) -> 2.8219404e+08 | F28: =F18-SUM(F20:F27) -> 3.0615391e+08 | G28: =G18-SUM(G20:G27) -> 3.3011378e+08 | H28: =H18-SUM(H20:H27) -> 3.81818e+08 | I28: =I18-SUM(I20:I27) -> 3.7803353e+08 | J28: =J18-SUM(J20:J27) -> 3.7049417e+08 | ... O28: =O18-SUM(O20:O27) -> 4.429914e+08
A29: FIXED COSTS
A30: Staff | C30: =Staffing!$J$15*C11 -> 166907330 | D30: =Staffing!$J$15*D11 -> 166907330 | E30: =Staffing!$J$15*E11 -> 166907330 | F30: =Staffing!$J$15*F11 -> 166907330 | G30: =Staffing!$J$15*G11 -> 166907330 | H30: =Staffing!$J$15*H11 -> 166907330 | I30: =Staffing!$J$15*I11 -> 166907330 | J30: =Staffing!$J$15*J11 -> 166907330 | ... O30: =Staffing!$J$15*O11 -> 1.7725558e+08
A31: Rent (P&L, escalates yearly) | C31: =OPEX!$B$21*(1+Inputs!$H$28)^(C6-1) -> 37774219 | D31: =OPEX!$B$21*(1+Inputs!$H$28)^(D6-1) -> 37774219 | E31: =OPEX!$B$21*(1+Inputs!$H$28)^(E6-1) -> 37774219 | F31: =OPEX!$B$21*(1+Inputs!$H$28)^(F6-1) -> 37774219 | G31: =OPEX!$B$21*(1+Inputs!$H$28)^(G6-1) -> 37774219 | H31: =OPEX!$B$21*(1+Inputs!$H$28)^(H6-1) -> 37774219 | I31: =OPEX!$B$21*(1+Inputs!$H$28)^(I6-1) -> 37774219 | J31: =OPEX!$B$21*(1+Inputs!$H$28)^(J6-1) -> 37774219 | ... O31: =OPEX!$B$21*(1+Inputs!$H$28)^(O6-1) -> 40040672
A32: Service charge / CAM | C32: =OPEX!$B$22*C12 -> 0 | D32: =OPEX!$B$22*D12 -> 0 | E32: =OPEX!$B$22*E12 -> 0 | F32: =OPEX!$B$22*F12 -> 0 | G32: =OPEX!$B$22*G12 -> 0 | H32: =OPEX!$B$22*H12 -> 0 | I32: =OPEX!$B$22*I12 -> 0 | J32: =OPEX!$B$22*J12 -> 0 | ... O32: =OPEX!$B$22*O12 -> 0
A33: Utilities | C33: =OPEX!$B$18*C12 -> 19002300 | D33: =OPEX!$B$18*D12 -> 19002300 | E33: =OPEX!$B$18*E12 -> 19002300 | F33: =OPEX!$B$18*F12 -> 19002300 | G33: =OPEX!$B$18*G12 -> 19002300 | H33: =OPEX!$B$18*H12 -> 19002300 | I33: =OPEX!$B$18*I12 -> 19002300 | J33: =OPEX!$B$18*J12 -> 19002300 | ... O33: =OPEX!$B$18*O12 -> 19667380
A34: Fixed overheads (+ equipment lease/rental/sponsor payments in Lease mode) | C34: =OPEX!$B$13*C12+IF(Inputs!$H$4=2,SUMPRODUCT(('CAPEX (Rent)'!$V$8:$V$25>=C$4)*'CAPEX (Rent)'!$U$8:$U$25),0) -> 67483150 | D34: =OPEX!$B$13*D12+IF(Inputs!$H$4=2,SUMPRODUCT(('CAPEX (Rent)'!$V$8:$V$25>=D$4)*'CAPEX (Rent)'!$U$8:$U$25),0) -> 67483150 | E34: =OPEX!$B$13*E12+IF(Inputs!$H$4=2,SUMPRODUCT(('CAPEX (Rent)'!$V$8:$V$25>=E$4)*'CAPEX (Rent)'!$U$8:$U$25),0) -> 67483150 | F34: =OPEX!$B$13*F12+IF(Inputs!$H$4=2,SUMPRODUCT(('CAPEX (Rent)'!$V$8:$V$25>=F$4)*'CAPEX (Rent)'!$U$8:$U$25),0) -> 67483150 | G34: =OPEX!$B$13*G12+IF(Inputs!$H$4=2,SUMPRODUCT(('CAPEX (Rent)'!$V$8:$V$25>=G$4)*'CAPEX (Rent)'!$U$8:$U$25),0) -> 67483150 | H34: =OPEX!$B$13*H12+IF(Inputs!$H$4=2,SUMPRODUCT(('CAPEX (Rent)'!$V$8:$V$25>=H$4)*'CAPEX (Rent)'!$U$8:$U$25),0) -> 67483150 | I34: =OPEX!$B$13*I12+IF(Inputs!$H$4=2,SUMPRODUCT(('CAPEX (Rent)'!$V$8:$V$25>=I$4)*'CAPEX (Rent)'!$U$8:$U$25),0) -> 67483150 | J34: =OPEX!$B$13*J12+IF(Inputs!$H$4=2,SUMPRODUCT(('CAPEX (Rent)'!$V$8:$V$25>=J$4)*'CAPEX (Rent)'!$U$8:$U$25),0) -> 67483150 | ... O34: =OPEX!$B$13*O12+IF(Inputs!$H$4=2,SUMPRODUCT(('CAPEX (Rent)'!$V$8:$V$25>=O$4)*'CAPEX (Rent)'!$U$8:$U$25),0) -> 69198150
A35: EBITDA | B35: EBITDA | C35: =C28-SUM(C30:C34) -> -56892701 | D35: =D28-SUM(D30:D34) -> -32932829 | E35: =E28-SUM(E30:E34) -> -8972957.9 | F35: =F28-SUM(F30:F34) -> 14986913 | G35: =G28-SUM(G30:G34) -> 38946785 | H35: =H28-SUM(H30:H34) -> 90651006 | I35: =I28-SUM(I30:I34) -> 86866528 | J35: =J28-SUM(J30:J34) -> 79327175 | ... O35: =O28-SUM(O30:O34) -> 1.3682961e+08
A36: EBITDA margin | C36: =IFERROR(C35/C18,0) -> -0.1406159 | D36: =IFERROR(D35/D18,0) -> -0.07384445 | E36: =IFERROR(E35/E18,0) -> -0.018411548 | F36: =IFERROR(F35/F18,0) -> 0.028344899 | G36: =IFERROR(G35/G18,0) -> 0.06831412 | H36: =IFERROR(H35/H18,0) -> 0.137472 | I36: =IFERROR(I35/I18,0) -> 0.133053 | J36: =IFERROR(J35/J18,0) -> 0.12397908 | ... O36: =IFERROR(O35/O18,0) -> 0.17884933
A37: Depreciation | C37: =IF(C4<=Inputs!$H$81*12,CHOOSE(Inputs!$H$4,'CAPEX (Buy)'!$H$42,'CAPEX (Rent)'!$H$45)/(Inputs!$H$81*12),0) -> 29497325 | D37: =IF(D4<=Inputs!$H$81*12,CHOOSE(Inputs!$H$4,'CAPEX (Buy)'!$H$42,'CAPEX (Rent)'!$H$45)/(Inputs!$H$81*12),0) -> 29497325 | E37: =IF(E4<=Inputs!$H$81*12,CHOOSE(Inputs!$H$4,'CAPEX (Buy)'!$H$42,'CAPEX (Rent)'!$H$45)/(Inputs!$H$81*12),0) -> 29497325 | F37: =IF(F4<=Inputs!$H$81*12,CHOOSE(Inputs!$H$4,'CAPEX (Buy)'!$H$42,'CAPEX (Rent)'!$H$45)/(Inputs!$H$81*12),0) -> 29497325 | G37: =IF(G4<=Inputs!$H$81*12,CHOOSE(Inputs!$H$4,'CAPEX (Buy)'!$H$42,'CAPEX (Rent)'!$H$45)/(Inputs!$H$81*12),0) -> 29497325 | H37: =IF(H4<=Inputs!$H$81*12,CHOOSE(Inputs!$H$4,'CAPEX (Buy)'!$H$42,'CAPEX (Rent)'!$H$45)/(Inputs!$H$81*12),0) -> 29497325 | I37: =IF(I4<=Inputs!$H$81*12,CHOOSE(Inputs!$H$4,'CAPEX (Buy)'!$H$42,'CAPEX (Rent)'!$H$45)/(Inputs!$H$81*12),0) -> 29497325 | J37: =IF(J4<=Inputs!$H$81*12,CHOOSE(Inputs!$H$4,'CAPEX (Buy)'!$H$42,'CAPEX (Rent)'!$H$45)/(Inputs!$H$81*12),0) -> 29497325 | ... O37: =IF(O4<=Inputs!$H$81*12,CHOOSE(Inputs!$H$4,'CAPEX (Buy)'!$H$42,'CAPEX (Rent)'!$H$45)/(Inputs!$H$81*12),0) -> 29497325
A38: Interest | C38: =IF(AND(Funding!$B$10>0,C4<=Funding!$B$17),IPMT(Funding!$B$16/12,C4,Funding!$B$17,-Funding!$B$10),0) -> 0 | D38: =IF(AND(Funding!$B$10>0,D4<=Funding!$B$17),IPMT(Funding!$B$16/12,D4,Funding!$B$17,-Funding!$B$10),0) -> 0 | E38: =IF(AND(Funding!$B$10>0,E4<=Funding!$B$17),IPMT(Funding!$B$16/12,E4,Funding!$B$17,-Funding!$B$10),0) -> 0 | F38: =IF(AND(Funding!$B$10>0,F4<=Funding!$B$17),IPMT(Funding!$B$16/12,F4,Funding!$B$17,-Funding!$B$10),0) -> 0 | G38: =IF(AND(Funding!$B$10>0,G4<=Funding!$B$17),IPMT(Funding!$B$16/12,G4,Funding!$B$17,-Funding!$B$10),0) -> 0 | H38: =IF(AND(Funding!$B$10>0,H4<=Funding!$B$17),IPMT(Funding!$B$16/12,H4,Funding!$B$17,-Funding!$B$10),0) -> 0 | I38: =IF(AND(Funding!$B$10>0,I4<=Funding!$B$17),IPMT(Funding!$B$16/12,I4,Funding!$B$17,-Funding!$B$10),0) -> 0 | J38: =IF(AND(Funding!$B$10>0,J4<=Funding!$B$17),IPMT(Funding!$B$16/12,J4,Funding!$B$17,-Funding!$B$10),0) -> 0 | ... O38: =IF(AND(Funding!$B$10>0,O4<=Funding!$B$17),IPMT(Funding!$B$16/12,O4,Funding!$B$17,-Funding!$B$10),0) -> 0
A39: Profit before tax | C39: =C35-C37-C38 -> -86390026 | D39: =D35-D37-D38 -> -62430154 | E39: =E35-E37-E38 -> -38470283 | F39: =F35-F37-F38 -> -14510412 | G39: =G35-G37-G38 -> 9449459.8 | H39: =H35-H37-H38 -> 61153681 | I39: =I35-I37-I38 -> 57369203 | J39: =J35-J37-J38 -> 49829850 | ... O39: =O35-O37-O38 -> 1.0733229e+08
A40: Cumulative profit before tax (loss carry-forward helper) | C40: =SUM($C39:C39) -> -86390026 | D40: =SUM($C39:D39) -> -1.4882018e+08 | E40: =SUM($C39:E39) -> -1.8729046e+08 | F40: =SUM($C39:F39) -> -2.0180087e+08 | G40: =SUM($C39:G39) -> -1.9235141e+08 | H40: =SUM($C39:H39) -> -1.3119773e+08 | I40: =SUM($C39:I39) -> -73828531 | J40: =SUM($C39:J39) -> -23998681 | ... O40: =SUM($C39:O39) -> 4.8362897e+08
A41: Corporate income tax (on cumulative profit) | C41: =MAX(0,C40*Inputs!$H$16-0) -> 0 | D41: =MAX(0,D40*Inputs!$H$16-SUM($C$41:C$41)) -> 0 | E41: =MAX(0,E40*Inputs!$H$16-SUM($C$41:D$41)) -> 0 | F41: =MAX(0,F40*Inputs!$H$16-SUM($C$41:E$41)) -> 0 | G41: =MAX(0,G40*Inputs!$H$16-SUM($C$41:F$41)) -> 0 | H41: =MAX(0,H40*Inputs!$H$16-SUM($C$41:G$41)) -> 0 | I41: =MAX(0,I40*Inputs!$H$16-SUM($C$41:H$41)) -> 0 | J41: =MAX(0,J40*Inputs!$H$16-SUM($C$41:I$41)) -> 0 | K41: =MAX(0,K40*Inputs!$H$16-SUM($C$41:J$41)) -> 13294567 | ... O41: =MAX(0,O40*Inputs!$H$16-SUM($C$41:N$41)) -> 23613103
A42: NET INCOME | C42: =C39-C41 -> -86390026 | D42: =D39-D41 -> -62430154 | E42: =E39-E41 -> -38470283 | F42: =F39-F41 -> -14510412 | G42: =G39-G41 -> 9449459.8 | H42: =H39-H41 -> 61153681 | I42: =I39-I41 -> 57369203 | J42: =J39-J41 -> 49829850 | ... O42: =O39-O41 -> 83719185
A43: CASH FLOW
